Workbook

Sheet INDEX
A1: Excel Intermediate to Advanced for Reporting & Analysis — Practice Workbook
A2: Adamjee Assurance Company Limited | One Day Training | 9:00 AM – 5:00 PM | Microsoft Excel 2016 | 63 problems, 63 datasets
A4: How to use: every topic has two sheets — a DATA sheet (the Adamjee dataset) and a TASK sheet (the problem statement plus a yellow area where you build your answer). Click a link below to jump.
A6: Topic | B6: Title | C6: Dataset | D6: Report Template
A7: Session 1: Advanced Lookup, Text & Date Functions
A8: 1.1 | B8: VLOOKUP with Approximate Match and Wildcards | C8: 1.1 Data | D8: 1.1 Report
A9: 1.2 | B9: HLOOKUP for Horizontal Data Tables | C9: 1.2 Data | D9: 1.2 Report
A10: 1.3 | B10: INDEX and MATCH (Single Criteria Lookup) | C10: 1.3 Data | D10: 1.3 Report
A11: 1.4 | B11: INDEX and MATCH (Two-Way Lookup) | C11: 1.4 Data | D11: 1.4 Report
A12: 1.5 | B12: INDEX and MATCH with Multiple Criteria (Array Formula, Ctrl+Shift+Enter) | C12: 1.5 Data | D12: 1.5 Report
A13: 1.6 | B13: OFFSET with MATCH for Dynamic Lookups | C13: 1.6 Data | D13: 1.6 Report
A14: 1.7 | B14: Handling Lookup Errors with IFERROR and IFNA | C14: 1.7 Data | D14: 1.7 Report
A15: 1.8 | B15: LEFT, RIGHT, MID | C15: 1.8 Data | D15: 1.8 Report
A16: 1.9 | B16: FIND and SEARCH | C16: 1.9 Data | D16: 1.9 Report
A17: 1.10 | B17: LEN, TRIM, CLEAN | C17: 1.10 Data | D17: 1.10 Report
A18: 1.11 | B18: SUBSTITUTE and REPLACE | C18: 1.11 Data | D18: 1.11 Report
A19: 1.12 | B19: CONCATENATE and the Ampersand (&) Operator | C19: 1.12 Data | D19: 1.12 Report
... A24: 1.17 | B24: Complex Date Calculations for Policy Lifecycle and Renewal Tracking | C24: 1.17 Data | D24: 1.17 Report
A25: Session 2: Array Formulas, Advanced Logic & Named Ranges
A26: 2.1 | B26: Understanding Array Formulas in Excel 2016 | C26: 2.1 Data | D26: 2.1 Report
A27: 2.2 | B27: Single-Cell Array Formulas for Multi-Criteria Calculations | C27: 2.2 Data | D27: 2.2 Report
A28: 2.3 | B28: Multi-Cell Array Formulas | C28: 2.3 Data | D28: 2.3 Report
A29: 2.4 | B29: SUM with IF Array for Conditional Totals | C29: 2.4 Data | D29: 2.4 Report
A30: 2.5 | B30: COUNT and AVERAGE with Array Conditions | C30: 2.5 Data | D30: 2.5 Report
A31: 2.6 | B31: Nested IF (Advanced Multi-Level Logic) | C31: 2.6 Data | D31: 2.6 Report
A32: 2.7 | B32: AND, OR Combined with IF | C32: 2.7 Data | D32: 2.7 Report
A33: 2.8 | B33: CHOOSE Function | C33: 2.8 Data | D33: 2.8 Report
A34: 2.9 | B34: SUMPRODUCT for Multi-Criteria Summing and Counting | C34: 2.9 Data | D34: 2.9 Report
A35: 2.10 | B35: SUMIFS, COUNTIFS, AVERAGEIFS (Multiple Criteria) | C35: 2.10 Data | D35: 2.10 Report
A36: 2.11 | B36: AGGREGATE Function (Ignoring Errors and Hidden Rows) | C36: 2.11 Data | D36: 2.11 Report
A37: 2.12 | B37: Creating and Managing Named Ranges | C37: 2.12 Data | D37: 2.12 Report
... A40: 2.15 | B40: INDIRECT Function for Dynamic References | C40: 2.15 Data | D40: 2.15 Report
A41: Session 3: Advanced Pivot Tables, Power Query & What-If Analysis
A42: 3.1 | B42: Calculated Fields and Calculated Items | C42: 3.1 Data | D42: 3.1 Report
A43: 3.2 | B43: Grouping Data (Dates by Month/Quarter/Year, Numbers, Text) | C43: 3.2 Data | D43: 3.2 Report
A44: 3.3 | B44: Show Values As (% of Grand Total, % of Parent, Running Total, Difference From) | C44: 3.3 Data | D44: 3.3 Report
A45: 3.4 | B45: Slicers and Timelines Connected to Multiple Pivot Tables | C45: 3.4 Data | D45: 3.4 Report
A46: 3.5 | B46: Pivot Table from Multiple Sheets Using Consolidation | C46: 3.5 Data | D46: 3.5 Report
A47: 3.6 | B47: Conditional Formatting Applied to Pivot Tables | C47: 3.6 Data | D47: 3.6 Report
A48: 3.7 | B48: Accessing Get & Transform from the Data Tab in Excel 2016 | C48: 3.7 Data | D48: 3.7 Report
A49: 3.8 | B49: Importing Data from Excel, CSV and Folder Sources | C49: 3.8 Data | D49: 3.8 Report
A50: 3.9 | B50: Transforming Data (Split Columns, Merge Columns, Replace Values, Change Data Types) | C50: 3.9 Data | D50: 3.9 Report
A51: 3.10 | B51: Unpivoting Data for Report-Ready Format | C51: 3.10 Data | D51: 3.10 Report
A52: 3.11 | B52: Merging and Appending Queries | C52: 3.11 Data | D52: 3.11 Report
A53: 3.12 | B53: Loading Results to Worksheet or Pivot Table | C53: 3.12 Data | D53: 3.12 Report
... A57: 3.16 | B57: Scenario Manager (Best Case, Worst Case, Base Case Modelling) | C57: 3.16 Data | D57: 3.16 Report
A58: Session 4: Advanced Charts, Macros & Workbook Management
A59: 4.1 | B59: Combo Charts (Column and Line on Secondary Axis) | C59: 4.1 Data | D59: 4.1 Report
A60: 4.2 | B60: Sparklines (Line, Column, Win/Loss) | C60: 4.2 Data | D60: 4.2 Report
A61: 4.3 | B61: Waterfall Charts (Premium vs Claims Reconciliation) | C61: 4.3 Data | D61: 4.3 Report
A62: 4.4 | B62: Dynamic Charts Using Named Ranges and OFFSET | C62: 4.4 Data | D62: 4.4 Report
A63: 4.5 | B63: Formatting Charts for Executive Presentations | C63: 4.5 Data | D63: 4.5 Report
A64: 4.6 | B64: Enabling the Developer Tab | C64: 4.6 Data | D64: 4.6 Report
A65: 4.7 | B65: Recording a Macro (Formatting, Sorting, Report Generation) | C65: 4.7 Data | D65: 4.7 Report
A66: 4.8 | B66: Running Macros and Assigning Macros to Buttons | C66: 4.8 Data | D66: 4.8 Report
A67: 4.9 | B67: Viewing and Editing Basic VBA Code in the Visual Basic Editor | C67: 4.9 Data | D67: 4.9 Report
A68: 4.10 | B68: Macro Security Settings and Trusted Locations | C68: 4.10 Data | D68: 4.10 Report
A69: 4.11 | B69: Formula Auditing Tools (Trace Precedents, Trace Dependents, Evaluate Formula, Error Checking) | C69: 4.11 Data | D69: 4.11 Report
A70: 4.12 | B70: Advanced Worksheet and Workbook Protection | C70: 4.12 Data | D70: 4.12 Report
... A73: 4.15 | B73: Q&A and Key Takeaways — Capstone Challenge | C73: 4.15 Data | D73: 4.15 Report

Sheet 1.1 Data
A1: Dataset 1.1 — VLOOKUP with Approximate Match and Wildcards
A2: Session 1: Advanced Lookup, Text & Date Functions | Part A: Advanced Lookup Functions | Adamjee Assurance Company Limited (Pakistan) — training data, figures in PKR
A4: Table A — Motor Own-Damage Banded Rate Card (ascending order required)
A5: Sum Insured From (PKR) | B5: Band | C5: Rate Applied | D5: No-Claim Discount
A6: 0 | B6: Band E | C6: 0.0285 | D6: 0
A7: 2000000 | B7: Band D | C7: 0.024 | D7: 0.05
A8: 5000000 | B8: Band C | C8: 0.0195 | D8: 0.075
A9: 10000000 | B9: Band B | C9: 0.016 | D9: 0.1
A10: 25000000 | B10: Band A | C10: 0.0125 | D10: 0.15
A11: 50000000 | B11: Band A+ | C11: 0.0095 | D11: 0.2
A13: Table B — Quotation Requests received at Karachi Main (UW Desk)
A14: Quote Ref | B14: Client Name (as registered) | C14: Client Code | D14: Vehicle / Asset | E14: Sum Insured (PKR)
A15: QT-2024-0451 | B15: Gul Ahmed Textile Mills Ltd | C15: KHI-CORP-0100 | D15: Toyota Hilux Revo 2023 | E15: 8450000
A16: QT-2024-0452 | B16: Lucky Cement Limited | C16: KHI-CORP-0102 | D16: Fleet – 6 x Suzuki Bolan | E16: 4320000
A17: QT-2024-0453 | B17: Ahmed Raza Qureshi | C17: KHI-INDV-0107 | D17: Honda Civic Oriel 2022 | E17: 6900000
A18: QT-2024-0454 | B18: Indus Motor Company Ltd | C18: KHI-CORP-0110 | D18: Executive fleet – 4 x Fortuner | E18: 34800000
A19: QT-2024-0455 | B19: Fatima Siddiqui | C19: LHR-INDV-0113 | D19: Suzuki Alto VXL 2024 | E19: 1950000
A20: QT-2024-0456 | B20: Interloop Limited | C20: FSD-CORP-0118 | D20: Staff transport buses – 3 units | E20: 22500000
A21: QT-2024-0457 | B21: K-Electric Limited | C21: KHI-CORP-0121 | D21: Utility fleet – 18 vehicles | E21: 61200000
A22: QT-2024-0458 | B22: Bilal Ahmed Khan | C22: ISB-INDV-0125 | D22: Kia Sportage AWD 2023 | E22: 9990000
A24: Table C — Partial names typed by the call centre (wildcard search list)
A25: Search Text Entered | B25: What the agent meant
A26: Gul Ahmed* | B26: Any client starting with Gul Ahmed
A27: *Cement* | B27: Any client containing Cement
A28: Interloop?Limited | B28: One unknown character between the two words
A29: *Electric* | B29: Any client containing Electric
A31: Note: This is simulated training data modelled on Adamjee Assurance general insurance operations. It is not actual company data.

Sheet 1.1 Report
A1: ADAMJEE ASSURANCE COMPANY LIMITED
A2: Motor Quotation Register — 8 quotes priced today
A3: Prepared for: | B3: Head of Motor Underwriting, Karachi Main
A4: Prepared by:
A5: Reporting date: | B5: As at reporting date shown on the dataset
A7: Eight quotation requests arrived this morning and the broker has promised all eight clients a price before close of business. The rate card is banded by sum insured and none of the eight sums insured lands exactly on a band edge. The junior underwriter priced three of them by eye yesterday and got two wrong.
A9: Source data: '1.1 Data' (click to open)
A11: Navy headers below = data linked live from the dataset sheet. Gold headers = blank — build your formula here.
A12: Quote Ref | B12: Client Name | C12: Sum Insured | D12: Band | E12: Rate Applied | F12: No-Claim Discount | G12: Gross Premium
A13: ='1.1 Data'!A15 | B13: ='1.1 Data'!B15 | C13: ='1.1 Data'!E15
A14: ='1.1 Data'!A16 | B14: ='1.1 Data'!B16 | C14: ='1.1 Data'!E16
A15: ='1.1 Data'!A17 | B15: ='1.1 Data'!B17 | C15: ='1.1 Data'!E17
A16: ='1.1 Data'!A18 | B16: ='1.1 Data'!B18 | C16: ='1.1 Data'!E18
A17: ='1.1 Data'!A19 | B17: ='1.1 Data'!B19 | C17: ='1.1 Data'!E19
A18: ='1.1 Data'!A20 | B18: ='1.1 Data'!B20 | C18: ='1.1 Data'!E20
A19: ='1.1 Data'!A21 | B19: ='1.1 Data'!B21 | C19: ='1.1 Data'!E21
A20: ='1.1 Data'!A22 | B20: ='1.1 Data'!B22 | C20: ='1.1 Data'!E22
A21: TOTAL / RESULT
A23: HOW TO WORK: navy-header columns are linked live from the dataset sheet — click any cell to see the formula. Gold-header columns are blank and shaded yellow — build the required formula there and copy it down every row, then complete the TOTAL / RESULT row at the foot.
A25: FURTHER REQUESTS ON THIS DATASET
A26: # | B26: Request | C26: Requested by | D26: Report / figure required | E26: Your formula or answer
A27: 1 | B27: Rate Card Sensitivity Note for the Underwriting Committee | C27: Chief Underwriting Officer | D27: A two-column comparison: Quote Ref | Premium at current rates | Premium at rates +0.25% | Difference | % change. One total line. The band rates must sit in cells so the Committee can type a new rate and watch the whole schedule move.
A28: 2 | B28: Call Centre Client Lookup — partial names | C28: Manager, Customer Contact Centre | D28: A lookup panel with the four search patterns down the side and these columns: Search Text | Client Name Matched | Client Code | Sum Insured on file. One formula copied down all four rows — the agent types a new pattern in the search cell and the answers appear.
A29: 3 | B29: Underwriting Exception Report — borderline sums insured | C29: Chief Underwriting Officer | D29: An exception list showing: Quote Ref | Sum Insured | Band applied | Distance to the next band up (PKR) | Flag 'Near boundary' where within 10%. Sorted with the closest to a boundary first.
A30: 4 | B30: Handover note for the new underwriting assistant | C30: Head of Motor Underwriting | D30: A five-line written note, in the yellow box, explaining: why the rate card must stay sorted ascending, what the 4th argument of VLOOKUP does, and what to check if a premium comes out obviously wrong.

Sheet 1.2 Data
A1: Dataset 1.2 — HLOOKUP for Horizontal Data Tables
A2: Session 1: Advanced Lookup, Text & Date Functions | Part A: Advanced Lookup Functions | Adamjee Assurance Company Limited (Pakistan) — training data, figures in PKR
A4: Table A — Gross Written Premium by Branch, 2024 (months across the top)
A5: Branch | B5: Jan-2024 | C5: Feb-2024 | D5: Mar-2024 | E5: Apr-2024 | F5: May-2024 | G5: Jun-2024 | H5: Jul-2024 | I5: Aug-2024 | J5: Sep-2024 | K5: Oct-2024 | L5: Nov-2024 | M5: Dec-2024
A6: Karachi Main | B6: 8478000 | C6: 5658000 | D6: 13810000 | E6: 4380000 | F6: 11934000 | G6: 9160000 | H6: 4145000 | I6: 11471000 | J6: 3811000 | K6: 10268000 | L6: 4338000 | M6: 4678000
A7: Lahore Gulberg | B7: 10119000 | C7: 16677000 | D7: 5217000 | E7: 6838000 | F7: 13427000 | G7: 18647000 | H7: 12606000 | I7: 9665000 | J7: 19112000 | K7: 3959000 | L7: 17193000 | M7: 7920000
A8: Islamabad Blue Area | B8: 5551000 | C8: 5120000 | D8: 8228000 | E8: 16502000 | F8: 6145000 | G8: 12680000 | H8: 13614000 | I8: 9270000 | J8: 12128000 | K8: 4223000 | L8: 4171000 | M8: 6557000
A9: Faisalabad | B9: 14290000 | C9: 10169000 | D9: 8320000 | E9: 12744000 | F9: 10586000 | G9: 8086000 | H9: 16148000 | I9: 14593000 | J9: 7178000 | K9: 12563000 | L9: 11760000 | M9: 17464000
A10: Multan | B10: 15089000 | C10: 7893000 | D10: 19176000 | E10: 5124000 | F10: 10015000 | G10: 15541000 | H10: 5677000 | I10: 11170000 | J10: 3839000 | K10: 14091000 | L10: 15662000 | M10: 12540000
A11: Peshawar | B11: 17470000 | C11: 8314000 | D11: 14533000 | E11: 12888000 | F11: 12652000 | G11: 10636000 | H11: 16891000 | I11: 18598000 | J11: 10927000 | K11: 14025000 | L11: 4188000 | M11: 14634000
A13: Table B — Claims Paid by Branch, 2024 (same horizontal layout)
A14: Branch | B14: Jan-2024 | C14: Feb-2024 | D14: Mar-2024 | E14: Apr-2024 | F14: May-2024 | G14: Jun-2024 | H14: Jul-2024 | I14: Aug-2024 | J14: Sep-2024 | K14: Oct-2024 | L14: Nov-2024 | M14: Dec-2024
A15: Karachi Main | B15: 7738000 | C15: 8827000 | D15: 6156000 | E15: 6066000 | F15: 4874000 | G15: 10967000 | H15: 3822000 | I15: 2397000 | J15: 3536000 | K15: 3530000 | L15: 4206000 | M15: 3605000
A16: Lahore Gulberg | B16: 1987000 | C16: 4187000 | D16: 4041000 | E16: 6649000 | F16: 2936000 | G16: 1614000 | H16: 2945000 | I16: 6378000 | J16: 4824000 | K16: 8308000 | L16: 9010000 | M16: 5085000
A17: Islamabad Blue Area | B17: 1903000 | C17: 8252000 | D17: 8532000 | E17: 4900000 | F17: 7548000 | G17: 3920000 | H17: 10140000 | I17: 9321000 | J17: 8898000 | K17: 10534000 | L17: 3251000 | M17: 6407000
A18: Faisalabad | B18: 8286000 | C18: 8994000 | D18: 4841000 | E18: 2299000 | F18: 7225000 | G18: 1956000 | H18: 8024000 | I18: 970000 | J18: 5490000 | K18: 5745000 | L18: 2109000 | M18: 5749000
A19: Multan | B19: 5950000 | C19: 4627000 | D19: 9952000 | E19: 9647000 | F19: 9894000 | G19: 3373000 | H19: 1161000 | I19: 4703000 | J19: 2047000 | K19: 8022000 | L19: 3555000 | M19: 2196000
A20: Peshawar | B20: 3765000 | C20: 4974000 | D20: 8327000 | E20: 5556000 | F20: 3941000 | G20: 7741000 | H20: 1357000 | I20: 3012000 | J20: 7843000 | K20: 8495000 | L20: 1923000 | M20: 1571000
A22: Table C — Report request parameters
A23: Parameter | B23: Value
A24: Reporting Month | B24: Sep-2024
A25: Branch under review | B25: Lahore Gulberg
A26: Comparison Month | B26: Mar-2024
A28: Note: This is simulated training data modelled on Adamjee Assurance general insurance operations. It is not actual company data.

Sheet 1.2 Report
A1: ADAMJEE ASSURANCE COMPANY LIMITED
A2: September Branch Premium Flash Report
A3: Prepared for: | B3: Chief Financial Officer
A4: Prepared by:
A5: Reporting date: | B5: As at reporting date shown on the dataset
A7: Finance publishes the monthly GWP file with months running across the top and refuses to change the layout. The CFO wants a one-page flash for September that pulls from that file automatically, because last month someone copied the August column by mistake and the flash went out with the wrong figures.
A9: Source data: '1.2 Data' (click to open)
A11: DELIVERABLE CHECKLIST
A12: # | B12: Deliverable | C12: Report specification | D12: Requested by | E12: Done?
A13: 1 | B13: September Branch Premium Flash Report | C13: A flash report block: Reporting Month (input cell) | Branch (input cell) | GWP | Claims Paid | Loss Ratio. All four output cells must be formulas driven by the two input cells — typing 'Oct-2024' into the month cell must refresh the entire block. | D13: Chief Financial Officer
A14: 2 | B14: Branch League Table for the Monday management call | C14: A league table with one row per branch and these columns: Branch | GWP for the selected month | Claims Paid | Loss Ratio | Rank by GWP. Driven by a single month input cell. Loss ratio formatted 0.0%. | D14: Regional Head — South
A15: 3 | B15: Month-on-Month Variance Commentary Pack | C15: A variance block: Branch | GWP Reporting Month | GWP Comparison Month | Variance (PKR) | Variance % | Direction (Up/Down/Flat). Both month names come from parameter cells. | D15: Head of Management Reporting
A16: 4 | B16: Layout risk memo to the Finance systems team | C16: A short memo, in the yellow box, stating: which formula broke, why a hard-coded row_num is fragile, the one-line fix, and when INDEX/MATCH should be used instead of HLOOKUP altogether. | D16: Head of Internal Audit
A18: BUILD YOUR REPORT / OUTPUT BELOW (pivot, chart, macro output, or model — as required above)
A34: HOW TO WORK: build the requested output in the blank area above (or insert a pivot table / chart / macro-driven control here), tick each deliverable off in the checklist, and record any formula or setting worth remembering in the specification column.

Sheet 1.3 Data
A1: Dataset 1.3 — INDEX and MATCH (Single Criteria Lookup)
A2: Session 1: Advanced Lookup, Text & Date Functions | Part A: Advanced Lookup Functions | Adamjee Assurance Company Limited (Pakistan) — training data, figures in PKR
A4: Table A — Policy Master Extract (Client Code deliberately placed left of Policy No)
A5: Client Code | B5: Policy No | C5: Client Name | D5: Branch | E5: Product | F5: Expiry Date | G5: Sum Insured (PKR) | H5: Gross Premium (PKR)
A6: KHI-CORP-0100 | B6: ADM-FIR-KHI-2024-1001 | C6: Gul Ahmed Textile Mills Ltd | D6: Karachi Main | E6: Fire & Property | F6: 45896 | G6: 4500000 | H6: 96000
A7: LHR-CORP-0101 | B7: ADM-TRV-LHR-2024-1002 | C7: Packages Limited | D7: Lahore Gulberg | E7: Travel | F7: 45865 | G7: 12000000 | H7: 201000
A8: ISB-INDV-0102 | B8: ADM-MTR-ISB-2024-1003 | C8: Bilal Ahmed Khan | D8: Islamabad Blue Area | E8: Motor | F8: 45868 | G8: 65000000 | H8: 1397000
A9: FSD-CORP-0103 | B9: ADM-HLT-FSD-2024-1004 | C9: Attock Refinery Limited | D9: Faisalabad | E9: Health | F9: 45934 | G9: 18500000 | H9: 305000
A10: MUL-CORP-0104 | B10: ADM-MSC-MUL-2024-1005 | C10: Descon Engineering Ltd | D10: Multan | E10: Miscellaneous | F10: 45895 | G10: 4500000 | H10: 75000
A11: PEW-INDV-0105 | B11: ADM-MAR-PEW-2024-1006 | C11: Hina Farooq | D11: Peshawar | E11: Marine Cargo | F11: 45834 | G11: 25000000 | H11: 380000
A12: QTA-CORP-0106 | B12: ADM-ENG-QTA-2024-1007 | C12: Indus Motor Company Ltd | D12: Quetta | E12: Engineering | F12: 45855 | G12: 18500000 | H12: 227000
A13: HYD-CORP-0107 | B13: ADM-FIR-HYD-2024-1008 | C13: Nishat Mills Limited | D13: Hyderabad | E13: Fire & Property | F13: 45874 | G13: 25000000 | H13: 290000
A14: SKT-INDV-0108 | B14: ADM-TRV-SKT-2024-1009 | C14: Imran Aslam Sheikh | D14: Sialkot | E14: Travel | F14: 45773 | G14: 7500000 | H14: 37000
A15: RWP-CORP-0109 | B15: ADM-MTR-RWP-2024-1010 | C15: Engro Polymer & Chemicals | D15: Rawalpindi | E15: Motor | F15: 45788 | G15: 65000000 | H15: 760000
A16: KHI-CORP-0110 | B16: ADM-HLT-KHI-2024-1011 | C16: Interloop Limited | D16: Karachi Main | E16: Health | F16: 45871 | G16: 90000000 | H16: 603000
A17: LHR-INDV-0111 | B17: ADM-MSC-LHR-2024-1012 | C17: Mehwish Anwar | D17: Lahore Gulberg | E17: Miscellaneous | F17: 45776 | G17: 40000000 | H17: 512000
... A25: RWP-CORP-0119 | B25: ADM-MAR-RWP-2024-1020 | C25: Thal Limited | D25: Rawalpindi | E25: Marine Cargo | F25: 45868 | G25: 7500000 | H25: 181000
A27: Table B — Servicing queue (policy numbers received from branches)
A28: Query Ref | B28: Policy No | C28: Query Type
A29: SRV-1001 | B29: ADM-HLT-FSD-2024-1004 | C29: Premium confirmation
A30: SRV-1002 | B30: ADM-MSC-LHR-2024-1012 | C30: Expiry confirmation
A31: SRV-1003 | B31: ADM-FIR-HYD-2024-1008 | C31: Client code required
A32: SRV-1004 | B32: ADM-MSC-SKT-2024-1019 | C32: Branch transfer
A33: SRV-1005 | B33: ADM-FIR-KHI-2024-1001 | C33: Sum insured endorsement
A35: Note: This is simulated training data modelled on Adamjee Assurance general insurance operations. It is not actual company data.

Sheet 1.3 Report
A1: ADAMJEE ASSURANCE COMPANY LIMITED
A2: Policy Servicing Queue — daily response file
A3: Prepared for: | B3: Manager, Policy Servicing
A4: Prepared by:
A5: Reporting date: | B5: As at reporting date shown on the dataset
A7: Five branch queries came in overnight, each quoting only a policy number. The team currently opens the master file and scrolls to each one by hand, which takes about ten minutes per query and is the main reason the 24-hour service standard was missed eleven times last month.
A9: Source data: '1.3 Data' (click to open)
A11: Navy headers below = data linked live from the dataset sheet. Gold headers = blank — build your formula here.
A12: Query Ref | B12: Policy No | C12: Client Name | D12: Client Code | E12: Branch | F12: Expiry Date | G12: Sum Insured | H12: Gross Premium
A13: ='1.3 Data'!A29 | B13: ='1.3 Data'!B29
A14: ='1.3 Data'!A30 | B14: ='1.3 Data'!B30
A15: ='1.3 Data'!A31 | B15: ='1.3 Data'!B31
A16: ='1.3 Data'!A32 | B16: ='1.3 Data'!B32
A17: ='1.3 Data'!A33 | B17: ='1.3 Data'!B33
A18: TOTAL / RESULT
A20: HOW TO WORK: navy-header columns are linked live from the dataset sheet — click any cell to see the formula. Gold-header columns are blank and shaded yellow — build the required formula there and copy it down every row, then complete the TOTAL / RESULT row at the foot.
A22: FURTHER REQUESTS ON THIS DATASET
A23: # | B23: Request | C23: Requested by | D23: Report / figure required | E23: Your formula or answer
A24: 1 | B24: Endorsement confirmation letter data | C24: Branch Manager, Karachi Main | D24: A single-row data block feeding the letter: Client Name | Client Code | Policy No | Product | Current Sum Insured | Expiry Date. Each field a formula keyed off the policy number in one cell, so changing that one cell produces the next client's letter.
A25: 2 | B25: Servicing Turnaround Dashboard — named range version | C25: Head of Operations | D25: The same response file rebuilt using named ranges (Policy_No, Client_Name, Gross_Premium and so on) instead of cell addresses, plus a one-line note confirming the results are identical to the address-based version.
A26: 3 | B26: Data integrity check before the file goes back to branches | C26: Head of Internal Audit | D26: A validation column: Match Type Used | Row Position Returned | Status ('Exact match confirmed' or 'Check'). Plus a one-line explanation of what MATCH's third argument was set to and what would happen at 1.

Sheet 1.4 Data
A1: Dataset 1.4 — INDEX and MATCH (Two-Way Lookup)
A2: Session 1: Advanced Lookup, Text & Date Functions | Part A: Advanced Lookup Functions | Adamjee Assurance Company Limited (Pakistan) — training data, figures in PKR
A4: Table A — Gross Written Premium 2024, Branch (rows) x Product (columns), PKR
A5: Branch | B5: Motor | C5: Fire & Property | D5: Marine Cargo | E5: Health | F5: Travel | G5: Engineering | H5: Miscellaneous
A6: Karachi Main | B6: 8344000 | C6: 12892000 | D6: 8101000 | E6: 7888000 | F6: 2473000 | G6: 6011000 | H6: 17784000
A7: Lahore Gulberg | B7: 12007000 | C7: 6810000 | D7: 15984000 | E7: 8354000 | F7: 8703000 | G7: 4393000 | H7: 13413000
A8: Islamabad Blue Area | B8: 13497000 | C8: 9086000 | D8: 4640000 | E8: 9170000 | F8: 15357000 | G8: 18314000 | H8: 5663000
A9: Faisalabad | B9: 22522000 | C9: 19592000 | D9: 13301000 | E9: 23640000 | F9: 3472000 | G9: 12220000 | H9: 7205000
A10: Multan | B10: 2425000 | C10: 5760000 | D10: 4235000 | E10: 9483000 | F10: 11513000 | G10: 18303000 | H10: 21853000
A11: Peshawar | B11: 4046000 | C11: 20673000 | D11: 11464000 | E11: 1358000 | F11: 16554000 | G11: 20109000 | H11: 13079000
A12: Quetta | B12: 17499000 | C12: 18867000 | D12: 5816000 | E12: 20252000 | F12: 12794000 | G12: 16694000 | H12: 23047000
A13: Hyderabad | B13: 12490000 | C13: 10235000 | D13: 11525000 | E13: 6239000 | F13: 2208000 | G13: 17135000 | H13: 11433000
A14: Sialkot | B14: 16248000 | C14: 13181000 | D14: 2928000 | E14: 7310000 | F14: 19592000 | G14: 3867000 | H14: 15522000
A15: Rawalpindi | B15: 13409000 | C15: 9436000 | D15: 8661000 | E15: 19270000 | F15: 15087000 | G15: 12038000 | H15: 18244000
A17: Table B — Claims Paid 2024, Branch (rows) x Product (columns), PKR
A18: Branch | B18: Motor | C18: Fire & Property | D18: Marine Cargo | E18: Health | F18: Travel | G18: Engineering | H18: Miscellaneous
A19: Karachi Main | B19: 11109000 | C19: 11296000 | D19: 3983000 | E19: 5818000 | F19: 11580000 | G19: 7108000 | H19: 3751000
A20: Lahore Gulberg | B20: 1743000 | C20: 3647000 | D20: 7438000 | E20: 12995000 | F20: 10006000 | G20: 6118000 | H20: 10598000
A21: Islamabad Blue Area | B21: 2805000 | C21: 11269000 | D21: 3924000 | E21: 1677000 | F21: 2444000 | G21: 3365000 | H21: 12545000
A22: Faisalabad | B22: 3975000 | C22: 1247000 | D22: 13522000 | E22: 11843000 | F22: 3654000 | G22: 12623000 | H22: 13699000
A23: Multan | B23: 1345000 | C23: 5307000 | D23: 2546000 | E23: 5170000 | F23: 11021000 | G23: 11352000 | H23: 8158000
A24: Peshawar | B24: 10677000 | C24: 6177000 | D24: 8770000 | E24: 3550000 | F24: 698000 | G24: 10846000 | H24: 10732000
A25: Quetta | B25: 5061000 | C25: 7744000 | D25: 6553000 | E25: 12674000 | F25: 5261000 | G25: 1000000 | H25: 3084000
A26: Hyderabad | B26: 1135000 | C26: 10949000 | D26: 6545000 | E26: 11015000 | F26: 1384000 | G26: 239000 | H26: 1306000
A27: Sialkot | B27: 11527000 | C27: 8888000 | D27: 3097000 | E27: 9878000 | F27: 3390000 | G27: 11634000 | H27: 13313000
A28: Rawalpindi | B28: 8216000 | C28: 10831000 | D28: 5962000 | E28: 7486000 | F28: 5498000 | G28: 3874000 | H28: 11521000
A30: Table C — Query cell inputs
A31: Parameter | B31: Value
A32: Branch | B32: Multan
A33: Product | B33: Marine Cargo
A35: Note: This is simulated training data modelled on Adamjee Assurance general insurance operations. It is not actual company data.

Sheet 1.4 Report
A1: ADAMJEE ASSURANCE COMPANY LIMITED
A2: Branch x Product Premium Query Panel
A3: Prepared for: | B3: Regional Head — Central
A4: Prepared by:
A5: Reporting date: | B5: As at reporting date shown on the dataset
A7: The Regional Head keeps a printed Branch x Product grid on his desk and reads the wrong cell about once a week because the grid is seven columns wide and ten rows deep. He has asked for a single query cell instead.
A9: Source data: '1.4 Data' (click to open)
A11: DELIVERABLE CHECKLIST
A12: # | B12: Deliverable | C12: Report specification | D12: Requested by | E12: Done?
A13: 1 | B13: Branch x Product Premium Query Panel | C13: A query panel at the top of the report: two input cells (Branch, Product) and three output cells (GWP, Claims Paid, Loss Ratio). Changing either input must refresh all three outputs. Loss ratio formatted 0.0%. | D13: Regional Head — Central
A14: 2 | B14: Error-proofing the panel before it goes to the Regional Heads | C14: The same panel with: drop-down lists on both input cells sourced from the row and column labels, and every output wrapped so an invalid entry reads 'Not found' rather than an error code. | D14: Head of MIS
A15: 3 | B15: Worst-Performing Product Line — quarterly underwriting review | C15: A ranked table: Product | Total GWP | Total Claims | Loss Ratio | Rank (1 = worst). Plus a single highlighted cell naming the single worst Branch/Product combination in the whole grid and its loss ratio. | D15: Chief Underwriting Officer
A16: 4 | B16: Portfolio Steering Note | C16: A three-line written recommendation in the yellow box naming the two lines, the loss ratio evidence for each, and one sentence on what you would do about it. | D16: Chief Underwriting Officer
A18: BUILD YOUR REPORT / OUTPUT BELOW (pivot, chart, macro output, or model — as required above)
A34: HOW TO WORK: build the requested output in the blank area above (or insert a pivot table / chart / macro-driven control here), tick each deliverable off in the checklist, and record any formula or setting worth remembering in the specification column.

Sheet 1.5 Data
A1: Dataset 1.5 — INDEX and MATCH with Multiple Criteria (Array Formula, Ctrl+Shift+Enter)
A2: Session 1: Advanced Lookup, Text & Date Functions | Part A: Advanced Lookup Functions | Adamjee Assurance Company Limited (Pakistan) — training data, figures in PKR
A4: Table A — Endorsement Register 2024
A5: Policy No | B5: Endorsement Type | C5: Effective Month | D5: Branch | E5: Premium Impact (PKR) | F5: Handled By
A6: ADM-FIR-KHI-2024-1001 | B6: Sum Insured Increase | C6: Jan-2024 | D6: Karachi Main | E6: 185000 | F6: Tariq Jameel
A7: ADM-TRV-LHR-2024-1002 | B7: Vehicle Change | C7: Jan-2024 | D7: Lahore Gulberg | E7: -42000 | F7: Nadia Hassan
A8: ADM-MTR-ISB-2024-1003 | B8: Sum Insured Increase | C8: Feb-2024 | D8: Islamabad Blue Area | E8: 260000 | F8: Salman Shah
A9: ADM-HLT-FSD-2024-1004 | B9: Address Change | C9: Feb-2024 | D9: Faisalabad | E9: 0 | F9: Komal Bashir
A10: ADM-MSC-MUL-2024-1005 | B10: Cancellation Refund | C10: Mar-2024 | D10: Multan | E10: -310000 | F10: Waqar Younis Khan
A11: ADM-MAR-PEW-2024-1006 | B11: Sum Insured Increase | C11: Mar-2024 | D11: Peshawar | E11: 96500 | F11: Amna Zubair
A12: ADM-ENG-QTA-2024-1007 | B12: Add Driver | C12: Apr-2024 | D12: Quetta | E12: 18000 | F12: Rizwan Ali Soomro
A13: ADM-FIR-HYD-2024-1008 | B13: Sum Insured Increase | C13: Apr-2024 | D13: Hyderabad | E13: 412000 | F13: Farhan Dar
A14: ADM-TRV-SKT-2024-1009 | B14: Vehicle Change | C14: May-2024 | D14: Sialkot | E14: -75000 | F14: Sobia Naz
A15: ADM-MTR-RWP-2024-1010 | B15: Extension of Period | C15: May-2024 | D15: Rawalpindi | E15: 133000 | F15: Junaid Akram
A16: ADM-HLT-KHI-2024-1011 | B16: Sum Insured Increase | C16: Jun-2024 | D16: Karachi Main | E16: 204500 | F16: Hamid Raza
A17: ADM-MSC-LHR-2024-1012 | B17: Cancellation Refund | C17: Jun-2024 | D17: Lahore Gulberg | E17: -88000 | F17: Nimra Saleem
... A25: ADM-MAR-RWP-2024-1020 | B25: Sum Insured Increase | C25: Oct-2024 | D25: Rawalpindi | E25: 190000 | F25: Farhan Dar
A27: Table B — Three-criteria query
A28: Criteria | B28: Value
A29: Policy No | B29: ADM-ENG-QTA-2024-1007
A30: Endorsement Type | B30: Add Driver
A31: Effective Month | B31: Apr-2024
A33: Note: This is simulated training data modelled on Adamjee Assurance general insurance operations. It is not actual company data.

Sheet 1.5 Report
A1: ADAMJEE ASSURANCE COMPANY LIMITED
A2: Cancellation Refund Reconciliation
A3: Prepared for: | B3: Finance Manager — Premium Accounting
A4: Prepared by:
A5: Reporting date: | B5: As at reporting date shown on the dataset
A7: Three cancellation refunds were posted in the ledger this quarter and Finance cannot match two of them to the endorsement register because the same policy also had a sum insured increase in the same month.
A9: Source data: '1.5 Data' (click to open)
A11: Navy headers below = data linked live from the dataset sheet. Gold headers = blank — build your formula here.
A12: Policy No | B12: Month | C12: Cancellation Refund from the register | D12: Amount in ledger (entered by you) | E12: Difference | F12: Status (
A13: ='1.5 Data'!A6 | B13: ='1.5 Data'!C6
A14: ='1.5 Data'!A7 | B14: ='1.5 Data'!C7
A15: ='1.5 Data'!A8 | B15: ='1.5 Data'!C8
A16: ='1.5 Data'!A9 | B16: ='1.5 Data'!C9
A17: ='1.5 Data'!A10 | B17: ='1.5 Data'!C10
A18: ='1.5 Data'!A11 | B18: ='1.5 Data'!C11
A19: ='1.5 Data'!A12 | B19: ='1.5 Data'!C12
A20: ='1.5 Data'!A13 | B20: ='1.5 Data'!C13
A21: ='1.5 Data'!A14 | B21: ='1.5 Data'!C14
A22: ='1.5 Data'!A15 | B22: ='1.5 Data'!C15
A23: ='1.5 Data'!A16 | B23: ='1.5 Data'!C16
A24: ='1.5 Data'!A17 | B24: ='1.5 Data'!C17
... A32: ='1.5 Data'!A25 | B32: ='1.5 Data'!C25
A33: TOTAL / RESULT
A35: HOW TO WORK: navy-header columns are linked live from the dataset sheet — click any cell to see the formula. Gold-header columns are blank and shaded yellow — build the required formula there and copy it down every row, then complete the TOTAL / RESULT row at the foot.
A37: FURTHER REQUESTS ON THIS DATASET
A38: # | B38: Request | C38: Requested by | D38: Report / figure required | E38: Your formula or answer
A39: 1 | B39: Endorsement Premium Impact Statement | C39: Manager, Policy Administration | D39: A statement block keyed on three criteria (Policy No, Endorsement Type, Effective Month) returning: Premium Impact | Branch | Handled By. Changing any of the three criteria cells must return the correct single record.
A40: 2 | B40: Endorsement Audit Trail — five disputed records | C40: Head of Internal Audit | D40: An audit schedule: five rows, each with Policy No | Endorsement Type | Effective Month as inputs, and Premium Impact | Handled By as formula outputs. One formula pattern copied down all five rows.
A41: 3 | B41: Robustness test before release | C41: Head of MIS | D41: Evidence of two tests, recorded in the yellow box: what the formula returns for a combination that does not exist, and what it returns after your fix. State which wrapper you used and why.

Sheet 1.6 Data
A1: Dataset 1.6 — OFFSET with MATCH for Dynamic Lookups
A2: Session 1: Advanced Lookup, Text & Date Functions | Part A: Advanced Lookup Functions | Adamjee Assurance Company Limited (Pakistan) — training data, figures in PKR
A4: Table A — Monthly Gross Written Premium, Adamjee Assurance (all branches), PKR
A5: Month | B5: Gross Written Premium | C5: Claims Paid | D5: Net Premium Earned | E5: Policies Issued
A6: Jan-2024 | B6: 70997000 | C6: 29629000 | D6: 58217540 | E6: 1200
A7: Feb-2024 | B7: 53831000 | C7: 39861000 | D7: 44141420 | E7: 1292
A8: Mar-2024 | B8: 69284000 | C8: 41849000 | D8: 56812880 | E8: 1384
A9: Apr-2024 | B9: 58476000 | C9: 35117000 | D9: 47950320 | E9: 1476
A10: May-2024 | B10: 64759000 | C10: 36418000 | D10: 53102380 | E10: 1348
A11: Jun-2024 | B11: 74750000 | C11: 29571000 | D11: 61295000 | E11: 1440
A12: Jul-2024 | B12: 69081000 | C12: 27449000 | D12: 56646420 | E12: 1532
A13: Aug-2024 | B13: 74767000 | C13: 26781000 | D13: 61308940 | E13: 1624
A14: Sep-2024 | B14: 56995000 | C14: 32638000 | D14: 46735900 | E14: 1496
A15: Oct-2024 | B15: 59129000 | C15: 44634000 | D15: 48485780 | E15: 1588
A16: Nov-2024 | B16: 57312000 | C16: 24054000 | D16: 46995840 | E16: 1680
A17: Dec-2024 | B17: 63793000 | C17: 24613000 | D17: 52310260 | E17: 1772
A19: Table B — Rolling window controls
A20: Control | B20: Value
A21: Start Month | B21: Apr-2024
A22: Number of Months | B22: 3
A23: Measure required | B23: Gross Written Premium
A25: Note: This is simulated training data modelled on Adamjee Assurance general insurance operations. It is not actual company data.

Sheet 1.6 Report
A1: ADAMJEE ASSURANCE COMPANY LIMITED
A2: Rolling 3-Month Premium Report
A3: Prepared for: | B3: Chief Financial Officer
A4: Prepared by:
A5: Reporting date: | B5: As at reporting date shown on the dataset
A7: The CFO reviews momentum on a rolling three-month basis, not year-to-date, because year-to-date hides a bad quarter. At present an analyst rewrites the SUM range every month and in July the range was left on the previous window, so the report understated premium by a full month.
A9: Source data: '1.6 Data' (click to open)
A11: DELIVERABLE CHECKLIST
A12: # | B12: Deliverable | C12: Report specification | D12: Requested by | E12: Done?
A13: 1 | B13: Rolling 3-Month Premium Report | C13: A rolling window report: Start Month (input) | Months in window (input) | Rolling Total GWP | Rolling Average GWP | Rolling Total Claims | Rolling Loss Ratio. Changing the start month or the window size must move the whole report with no formula edits. | D13: Chief Financial Officer
A14: 2 | B14: Measure Switch for the one-page CFO summary | C14: The rolling report with a Measure selector cell (Gross Written Premium / Claims Paid / Net Premium Earned / Policies Issued). The column offset inside OFFSET must be driven by that cell. | D14: Head of Management Reporting
A15: 3 | B15: Quarter-on-quarter momentum table | C15: A momentum table: Window | Total GWP | Average GWP per month | Change vs previous window (PKR and %). Three windows: Jan-Mar, Apr-Jun, Jul-Sep, each built from the same OFFSET formula with a different start month cell. | D15: Regional Head — North
A16: 4 | B16: Performance memo on volatile functions | C16: A short memo in the yellow box: what 'volatile' means, why OFFSET slows a large workbook, and the non-volatile alternative you would use in a 200,000-row file. | D16: Head of MIS
A18: BUILD YOUR REPORT / OUTPUT BELOW (pivot, chart, macro output, or model — as required above)
A34: HOW TO WORK: build the requested output in the blank area above (or insert a pivot table / chart / macro-driven control here), tick each deliverable off in the checklist, and record any formula or setting worth remembering in the specification column.

Sheet 1.7 Data
A1: Dataset 1.7 — Handling Lookup Errors with IFERROR and IFNA
A2: Session 1: Advanced Lookup, Text & Date Functions | Part A: Advanced Lookup Functions | Adamjee Assurance Company Limited (Pakistan) — training data, figures in PKR
A4: Table A — Policy Master Extract
A5: Policy No | B5: Client Name | C5: Branch | D5: Gross Premium (PKR) | E5: Claims Paid (PKR)
A6: ADM-FIR-KHI-2024-1001 | B6: Gul Ahmed Textile Mills Ltd | C6: Karachi Main | D6: 96000 | E6: 120362
A7: ADM-TRV-LHR-2024-1002 | B7: Packages Limited | C7: Lahore Gulberg | D7: 201000 | E7: 206906
A8: ADM-MTR-ISB-2024-1003 | B8: Bilal Ahmed Khan | C8: Islamabad Blue Area | D8: 1397000 | E8: 400344
A9: ADM-HLT-FSD-2024-1004 | B9: Attock Refinery Limited | C9: Faisalabad | D9: 305000 | E9: 173654
A10: ADM-MSC-MUL-2024-1005 | B10: Descon Engineering Ltd | C10: Multan | D10: 75000 | E10: 26600
A11: ADM-MAR-PEW-2024-1006 | B11: Hina Farooq | C11: Peshawar | D11: 380000 | E11: 275064
A12: ADM-ENG-QTA-2024-1007 | B12: Indus Motor Company Ltd | C12: Quetta | D12: 227000 | E12: 227881
A13: ADM-FIR-HYD-2024-1008 | B13: Nishat Mills Limited | C13: Hyderabad | D13: 290000 | E13: 404928
A14: ADM-TRV-SKT-2024-1009 | B14: Imran Aslam Sheikh | C14: Sialkot | D14: 37000 | E14: 9893
A15: ADM-MTR-RWP-2024-1010 | B15: Engro Polymer & Chemicals | C15: Rawalpindi | D15: 760000 | E15: 483596
A16: ADM-HLT-KHI-2024-1011 | B16: Interloop Limited | C16: Karachi Main | D16: 603000 | E16: 775060
A17: ADM-MSC-LHR-2024-1012 | B17: Mehwish Anwar | C17: Lahore Gulberg | D17: 512000 | E17: 210598
... A25: ADM-MAR-RWP-2024-1020 | B25: Thal Limited | C25: Rawalpindi | D25: 181000 | E25: 145864
A27: Table B — Recovery Register (as received — contains bad references)
A28: Line | B28: Policy No Pasted | C28: Source Branch | D28: Status Noted
A29: 1 | B29: ADM-MTR-ISB-2024-1003 | C29: Karachi Main | D29: Valid
A30: 2 | B30: ADM-MTR-KHI-2024-9999 | C30: Karachi Main | D30: Cancelled policy
A31: 3 | B31: ADM-MAR-PEW-2024-1006 | C31: Lahore Gulberg | D31: Valid
A32: 4 | B32: ADM-TRV-SKT-2024-1009 | C32: Lahore Gulberg | D32: Trailing space typed
A33: 5 | B33: ADM-FIR-LHR-2023-0450 | C33: Lahore Gulberg | D33: Prior year – not in master
A34: 6 | B34: ADM-ENG-FSD-2024-1014 | C34: Islamabad Blue Area | D34: Valid
A35: 7 | C35: Islamabad Blue Area | D35: Blank cell pasted
A36: 8 | B36: ADM-HLT-HYD-2024-1018 | C36: Multan | D36: Valid
A38: Table C — Branch premium and claims for loss ratio (note the zero)
A39: Branch | B39: Gross Premium (PKR) | C39: Claims Paid (PKR)
A40: Karachi Main | B40: 48500000 | C40: 21300000
A41: Lahore Gulberg | B41: 33200000 | C41: 19900000
A42: Quetta (opened Dec-2024) | B42: 0 | C42: 0
A43: Multan | B43: 12700000 | C43: 8450000
A45: Note: This is simulated training data modelled on Adamjee Assurance general insurance operations. It is not actual company data.

Sheet 1.7 Report
A1: ADAMJEE ASSURANCE COMPANY LIMITED
A2: Recovery Register — cleaned for CFO signature
A3: Prepared for: | B3: Chief Financial Officer
A4: Prepared by:
A5: Reporting date: | B5: As at reporting date shown on the dataset
A7: The Recovery Register is compiled by pasting policy numbers from three branches. This month's draft went to the CFO with N/A in four rows and a DIV/0! in the branch summary. It came back unsigned with the comment 'I cannot present this to the Board'.
A9: Source data: '1.7 Data' (click to open)
A11: Navy headers below = data linked live from the dataset sheet. Gold headers = blank — build your formula here.
A12: Line | B12: Policy No | C12: Client Name | D12: Branch | E12: Gross Premium | F12: Status
B13: ='1.7 Data'!A6 | C13: ='1.7 Data'!B6 | D13: ='1.7 Data'!C6 | E13: ='1.7 Data'!D6
B14: ='1.7 Data'!A7 | C14: ='1.7 Data'!B7 | D14: ='1.7 Data'!C7 | E14: ='1.7 Data'!D7
B15: ='1.7 Data'!A8 | C15: ='1.7 Data'!B8 | D15: ='1.7 Data'!C8 | E15: ='1.7 Data'!D8
B16: ='1.7 Data'!A9 | C16: ='1.7 Data'!B9 | D16: ='1.7 Data'!C9 | E16: ='1.7 Data'!D9
B17: ='1.7 Data'!A10 | C17: ='1.7 Data'!B10 | D17: ='1.7 Data'!C10 | E17: ='1.7 Data'!D10
B18: ='1.7 Data'!A11 | C18: ='1.7 Data'!B11 | D18: ='1.7 Data'!C11 | E18: ='1.7 Data'!D11
B19: ='1.7 Data'!A12 | C19: ='1.7 Data'!B12 | D19: ='1.7 Data'!C12 | E19: ='1.7 Data'!D12
B20: ='1.7 Data'!A13 | C20: ='1.7 Data'!B13 | D20: ='1.7 Data'!C13 | E20: ='1.7 Data'!D13
B21: ='1.7 Data'!A14 | C21: ='1.7 Data'!B14 | D21: ='1.7 Data'!C14 | E21: ='1.7 Data'!D14
B22: ='1.7 Data'!A15 | C22: ='1.7 Data'!B15 | D22: ='1.7 Data'!C15 | E22: ='1.7 Data'!D15
B23: ='1.7 Data'!A16 | C23: ='1.7 Data'!B16 | D23: ='1.7 Data'!C16 | E23: ='1.7 Data'!D16
B24: ='1.7 Data'!A17 | C24: ='1.7 Data'!B17 | D24: ='1.7 Data'!C17 | E24: ='1.7 Data'!D17
... B32: ='1.7 Data'!A25 | C32: ='1.7 Data'!B25 | D32: ='1.7 Data'!C25 | E32: ='1.7 Data'!D25
A33: TOTAL / RESULT
A35: HOW TO WORK: navy-header columns are linked live from the dataset sheet — click any cell to see the formula. Gold-header columns are blank and shaded yellow — build the required formula there and copy it down every row, then complete the TOTAL / RESULT row at the foot.
A37: FURTHER REQUESTS ON THIS DATASET
A38: # | B38: Request | C38: Requested by | D38: Report / figure required | E38: Your formula or answer
A39: 1 | B39: Exception Schedule for the branch network | C39: Head of Internal Audit | D39: An exception schedule: Line | Policy No as pasted | Failure reason (Cancelled policy / Trailing space / Prior year / Blank cell) | Action for the branch. Count of exceptions shown at the top.
A40: 2 | B40: Recovering the trailing-space line without touching source data | C40: Manager, Policy Servicing | D40: The register with line 4 matching correctly, source data unchanged. Show the formula used and state in one line how many of the eight lines matched before and after your fix.
A41: 3 | B41: Branch Loss Ratio table including the new Quetta branch | C41: Regional Head — South | D41: A branch loss ratio table: Branch | GWP | Claims Paid | Loss Ratio, where a branch with no premium shows 'n/a' rather than an error. Ratios formatted 0.0%.
A42: 4 | B42: Control note on blanket error suppression | C42: Head of Internal Audit | D42: A three-line control note: why blanket IFERROR is dangerous in a financial report, the difference between IFERROR and IFNA, and your recommendation on which to use in the Recovery Register.

Sheet 1.8 Data
A1: Dataset 1.8 — LEFT, RIGHT, MID
A2: Session 1: Advanced Lookup, Text & Date Functions | Part B: Advanced Text Functions | Adamjee Assurance Company Limited (Pakistan) — training data, figures in PKR
A4: Table A — Policy Number Register (structure: ADM-PPP-BBB-YYYY-NNNN)
A5: Line | B5: Policy No | C5: Client Name | D5: Gross Premium (PKR)
A6: 1 | B6: ADM-MTR-KHI-2024-1001 | C6: Gul Ahmed Textile Mills Ltd | D6: 96000
A7: 2 | B7: ADM-FIR-KHI-2024-1002 | C7: Packages Limited | D7: 201000
A8: 3 | B8: ADM-MAR-KHI-2024-1003 | C8: Bilal Ahmed Khan | D8: 1397000
A9: 4 | B9: ADM-HLT-KHI-2024-1004 | C9: Attock Refinery Limited | D9: 305000
A10: 5 | B10: ADM-TRV-LHR-2024-1005 | C10: Descon Engineering Ltd | D10: 75000
A11: 6 | B11: ADM-ENG-LHR-2024-1006 | C11: Hina Farooq | D11: 380000
A12: 7 | B12: ADM-MSC-LHR-2024-1008 | C12: Indus Motor Company Ltd | D12: 227000
A13: 8 | B13: ADM-MTR-ISB-2024-1009 | C13: Nishat Mills Limited | D13: 290000
A14: 9 | B14: ADM-FIR-ISB-2024-1010 | C14: Imran Aslam Sheikh | D14: 37000
A15: 10 | B15: ADM-MAR-ISB-2024-1011 | C15: Engro Polymer & Chemicals | D15: 760000
A16: 11 | B16: ADM-HLT-FSD-2024-1012 | C16: Interloop Limited | D16: 603000
A17: 12 | B17: ADM-TRV-FSD-2024-1013 | C17: Mehwish Anwar | D17: 512000
... A29: 24 | B29: ADM-MAR-QTA-2024-1025 | C29: Ayesha Tariq | D29: 2304000
A31: Table B — Decode tables
A32: Product Code | B32: Product | C32: Branch Code | D32: Branch
A33: MTR | B33: Motor | C33: KHI | D33: Karachi Main
A34: FIR | B34: Fire & Property | C34: LHR | D34: Lahore Gulberg
A35: MAR | B35: Marine Cargo | C35: ISB | D35: Islamabad Blue Area
A36: HLT | B36: Health | C36: FSD | D36: Faisalabad
A37: TRV | B37: Travel | C37: MUL | D37: Multan
A38: ENG | B38: Engineering | C38: PEW | D38: Peshawar
A39: MSC | B39: Miscellaneous | C39: QTA | D39: Quetta
A41: Note: This is simulated training data modelled on Adamjee Assurance general insurance operations. It is not actual company data.

Sheet 1.8 Report
A1: ADAMJEE ASSURANCE COMPANY LIMITED
A2: Policy Register split into MIS dimensions
A3: Prepared for: | B3: Head of MIS
A4: Prepared by:
A5: Reporting date: | B5: As at reporting date shown on the dataset
A7: The data warehouse rebuild needs product and branch as separate fields. Today they exist only inside the policy number, and the interim solution has been a manual mapping file that a colleague updates by hand every month and which was last updated in June.
A9: Source data: '1.8 Data' (click to open)
A11: Navy headers below = data linked live from the dataset sheet. Gold headers = blank — build your formula here.
A12: Line | B12: Policy No | C12: Prefix | D12: Product Code | E12: Branch Code | F12: Year | G12: Serial | H12: Gross Premium
A13: ='1.8 Data'!A6 | B13: ='1.8 Data'!B6 | H13: ='1.8 Data'!D6
A14: ='1.8 Data'!A7 | B14: ='1.8 Data'!B7 | H14: ='1.8 Data'!D7
A15: ='1.8 Data'!A8 | B15: ='1.8 Data'!B8 | H15: ='1.8 Data'!D8
A16: ='1.8 Data'!A9 | B16: ='1.8 Data'!B9 | H16: ='1.8 Data'!D9
A17: ='1.8 Data'!A10 | B17: ='1.8 Data'!B10 | H17: ='1.8 Data'!D10
A18: ='1.8 Data'!A11 | B18: ='1.8 Data'!B11 | H18: ='1.8 Data'!D11
A19: ='1.8 Data'!A12 | B19: ='1.8 Data'!B12 | H19: ='1.8 Data'!D12
A20: ='1.8 Data'!A13 | B20: ='1.8 Data'!B13 | H20: ='1.8 Data'!D13
A21: ='1.8 Data'!A14 | B21: ='1.8 Data'!B14 | H21: ='1.8 Data'!D14
A22: ='1.8 Data'!A15 | B22: ='1.8 Data'!B15 | H22: ='1.8 Data'!D15
A23: ='1.8 Data'!A16 | B23: ='1.8 Data'!B16 | H23: ='1.8 Data'!D16
A24: ='1.8 Data'!A17 | B24: ='1.8 Data'!B17 | H24: ='1.8 Data'!D17
... A36: ='1.8 Data'!A29 | B36: ='1.8 Data'!B29 | H36: ='1.8 Data'!D29
A37: TOTAL / RESULT
A39: HOW TO WORK: navy-header columns are linked live from the dataset sheet — click any cell to see the formula. Gold-header columns are blank and shaded yellow — build the required formula there and copy it down every row, then complete the TOTAL / RESULT row at the foot.
A41: FURTHER REQUESTS ON THIS DATASET
A42: # | B42: Request | C42: Requested by | D42: Report / figure required | E42: Your formula or answer
A43: 1 | B43: Product and Branch names for the MIS extract | C43: Head of MIS | D43: The dimension table extended with Product Name and Branch Name columns, joined from the decode tables using your extracted codes.
A44: 2 | B44: Serial number continuity check | C44: Head of Internal Audit | D44: A continuity check: Branch Code | First Serial | Last Serial | Count of policies | Expected count | Gap flag. Serials must be real numbers, not text.
A45: 3 | B45: Format validation for the incoming feed | C45: Head of MIS | D45: A validation column flagging any policy number whose prefix is not exactly 'ADM', whose year is not 2024, or whose serial is not four digits. Count of failures shown at the top.

Sheet 1.9 Data
A1: Dataset 1.9 — FIND and SEARCH
A2: Session 1: Advanced Lookup, Text & Date Functions | Part B: Advanced Text Functions | Adamjee Assurance Company Limited (Pakistan) — training data, figures in PKR
A4: Table A — Claim Intimation Remarks (free text, positions vary)
A5: Claim No | B5: Branch | C5: Intimation Remark | D5: Claimed Amount (PKR)
A6: CLM-KHI-2024-0501 | B6: Karachi Main | C6: Vehicle Reg: AEE-1234 | Surveyor: Crawford Pakistan | Ref#45231 | D6: 385000
A7: CLM-LHR-2024-0502 | B7: Lahore Gulberg | C7: Vehicle Reg: LEB-8890 | Surveyor: Alpha Loss Adjusters | Ref#45298 | D7: 1240000
A8: CLM-ISB-2024-0503 | B8: Islamabad Blue Area | C8: Vehicle Reg: ICT-4471 | Surveyor: Rehman Surveyors Pvt Ltd | Ref#45310 | D8: 92500
A9: CLM-FSD-2024-0504 | B9: Faisalabad | C9: Vehicle Reg: FDR-2209 | Surveyor: Ravi Assessors | Ref#45344 | D9: 660000
A10: CLM-MUL-2024-0505 | B10: Multan | C10: vehicle reg: MNJ-7712 | surveyor: Sindh Survey Services | ref#45390 | D10: 208000
A11: CLM-KHI-2024-0506 | B11: Karachi Main | C11: Vehicle Reg: AKL-0056 | Surveyor: Crawford Pakistan | Ref#45412 | D11: 1875000
A12: CLM-PEW-2024-0507 | B12: Peshawar | C12: Vehicle Reg: PSR-3390 | Surveyor: Alpha Loss Adjusters | Ref#45457 | D12: 445000
A13: CLM-HYD-2024-0508 | B13: Hyderabad | C13: Vehicle Reg: HDA-6621 | Surveyor: Ravi Assessors | Ref#45501 | D13: 130000
A15: Note: This is simulated training data modelled on Adamjee Assurance general insurance operations. It is not actual company data.

Sheet 1.9 Report
A1: ADAMJEE ASSURANCE COMPANY LIMITED
A2: Motor Claims Intimation Register — fields extracted
A3: Prepared for: | B3: Manager, Motor Claims
A4: Prepared by:
A5: Reporting date: | B5: As at reporting date shown on the dataset
A7: Claim intimations arrive by email and the whole detail sits in one free-text remark field. The surveyor allocation report is currently produced by reading each remark and typing the three fields out, which takes an afternoon a week and is the reason surveyor workload is never accurate.
A9: Source data: '1.9 Data' (click to open)
A11: Navy headers below = data linked live from the dataset sheet. Gold headers = blank — build your formula here.
A12: Claim No | B12: Branch | C12: Vehicle Registration | D12: Surveyor Firm | E12: Reference No | F12: Claimed Amount
A13: ='1.9 Data'!A6 | B13: ='1.9 Data'!B6 | F13: ='1.9 Data'!D6
A14: ='1.9 Data'!A7 | B14: ='1.9 Data'!B7 | F14: ='1.9 Data'!D7
A15: ='1.9 Data'!A8 | B15: ='1.9 Data'!B8 | F15: ='1.9 Data'!D8
A16: ='1.9 Data'!A9 | B16: ='1.9 Data'!B9 | F16: ='1.9 Data'!D9
A17: ='1.9 Data'!A10 | B17: ='1.9 Data'!B10 | F17: ='1.9 Data'!D10
A18: ='1.9 Data'!A11 | B18: ='1.9 Data'!B11 | F18: ='1.9 Data'!D11
A19: ='1.9 Data'!A12 | B19: ='1.9 Data'!B12 | F19: ='1.9 Data'!D12
A20: ='1.9 Data'!A13 | B20: ='1.9 Data'!B13 | F20: ='1.9 Data'!D13
A21: TOTAL / RESULT
A23: HOW TO WORK: navy-header columns are linked live from the dataset sheet — click any cell to see the formula. Gold-header columns are blank and shaded yellow — build the required formula there and copy it down every row, then complete the TOTAL / RESULT row at the foot.
A25: FURTHER REQUESTS ON THIS DATASET
A26: # | B26: Request | C26: Requested by | D26: Report / figure required | E26: Your formula or answer
A27: 1 | B27: Surveyor Workload and Fee Accrual Report | C27: Head of Claims Operations | D27: A surveyor summary: Surveyor Firm | Cases Allocated | Total Claimed Amount | Average Claim Size | Share of cases %. Built on the extracted surveyor field, sorted by cases descending.
A28: 2 | B28: Case-sensitivity defect report | C28: Head of MIS | D28: A defect note plus the corrected formula: identify the affected row, state which of FIND and SEARCH failed and why, and show the formula that works for both upper and lower case.
A29: 3 | B29: Incomplete intimation exception list | C29: Manager, Motor Claims | D29: An exception list flagging any intimation whose remark does not contain the word 'Surveyor', with Claim No, Branch and the remark as received, plus a count at the top for the daily stand-up.

Sheet 1.10 Data
A1: Dataset 1.10 — LEN, TRIM, CLEAN
A2: Session 1: Advanced Lookup, Text & Date Functions | Part B: Advanced Text Functions | Adamjee Assurance Company Limited (Pakistan) — training data, figures in PKR
A4: Table A — Client names received from the bancassurance partner (dirty)
A5: Line | B5: Client Name (as received) | C5: CNIC / NTN | D5: Sum Insured (PKR)
A6: 1 | B6: Gul Ahmed Textile Mills Ltd | C6: 0713456-7 | D6: 45000000
A7: 2 | B7: Lucky Cement Limited | C7: 1234567-8 | D7: 88000000
A8: 3 | B8: Ahmed Raza Qureshi | C8: 42101-1234567-1 | D8: 6900000
A9: 4 | B9: Nishat Mills Limited | C9: 0918822-3 | D9: 62500000
A10: 5 | B10: Fatima Siddiqui | C10: 35202-9876543-2 | D10: 1950000
A11: 6 | B11: K-Electric Limited | C11: 0511223-4 | D11: 120000000
A12: 7 | B12: Interloop Limited | C12: 3301144-5 | D12: 22500000
A13: 8 | B13: Bilal Ahmed Khan | C13: 61101-4455667-9 | D13: 9990000
A15: Table B — Adamjee Policy Master (clean names, for matching)
A16: Client Name | B16: Client Code | C16: Branch | D16: Gross Premium (PKR)
A17: Gul Ahmed Textile Mills Ltd | B17: KHI-CORP-0100 | C17: Karachi Main | D17: 985000
A18: Lucky Cement Limited | B18: KHI-CORP-0102 | C18: Karachi Main | D18: 1640000
A19: Ahmed Raza Qureshi | B19: KHI-INDV-0107 | C19: Karachi Main | D19: 148000
A20: Nishat Mills Limited | B20: LHR-CORP-0111 | C20: Lahore Gulberg | D20: 1210000
A21: Fatima Siddiqui | B21: LHR-INDV-0113 | C21: Lahore Gulberg | D21: 46800
A22: K-Electric Limited | B22: KHI-CORP-0121 | C22: Karachi Main | D22: 3480000
A23: Interloop Limited | B23: FSD-CORP-0118 | C23: Faisalabad | D23: 720000
A24: Bilal Ahmed Khan | B24: ISB-INDV-0125 | C24: Islamabad Blue Area | D24: 205000
A26: Note: This is simulated training data modelled on Adamjee Assurance general insurance operations. It is not actual company data.

Sheet 1.10 Report
A1: ADAMJEE ASSURANCE COMPANY LIMITED
A2: Bancassurance Reconciliation — matched and unmatched
A3: Prepared for: | B3: Head of Bancassurance
A4: Prepared by:
A5: Reporting date: | B5: As at reporting date shown on the dataset
A7: The partner bank's monthly client file will not match the Adamjee policy master. On screen the names look identical, yet the lookup returns N/A on five of eight rows. The commission settlement with the bank is held up as a result and the relationship manager has escalated it twice.
A9: Source data: '1.10 Data' (click to open)
A11: Navy headers below = data linked live from the dataset sheet. Gold headers = blank — build your formula here.
A12: Line | B12: Name as received | C12: Character count | D12: Cleaned name | E12: Client Code matched | F12: Status (Matched / Unmatched)
A13: ='1.10 Data'!A6 | B13: ='1.10 Data'!B6
A14: ='1.10 Data'!A7 | B14: ='1.10 Data'!B7
A15: ='1.10 Data'!A8 | B15: ='1.10 Data'!B8
A16: ='1.10 Data'!A9 | B16: ='1.10 Data'!B9
A17: ='1.10 Data'!A10 | B17: ='1.10 Data'!B10
A18: ='1.10 Data'!A11 | B18: ='1.10 Data'!B11
A19: ='1.10 Data'!A12 | B19: ='1.10 Data'!B12
A20: ='1.10 Data'!A13 | B20: ='1.10 Data'!B13
A21: TOTAL / RESULT
A23: HOW TO WORK: navy-header columns are linked live from the dataset sheet — click any cell to see the formula. Gold-header columns are blank and shaded yellow — build the required formula there and copy it down every row, then complete the TOTAL / RESULT row at the foot.
A25: FURTHER REQUESTS ON THIS DATASET
A26: # | B26: Request | C26: Requested by | D26: Report / figure required | E26: Your formula or answer
A27: 1 | B27: Data quality defect log for the partner bank | C27: Head of Bancassurance | D27: A defect log: Line | Defect type (leading spaces / repeated inner spaces / trailing space / line feed / tab) | Extra characters counted | Example. One row per affected line, ready to attach to the email.
A28: 2 | B28: Commission settlement schedule | C28: Finance Manager — Premium Accounting | D28: A settlement schedule: Client Code | Client Name | Branch | Gross Premium | Commission due at 12.5% | Sum Insured from the bank file. Only matched rows included; unmatched rows listed separately below.
A29: 3 | B29: Source-system prevention recommendation | C29: Head of Bancassurance | D29: A two-line recommendation for the bank, in the yellow box: the single data-quality rule they should apply at source, and what Adamjee will do at its end as a safety net.

Sheet 1.11 Data
A1: Dataset 1.11 — SUBSTITUTE and REPLACE
A2: Session 1: Advanced Lookup, Text & Date Functions | Part B: Advanced Text Functions | Adamjee Assurance Company Limited (Pakistan) — training data, figures in PKR
A4: Table A — Legacy register requiring re-coding and masking
A5: Line | B5: Legacy Policy No | C5: Client Name | D5: CNIC | E5: Mobile | F5: Premium (PKR)
A6: 1 | B6: ADM-MTR-KHI-2022-1044 | C6: Gul Ahmed Textile Mills Ltd | D6: 42101-1234567-1 | E6: 0300-2345678 | F6: 985000
A7: 2 | B7: ADM-FIR-LHR-2022-1088 | C7: Nishat Mills Limited | D7: 35202-9876543-2 | E7: 0321-8765432 | F7: 1210000
A8: 3 | B8: ADM-MAR-KHI-2022-1120 | C8: Lucky Cement Limited | D8: 42201-5566778-3 | E8: 0333-1122334 | F8: 1640000
A9: 4 | B9: ADM-HLT-ISB-2022-1156 | C9: Bilal Ahmed Khan | D9: 61101-4455667-9 | E9: 0345-9988776 | F9: 205000
A10: 5 | B10: ADM-ENG-FSD-2022-1190 | C10: Interloop Limited | D10: 33100-2233445-7 | E10: 0301-4455667 | F10: 720000
A11: 6 | B11: ADM-MTR-LHR-2022-1215 | C11: Fatima Siddiqui | D11: 35201-7788990-4 | E11: 0312-3344556 | F11: 46800
A12: 7 | B12: ADM-TRV-KHI-2022-1240 | C12: Ahmed Raza Qureshi | D12: 42000-1029384-5 | E12: 0308-6677889 | F12: 148000
A13: 8 | B13: ADM-MSC-PEW-2022-1277 | C13: Descon Engineering Ltd | D13: 17301-5647382-6 | E13: 0311-2233445 | F13: 640000
A15: Table B — Branch re-coding map (old code to new code)
A16: Old Code | B16: New Code | C16: Branch
A17: KHI | B17: KHIM | C17: Karachi Main
A18: LHR | B18: LHGB | C18: Lahore Gulberg
A19: ISB | B19: ISBA | C19: Islamabad Blue Area
A20: FSD | B20: FSDC | C20: Faisalabad
A21: PEW | B21: PEWC | C21: Peshawar
A22: MUL | B22: MULC | C22: Multan
A24: Note: This is simulated training data modelled on Adamjee Assurance general insurance operations. It is not actual company data.

Sheet 1.11 Report
A1: ADAMJEE ASSURANCE COMPANY LIMITED
A2: Legacy Policy Re-coding Schedule
A3: Prepared for: | B3: Head of MIS
A4: Prepared by:
A5: Reporting date: | B5: As at reporting date shown on the dataset
A7: Adamjee has moved to four-letter branch codes. Eight thousand legacy policy numbers still carry the old three-letter codes and the migration date is the end of this month. The first attempt re-coded Lahore policies as Karachi because the mapping was applied by hand.
A9: Source data: '1.11 Data' (click to open)
A11: Navy headers below = data linked live from the dataset sheet. Gold headers = blank — build your formula here.
A12: Line | B12: Legacy Policy No | C12: New Policy No (year updated to 2025 and branch code converted) | D12: Old Code | E12: New Code | F12: Branch Name
A13: ='1.11 Data'!A6 | B13: ='1.11 Data'!B6
A14: ='1.11 Data'!A7 | B14: ='1.11 Data'!B7
A15: ='1.11 Data'!A8 | B15: ='1.11 Data'!B8
A16: ='1.11 Data'!A9 | B16: ='1.11 Data'!B9
A17: ='1.11 Data'!A10 | B17: ='1.11 Data'!B10
A18: ='1.11 Data'!A11 | B18: ='1.11 Data'!B11
A19: ='1.11 Data'!A12 | B19: ='1.11 Data'!B12
A20: ='1.11 Data'!A13 | B20: ='1.11 Data'!B13
A21: TOTAL / RESULT
A23: HOW TO WORK: navy-header columns are linked live from the dataset sheet — click any cell to see the formula. Gold-header columns are blank and shaded yellow — build the required formula there and copy it down every row, then complete the TOTAL / RESULT row at the foot.
A25: FURTHER REQUESTS ON THIS DATASET
A26: # | B26: Request | C26: Requested by | D26: Report / figure required | E26: Your formula or answer
A27: 1 | B27: Masked Client Register for the external surveyor | C27: Head of Compliance | D27: A masked register: Line | Policy No | Client Name | CNIC masked to show only the final digit | Mobile masked to show only the network prefix | Premium. Nothing typed by hand — every mask produced by formula.
A28: 2 | B28: Product line re-designation for the SECP return | C28: Head of Regulatory Reporting | D28: A return extract: Original Policy No | Return Policy No (characters 5-7 replaced with GEN) | Product | Premium. The original column must remain visible for reconciliation.
A29: 3 | B29: Method selection note for the migration runbook | C29: Head of MIS | D29: A two-line entry for the runbook: when to use SUBSTITUTE and when to use REPLACE, with one Adamjee example of each from the work you just did.

Sheet 1.12 Data
A1: Dataset 1.12 — CONCATENATE and the Ampersand (&) Operator
A2: Session 1: Advanced Lookup, Text & Date Functions | Part B: Advanced Text Functions | Adamjee Assurance Company Limited (Pakistan) — training data, figures in PKR
A4: Table A — Renewal campaign base data
A5: Client Code | B5: Title | C5: Client Name | D5: Address Line | E5: City | F5: Product Code | G5: Branch Code | H5: Policy Serial | I5: Renewal Date | J5: Renewal Premium (PKR)
A6: KHI-CORP-0100 | B6: M/s | C6: Gul Ahmed Textile Mills Ltd | D6: Plot 82, Korangi Industrial Area | E6: Karachi | F6: MTR | G6: KHI | H6: 1044 | I6: 45672 | J6: 1085000
A7: LHR-CORP-0111 | B7: M/s | C7: Nishat Mills Limited | D7: 7-Main Gulberg | E7: Lahore | F7: FIR | G7: LHR | H7: 1088 | I7: 45689 | J7: 1330000
A8: KHI-CORP-0102 | B8: M/s | C8: Lucky Cement Limited | D8: Main Shahrah-e-Faisal | E8: Karachi | F8: MAR | G8: KHI | H8: 1120 | I8: 45706 | J8: 1805000
A9: ISB-INDV-0125 | B9: Mr. | C9: Bilal Ahmed Khan | D9: House 44, Street 6, F-8/3 | E9: Islamabad | F9: HLT | G9: ISB | H9: 1156 | I9: 45720 | J9: 225000
A10: FSD-CORP-0118 | B10: M/s | C10: Interloop Limited | D10: Khurrianwala-Jaranwala Road | E10: Faisalabad | F10: ENG | G10: FSD | H10: 1190 | I10: 45737 | J10: 792000
A11: LHR-INDV-0113 | B11: Ms. | C11: Fatima Siddiqui | D11: 12-C Model Town Link Road | E11: Lahore | F11: MTR | G11: LHR | H11: 1215 | I11: 45756 | J11: 51400
A12: KHI-INDV-0107 | B12: Mr. | C12: Ahmed Raza Qureshi | D12: Flat 301, Block 6 PECHS | E12: Karachi | F12: TRV | G12: KHI | H12: 1240 | I12: 45774 | J12: 162000
A13: PEW-CORP-0133 | B13: M/s | C13: Descon Engineering Ltd | D13: Industrial Estate, Hayatabad | E13: Peshawar | F13: MSC | G13: PEW | H13: 1277 | I13: 45789 | J13: 704000
A15: Note: This is simulated training data modelled on Adamjee Assurance general insurance operations. It is not actual company data.

Sheet 1.12 Report
A1: ADAMJEE ASSURANCE COMPANY LIMITED
A2: Renewal Campaign Reference Key file
A3: Prepared for: | B3: Head of Management Reporting
A4: Prepared by:
A5: Reporting date: | B5: As at reporting date shown on the dataset
A7: The renewal campaign file arrives from Marketing with the policy components in separate columns, but the call centre system will only accept a single formatted policy reference. Eight hundred references were typed manually last year and forty-one were rejected by the system.
A9: Source data: '1.12 Data' (click to open)
A11: Navy headers below = data linked live from the dataset sheet. Gold headers = blank — build your formula here.
A12: Client Code | B12: Full Policy Reference in the format ADM-MTR-KHI-2025-1044 | C12: Renewal Date | D12: Renewal Premium
A13: ='1.12 Data'!A6 | C13: ='1.12 Data'!I6 | D13: ='1.12 Data'!J6
A14: ='1.12 Data'!A7 | C14: ='1.12 Data'!I7 | D14: ='1.12 Data'!J7
A15: ='1.12 Data'!A8 | C15: ='1.12 Data'!I8 | D15: ='1.12 Data'!J8
A16: ='1.12 Data'!A9 | C16: ='1.12 Data'!I9 | D16: ='1.12 Data'!J9
A17: ='1.12 Data'!A10 | C17: ='1.12 Data'!I10 | D17: ='1.12 Data'!J10
A18: ='1.12 Data'!A11 | C18: ='1.12 Data'!I11 | D18: ='1.12 Data'!J11
A19: ='1.12 Data'!A12 | C19: ='1.12 Data'!I12 | D19: ='1.12 Data'!J12
A20: ='1.12 Data'!A13 | C20: ='1.12 Data'!I13 | D20: ='1.12 Data'!J13
A21: TOTAL / RESULT
A23: HOW TO WORK: navy-header columns are linked live from the dataset sheet — click any cell to see the formula. Gold-header columns are blank and shaded yellow — build the required formula there and copy it down every row, then complete the TOTAL / RESULT row at the foot.
A25: FURTHER REQUESTS ON THIS DATASET
A26: # | B26: Request | C26: Requested by | D26: Report / figure required | E26: Your formula or answer
A27: 1 | B27: Printed Mailing Labels for the renewal mailshot | C27: Marketing Manager | D27: A label column producing: line one 'M/s Gul Ahmed Textile Mills Ltd', line two 'Plot 82, Korangi Industrial Area, Karachi'. Wrap Text switched on so the two lines are visible in the cell.
A28: 2 | B28: Renewal SMS Text file for the bulk gateway | C28: Marketing Manager | D28: An SMS column reading: 'Dear <Name>, your Adamjee policy <PolicyNo> renews on 15-Jan-2025. Premium PKR 1,085,000.' — date as dd-mmm-yyyy, amount comma-formatted. One formula copied down all eight rows.
A29: 3 | B29: Defect demonstration for the Marketing sign-off | C29: Marketing Manager | D29: A side-by-side demonstration: one SMS line built without TEXT around the date and amount, one built with it, and a one-line explanation of what Excel is actually storing behind a date.

Sheet 1.13 Data
A1: Dataset 1.13 — Extracting Data from Policy Numbers and Client Codes Using Text Formulas
A2: Session 1: Advanced Lookup, Text & Date Functions | Part B: Advanced Text Functions | Adamjee Assurance Company Limited (Pakistan) — training data, figures in PKR
A4: Table A — Flat file received from the legacy policy administration system
A5: Line | B5: Policy No | C5: Client Code | D5: Combined Description | E5: Gross Premium (PKR)
A6: 1 | B6: ADM-MTR-KHI-2024-1001 | C6: KHI-CORP-0100 | D6: Gul Ahmed Textile Mills Ltd/Motor Fleet/Karachi/Active | E6: 985000
A7: 2 | B7: ADM-FIR-LHR-2024-1002 | C7: LHR-CORP-0111 | D7: Nishat Mills Limited/Fire and Property/Lahore/Active | E7: 1210000
A8: 3 | B8: ADM-MAR-KHI-2024-1003 | C8: KHI-CORP-0102 | D8: Lucky Cement Limited/Marine Cargo/Karachi/Renewed | E8: 1640000
A9: 4 | B9: ADM-HLT-ISB-2024-1004 | C9: ISB-INDV-0125 | D9: Bilal Ahmed Khan/Health Individual/Islamabad/Active | E9: 205000
A10: 5 | B10: ADM-ENG-FSD-2024-1005 | C10: FSD-CORP-0118 | D10: Interloop Limited/Engineering CAR/Faisalabad/Lapsed | E10: 720000
A11: 6 | B11: ADM-MTR-LHR-2024-1006 | C11: LHR-INDV-0113 | D11: Fatima Siddiqui/Motor Private/Lahore/Active | E11: 46800
A12: 7 | B12: ADM-TRV-KHI-2024-1007 | C12: KHI-INDV-0107 | D12: Ahmed Raza Qureshi/Travel Schengen/Karachi/Expired | E12: 148000
A13: 8 | B13: ADM-MSC-PEW-2024-1008 | C13: PEW-CORP-0133 | D13: Descon Engineering Ltd/Workmen Compensation/Peshawar/Active | E13: 640000
A14: 9 | B14: ADM-FIR-MUL-2024-1009 | C14: MUL-CORP-0140 | D14: Fauji Fertilizer Company/Fire and Property/Multan/Active | E14: 2310000
A15: 10 | B15: ADM-MTR-HYD-2024-1010 | C15: HYD-INDV-0145 | D15: Sana Javed Butt/Motor Private/Hyderabad/Cancelled | E15: 38500
A17: Note: This is simulated training data modelled on Adamjee Assurance general insurance operations. It is not actual company data.

Sheet 1.13 Report
A1: ADAMJEE ASSURANCE COMPANY LIMITED
A2: Actuarial Flat File — fully parsed
A3: Prepared for: | B3: Actuarial Manager
A4: Prepared by:
A5: Reporting date: | B5: As at reporting date shown on the dataset
A7: The legacy policy administration system has been decommissioned and the final extract is a flat file with no structure: policy number, client code and a slash-separated description are all that survived. The actuarial reserving run cannot start until every field is parsed, and the year-end timetable has nine days of slack left.
A9: Source data: '1.13 Data' (click to open)
A11: Navy headers below = data linked live from the dataset sheet. Gold headers = blank — build your formula here.
A12: Line | B12: Policy No | C12: Prefix | D12: Product Code | E12: Branch Code | F12: Year | G12: Serial | H12: Client Code | I12: Client Branch | J12: Client Type | K12: Client Sequence | L12: Gross Premium
A13: ='1.13 Data'!A6 | B13: ='1.13 Data'!B6 | H13: ='1.13 Data'!C6 | L13: ='1.13 Data'!E6
A14: ='1.13 Data'!A7 | B14: ='1.13 Data'!B7 | H14: ='1.13 Data'!C7 | L14: ='1.13 Data'!E7
A15: ='1.13 Data'!A8 | B15: ='1.13 Data'!B8 | H15: ='1.13 Data'!C8 | L15: ='1.13 Data'!E8
A16: ='1.13 Data'!A9 | B16: ='1.13 Data'!B9 | H16: ='1.13 Data'!C9 | L16: ='1.13 Data'!E9
A17: ='1.13 Data'!A10 | B17: ='1.13 Data'!B10 | H17: ='1.13 Data'!C10 | L17: ='1.13 Data'!E10
A18: ='1.13 Data'!A11 | B18: ='1.13 Data'!B11 | H18: ='1.13 Data'!C11 | L18: ='1.13 Data'!E11
A19: ='1.13 Data'!A12 | B19: ='1.13 Data'!B12 | H19: ='1.13 Data'!C12 | L19: ='1.13 Data'!E12
A20: ='1.13 Data'!A13 | B20: ='1.13 Data'!B13 | H20: ='1.13 Data'!C13 | L20: ='1.13 Data'!E13
A21: ='1.13 Data'!A14 | B21: ='1.13 Data'!B14 | H21: ='1.13 Data'!C14 | L21: ='1.13 Data'!E14
A22: ='1.13 Data'!A15 | B22: ='1.13 Data'!B15 | H22: ='1.13 Data'!C15 | L22: ='1.13 Data'!E15
A23: TOTAL / RESULT
A25: HOW TO WORK: navy-header columns are linked live from the dataset sheet — click any cell to see the formula. Gold-header columns are blank and shaded yellow — build the required formula there and copy it down every row, then complete the TOTAL / RESULT row at the foot.
A27: FURTHER REQUESTS ON THIS DATASET
A28: # | B28: Request | C28: Requested by | D28: Report / figure required | E28: Your formula or answer
A29: 1 | B29: Description field broken into reporting dimensions | C29: Actuarial Manager | D29: Three further columns: Client Name (before the first slash) | Product Description (between the first and second) | Status (after the last slash). Ten rows, one formula per column.
A30: 2 | B30: Branch Code Integrity Exception Report | C30: Head of Internal Audit | D30: An exception report: Line | Branch Code from Policy No | Branch Code from Client Code | Status (OK / Mismatch) | Premium at risk. Total premium at risk shown at the top.
A31: 3 | B31: Standardised record for loading to the new system | C31: Head of MIS | D31: A load file column in the format ClientCode|ProductCode|Branch|Status, built from your parsed columns, plus a length check flagging any row that is not the expected length.

Sheet 1.14 Data
A1: Dataset 1.14 — EDATE and EOMONTH
A2: Session 1: Advanced Lookup, Text & Date Functions | Part C: Advanced Date Functions | Adamjee Assurance Company Limited (Pakistan) — training data, figures in PKR
A4: Table A — Policies written, with term in months
A5: Policy No | B5: Client Name | C5: Product | D5: Inception Date | E5: Term (Months) | F5: Gross Premium (PKR)
A6: ADM-MTR-KHI-2024-1001 | B6: Gul Ahmed Textile Mills Ltd | C6: Motor | D6: 45306 | E6: 12 | F6: 985000
A7: ADM-MAR-KHI-2024-1003 | B7: Lucky Cement Limited | C7: Marine Cargo | D7: 45351 | E7: 6 | F7: 1640000
A8: ADM-ENG-FSD-2024-1005 | B8: Interloop Limited | C8: Engineering | D8: 45361 | E8: 36 | F8: 720000
A9: ADM-FIR-LHR-2024-1002 | B9: Nishat Mills Limited | C9: Fire & Property | D9: 45383 | E9: 12 | F9: 1210000
A10: ADM-HLT-ISB-2024-1004 | B10: Bilal Ahmed Khan | C10: Health | D10: 45443 | E10: 12 | F10: 205000
A11: ADM-TRV-KHI-2024-1007 | B11: Ahmed Raza Qureshi | C11: Travel | D11: 45461 | E11: 3 | F11: 148000
A12: ADM-MSC-PEW-2024-1008 | B12: Descon Engineering Ltd | C12: Miscellaneous | D12: 45535 | E12: 18 | F12: 640000
A13: ADM-MTR-LHR-2024-1006 | B13: Fatima Siddiqui | C13: Motor | D13: 45626 | E13: 12 | F13: 46800
A14: ADM-FIR-MUL-2024-1009 | B14: Fauji Fertilizer Company | C14: Fire & Property | D14: 45641 | E14: 24 | F14: 2310000
A16: Table B — Reporting parameters
A17: Parameter | B17: Value
A18: Accounting Close Date | B18: 45565
A19: Renewal notice lead time (months) | B19: -1
A20: Reporting Period | B20: Q3 2024
A22: Note: This is simulated training data modelled on Adamjee Assurance general insurance operations. It is not actual company data.

Sheet 1.14 Report
A1: ADAMJEE ASSURANCE COMPANY LIMITED
A2: Policy Expiry Schedule for the renewals team
A3: Prepared for: | B3: Manager, Renewals
A4: Prepared by:
A5: Reporting date: | B5: As at reporting date shown on the dataset
A7: Policy terms at Adamjee are written in months — 12-month motor, 6-month marine open cover, 36-month engineering. The renewals team currently adds 365 days to inception, which is why a 36-month CAR policy was chased for renewal thirty-four months early.
A9: Source data: '1.14 Data' (click to open)
A11: Navy headers below = data linked live from the dataset sheet. Gold headers = blank — build your formula here.
A12: Policy No | B12: Client | C12: Product | D12: Inception | E12: Term (months) | F12: Expiry Date | G12: Renewal Notice Date (one month before expiry)
A13: ='1.14 Data'!A6 | B13: ='1.14 Data'!B6 | C13: ='1.14 Data'!C6 | D13: ='1.14 Data'!D6 | E13: ='1.14 Data'!E6
A14: ='1.14 Data'!A7 | B14: ='1.14 Data'!B7 | C14: ='1.14 Data'!C7 | D14: ='1.14 Data'!D7 | E14: ='1.14 Data'!E7
A15: ='1.14 Data'!A8 | B15: ='1.14 Data'!B8 | C15: ='1.14 Data'!C8 | D15: ='1.14 Data'!D8 | E15: ='1.14 Data'!E8
A16: ='1.14 Data'!A9 | B16: ='1.14 Data'!B9 | C16: ='1.14 Data'!C9 | D16: ='1.14 Data'!D9 | E16: ='1.14 Data'!E9
A17: ='1.14 Data'!A10 | B17: ='1.14 Data'!B10 | C17: ='1.14 Data'!C10 | D17: ='1.14 Data'!D10 | E17: ='1.14 Data'!E10
A18: ='1.14 Data'!A11 | B18: ='1.14 Data'!B11 | C18: ='1.14 Data'!C11 | D18: ='1.14 Data'!D11 | E18: ='1.14 Data'!E11
A19: ='1.14 Data'!A12 | B19: ='1.14 Data'!B12 | C19: ='1.14 Data'!C12 | D19: ='1.14 Data'!D12 | E19: ='1.14 Data'!E12
A20: ='1.14 Data'!A13 | B20: ='1.14 Data'!B13 | C20: ='1.14 Data'!C13 | D20: ='1.14 Data'!D13 | E20: ='1.14 Data'!E13
A21: ='1.14 Data'!A14 | B21: ='1.14 Data'!B14 | C21: ='1.14 Data'!C14 | D21: ='1.14 Data'!D14 | E21: ='1.14 Data'!E14
A22: TOTAL / RESULT
A24: HOW TO WORK: navy-header columns are linked live from the dataset sheet — click any cell to see the formula. Gold-header columns are blank and shaded yellow — build the required formula there and copy it down every row, then complete the TOTAL / RESULT row at the foot.
A26: FURTHER REQUESTS ON THIS DATASET
A27: # | B27: Request | C27: Requested by | D27: Report / figure required | E27: Your formula or answer
A28: 1 | B28: Leap-year exception note for the Marine open cover | C28: Manager, Renewals | D28: A one-line written explanation of what EDATE returns for a 29-February inception and why, plus the expiry date you will confirm to the client.
A29: 2 | B29: Unearned Premium Reserve schedule as at 30 September | C29: Finance Manager — Technical Accounts | D29: A UPR schedule: Policy No | Inception | Accounting month-end of inception | Expiry | Months earned to 30 September | Months unearned | Unearned Premium (PKR). Amounts #,##0.
A30: 3 | B30: Q3 Expiry Count for the renewals resourcing plan | C30: Manager, Renewals | D30: A resourcing summary: expiries falling in July, August and September 2024 counted separately, with total premium at risk for each month and a quarter total.

Sheet 1.15 Data
A1: Dataset 1.15 — WORKDAY and WORKDAY.INTL
A2: Session 1: Advanced Lookup, Text & Date Functions | Part C: Advanced Date Functions | Adamjee Assurance Company Limited (Pakistan) — training data, figures in PKR
A4: Table A — Claims intimated, with SLA targets
A5: Claim No | B5: Branch | C5: Intimation Date | D5: Survey SLA (working days) | E5: Payment SLA (working days) | F5: Claimed Amount (PKR)
A6: CLM-KHI-2024-0501 | B6: Karachi Main | C6: 45385 | D6: 5 | E6: 10 | F6: 385000
A7: CLM-LHR-2024-0502 | B7: Lahore Gulberg | C7: 45390 | D7: 5 | E7: 10 | F7: 1240000
A8: CLM-ISB-2024-0503 | B8: Islamabad Blue Area | C8: 45455 | D8: 3 | E8: 7 | F8: 92500
A9: CLM-FSD-2024-0504 | B9: Faisalabad | C9: 45457 | D9: 5 | E9: 15 | F9: 660000
A10: CLM-MUL-2024-0505 | B10: Multan | C10: 45513 | D10: 5 | E10: 10 | F10: 208000
A11: CLM-KHI-2024-0506 | B11: Karachi Main | C11: 45516 | D11: 7 | E11: 12 | F11: 1875000
A12: CLM-PEW-2024-0507 | B12: Peshawar | C12: 45646 | D12: 5 | E12: 10 | F12: 445000
A13: CLM-HYD-2024-0508 | B13: Hyderabad | C13: 45650 | D13: 5 | E13: 10 | F13: 130000
A15: Table B — Pakistan public holidays 2024 (as observed by the company)
A16: Holiday | B16: Date
A17: Kashmir Day | B17: 45327
A18: Pakistan Day | B18: 45374
A19: Eid-ul-Fitr Day 1 | B19: 45392
A20: Eid-ul-Fitr Day 2 | B20: 45393
A21: Eid-ul-Fitr Day 3 | B21: 45394
A22: Labour Day | B22: 45413
A23: Eid-ul-Azha Day 1 | B23: 45460
A24: Eid-ul-Azha Day 2 | B24: 45461
A25: Eid-ul-Azha Day 3 | B25: 45462
A26: Ashura (9 Muharram) | B26: 45489
A27: Ashura (10 Muharram) | B27: 45490
A28: Independence Day | B28: 45518
... A31: Quaid-e-Azam Day / Christmas | B31: 45651
A33: Table C — Working week patterns
A34: Office | B34: Working Week | C34: WORKDAY.INTL weekend argument
A35: Karachi Head Office | B35: Monday to Friday | C35: 1 (Sat, Sun off)
A36: Regional branches | B36: Monday to Saturday | C36: 11 (Sunday only off)
A37: Bancassurance desk | B37: Sunday to Thursday | C37: 7 (Fri, Sat off)
A39: Note: This is simulated training data modelled on Adamjee Assurance general insurance operations. It is not actual company data.

Sheet 1.15 Report
A1: ADAMJEE ASSURANCE COMPANY LIMITED
A2: Claims SLA Tracker — survey report due dates
A3: Prepared for: | B3: Head of Claims Operations
A4: Prepared by:
A5: Reporting date: | B5: As at reporting date shown on the dataset
A7: The claims SLA is measured in working days, not calendar days. The current tracker adds five calendar days, so every claim intimated before a weekend or an Eid holiday shows as breached when it is not. The Service Quality Committee has been shown a breach rate that is wrong for three months running.
A9: Source data: '1.15 Data' (click to open)
A11: Navy headers below = data linked live from the dataset sheet. Gold headers = blank — build your formula here.
A12: Claim No | B12: Branch | C12: Intimation Date | D12: Survey SLA days | E12: Survey Report Due (working days
A13: ='1.15 Data'!A6 | B13: ='1.15 Data'!B6 | C13: ='1.15 Data'!C6
A14: ='1.15 Data'!A7 | B14: ='1.15 Data'!B7 | C14: ='1.15 Data'!C7
A15: ='1.15 Data'!A8 | B15: ='1.15 Data'!B8 | C15: ='1.15 Data'!C8
A16: ='1.15 Data'!A9 | B16: ='1.15 Data'!B9 | C16: ='1.15 Data'!C9
A17: ='1.15 Data'!A10 | B17: ='1.15 Data'!B10 | C17: ='1.15 Data'!C10
A18: ='1.15 Data'!A11 | B18: ='1.15 Data'!B11 | C18: ='1.15 Data'!C11
A19: ='1.15 Data'!A12 | B19: ='1.15 Data'!B12 | C19: ='1.15 Data'!C12
A20: ='1.15 Data'!A13 | B20: ='1.15 Data'!B13 | C20: ='1.15 Data'!C13
A21: TOTAL / RESULT
A23: HOW TO WORK: navy-header columns are linked live from the dataset sheet — click any cell to see the formula. Gold-header columns are blank and shaded yellow — build the required formula there and copy it down every row, then complete the TOTAL / RESULT row at the foot.
A25: FURTHER REQUESTS ON THIS DATASET
A26: # | B26: Request | C26: Requested by | D26: Report / figure required | E26: Your formula or answer
A27: 1 | B27: Eid impact analysis for the Service Quality Committee | C27: Head of Claims Operations | D27: An impact table: Claim No | Intimation Date | Working-day due date | Calendar days consumed | Holidays falling inside the window. Covering the Eid-ul-Fitr, Eid-ul-Azha and Muharram claims.
A28: 2 | B28: Cheque Release Forecast for Treasury | C28: Treasury Manager | D28: A release forecast: Claim No | Claimed Amount | Survey Report Due | Payment SLA days | Cheque Release Date | Week of release. Sorted by release date, with a weekly cash requirement total.
A29: 3 | B29: Regional branch SLA under a six-day working week | C29: Regional Head — Central | D29: A comparison for claim 0507 (intimated 20-Dec-2024) showing the five working-day due date under all three working weeks: Head Office (Sat/Sun off), Regional (Sunday only off), Bancassurance (Fri/Sat off).

Sheet 1.16 Data
A1: Dataset 1.16 — WEEKNUM
A2: Session 1: Advanced Lookup, Text & Date Functions | Part C: Advanced Date Functions | Adamjee Assurance Company Limited (Pakistan) — training data, figures in PKR
A4: Table A — Claim intimations, Adamjee Assurance 2024
A5: Claim No | B5: Branch | C5: Product | D5: Intimation Date | E5: Claimed Amount (PKR) | F5: Claim Status
A6: CLM-KHI-2024-0501 | B6: Karachi Main | C6: Fire & Property | D6: 45767 | E6: 366000 | F6: Settled
A7: CLM-LHR-2024-0502 | B7: Lahore Gulberg | C7: Travel | D7: 45643 | E7: 2562000 | F7: Settled
A8: CLM-ISB-2024-0503 | B8: Islamabad Blue Area | C8: Motor | D8: 45735 | E8: 995000 | F8: Settled
A9: CLM-FSD-2024-0504 | B9: Faisalabad | C9: Health | D9: 45716 | E9: 3419000 | F9: Settled
A10: CLM-MUL-2024-0505 | B10: Multan | C10: Miscellaneous | D10: 45801 | E10: 80000 | F10: Settled
A11: CLM-PEW-2024-0506 | B11: Peshawar | C11: Marine Cargo | D11: 45672 | E11: 5265000 | F11: Under Survey
A12: CLM-QTA-2024-0507 | B12: Quetta | C12: Engineering | D12: 45760 | E12: 3655000 | F12: Settled
A13: CLM-HYD-2024-0508 | B13: Hyderabad | C13: Fire & Property | D13: 45662 | E13: 3102000 | F13: Settled
A14: CLM-SKT-2024-0509 | B14: Sialkot | C14: Travel | D14: 45536 | E14: 245000 | F14: Repudiated
A15: CLM-RWP-2024-0510 | B15: Rawalpindi | C15: Motor | D15: 45495 | E15: 10182000 | F15: Under Survey
A16: CLM-KHI-2024-0511 | B16: Karachi Main | C16: Health | D16: 45747 | E16: 18655000 | F16: Settled
A17: CLM-LHR-2024-0512 | B17: Lahore Gulberg | C17: Miscellaneous | D17: 45529 | E17: 5214000 | F17: Repudiated
... A35: CLM-RWP-2024-0530 | B35: Rawalpindi | C35: Travel | D35: 45370 | E35: 5330000 | F35: Repudiated
A37: Table B — Week numbering convention
A38: Convention | B38: return_type argument | C38: Used by
A39: Week begins Sunday | B39: 1 | C39: Default Excel / US convention
A40: Week begins Monday | B40: 2 | C40: Adamjee MIS standard
A41: ISO 8601 week | B41: 21 | C41: Reinsurance treaty reporting
A43: Note: This is simulated training data modelled on Adamjee Assurance general insurance operations. It is not actual company data.

Sheet 1.16 Report
A1: ADAMJEE ASSURANCE COMPANY LIMITED
A2: Convention reconciliation for the reinsurance treaty return
A3: Prepared for: | B3: Head of Reinsurance
A4: Prepared by:
A5: Reporting date: | B5: As at reporting date shown on the dataset
A7: The treaty return to the reinsurer must use ISO 8601 weeks. Adamjee MIS uses Monday-start weeks and the default Excel export uses Sunday-start. Three claims fell into a different week in each version last quarter and the reinsurer queried the return.
A9: Source data: '1.16 Data' (click to open)
A11: Navy headers below = data linked live from the dataset sheet. Gold headers = blank — build your formula here.
A12: Claim No | B12: Intimation Date | C12: Week (Sunday convention) | D12: Week (Monday convention) | E12: Week (ISO 8601) | F12: Flag where the three disagree
A13: ='1.16 Data'!A6 | B13: ='1.16 Data'!D6
A14: ='1.16 Data'!A7 | B14: ='1.16 Data'!D7
A15: ='1.16 Data'!A8 | B15: ='1.16 Data'!D8
A16: ='1.16 Data'!A9 | B16: ='1.16 Data'!D9
A17: ='1.16 Data'!A10 | B17: ='1.16 Data'!D10
A18: ='1.16 Data'!A11 | B18: ='1.16 Data'!D11
A19: ='1.16 Data'!A12 | B19: ='1.16 Data'!D12
A20: ='1.16 Data'!A13 | B20: ='1.16 Data'!D13
A21: ='1.16 Data'!A14 | B21: ='1.16 Data'!D14
A22: ='1.16 Data'!A15 | B22: ='1.16 Data'!D15
A23: ='1.16 Data'!A16 | B23: ='1.16 Data'!D16
A24: ='1.16 Data'!A17 | B24: ='1.16 Data'!D17
... A42: ='1.16 Data'!A35 | B42: ='1.16 Data'!D35
A43: TOTAL / RESULT
A45: HOW TO WORK: navy-header columns are linked live from the dataset sheet — click any cell to see the formula. Gold-header columns are blank and shaded yellow — build the required formula there and copy it down every row, then complete the TOTAL / RESULT row at the foot.
A47: FURTHER REQUESTS ON THIS DATASET
A48: # | B48: Request | C48: Requested by | D48: Report / figure required | E48: Your formula or answer
A49: 1 | B49: Weekly Claims Intimation Trend | C49: Manager, Motor Claims | D49: A weekly trend table: Week Number | Week label (2024-W28 format) | Claims Intimated | Total Claimed Amount | Average Claim Size. Sorted by week, with the peak week highlighted.
A50: 2 | B50: Surveyor capacity plan for the top three weeks | C50: Head of Claims Operations | D50: A capacity note: the top three weeks by total claimed amount, each with week label, claim count, total claimed, and a one-line recommendation on surveyor capacity for those weeks.
A51: 3 | B51: Method note for the Claims Manager | C51: Manager, Motor Claims | D51: A three-line note comparing weekly and monthly bucketing for claims analysis, using a specific example from the data where the monthly view hid something the weekly view showed.

Sheet 1.17 Data
A1: Dataset 1.17 — Complex Date Calculations for Policy Lifecycle and Renewal Tracking
A2: Session 1: Advanced Lookup, Text & Date Functions | Part C: Advanced Date Functions | Adamjee Assurance Company Limited (Pakistan) — training data, figures in PKR
A4: Table A — In-force policy register
A5: Policy No | B5: Client Name | C5: Branch | D5: Product | E5: Inception Date | F5: Term (Months) | G5: Gross Premium (PKR) | H5: Auto-Renew Flag
A6: ADM-FIR-KHI-2024-1001 | B6: Gul Ahmed Textile Mills Ltd | C6: Karachi Main | D6: Fire & Property | E6: 44941 | F6: 12 | G6: 96000 | H6: No
A7: ADM-TRV-LHR-2024-1002 | B7: Packages Limited | C7: Lahore Gulberg | D7: Travel | E7: 45026 | F7: 12 | G7: 201000 | H7: Yes
A8: ADM-MTR-ISB-2024-1003 | B8: Bilal Ahmed Khan | C8: Islamabad Blue Area | D8: Motor | E8: 45099 | F8: 12 | G8: 1397000 | H8: Yes
A9: ADM-HLT-FSD-2024-1004 | B9: Attock Refinery Limited | C9: Faisalabad | D9: Health | E9: 45204 | F9: 12 | G9: 305000 | H9: No
A10: ADM-MSC-MUL-2024-1005 | B10: Descon Engineering Ltd | C10: Multan | D10: Miscellaneous | E10: 45235 | F10: 12 | G10: 75000 | H10: Yes
A11: ADM-MAR-PEW-2024-1006 | B11: Hina Farooq | C11: Peshawar | D11: Marine Cargo | E11: 45245 | F11: 12 | G11: 380000 | H11: Yes
A12: ADM-ENG-QTA-2024-1007 | B12: Indus Motor Company Ltd | C12: Quetta | D12: Engineering | E12: 45263 | F12: 12 | G12: 227000 | H12: No
A13: ADM-FIR-HYD-2024-1008 | B13: Nishat Mills Limited | C13: Hyderabad | D13: Fire & Property | E13: 45275 | F13: 12 | G13: 290000 | H13: Yes
A14: ADM-TRV-SKT-2024-1009 | B14: Imran Aslam Sheikh | C14: Sialkot | D14: Travel | E14: 45288 | F14: 12 | G14: 37000 | H14: Yes
A15: ADM-MTR-RWP-2024-1010 | B15: Engro Polymer & Chemicals | C15: Rawalpindi | D15: Motor | E15: 45424 | F15: 12 | G15: 760000 | H15: No
A16: ADM-HLT-KHI-2024-1011 | B16: Interloop Limited | C16: Karachi Main | D16: Health | E16: 45507 | F16: 12 | G16: 603000 | H16: Yes
A17: ADM-MSC-LHR-2024-1012 | B17: Mehwish Anwar | C17: Lahore Gulberg | D17: Miscellaneous | E17: 45412 | F17: 12 | G17: 512000 | H17: Yes
... A27: ADM-FIR-LHR-2024-1022 | B27: Packages Limited | C27: Lahore Gulberg | D27: Fire & Property | E27: 45343 | F27: 12 | G27: 368000 | H27: No
A29: Table B — Tracker parameters
A30: Parameter | B30: Value
A31: Reporting Date | B31: 45596
A32: Grace Period (days) | B32: 30
A33: Renewal Notice Lead (working days) | B33: 15
A34: Cancellation Date (for refund test) | B34: 45616
A36: Table C — Public holidays 2024 (extract)
A37: Holiday | B37: Date
A38: Independence Day | B38: 45518
A39: Eid Milad-un-Nabi | B39: 45551
A40: Iqbal Day | B40: 45605
A41: Quaid-e-Azam Day | B41: 45651
A43: Note: This is simulated training data modelled on Adamjee Assurance general insurance operations. It is not actual company data.

Sheet 1.17 Report
A1: ADAMJEE ASSURANCE COMPANY LIMITED
A2: Live Renewal Tracker as at 31 October
A3: Prepared for: | B3: Manager, Renewals
A4: Prepared by:
A5: Reporting date: | B5: As at reporting date shown on the dataset
A7: The renewals unit works from four separate spreadsheets: one for expiries, one for the grace period, one for the call list and one for cancellations. The four disagree, and in September a corporate client worth PKR 2.3 million in premium lapsed because it appeared on none of them.
A9: Source data: '1.17 Data' (click to open)
A11: Navy headers below = data linked live from the dataset sheet. Gold headers = blank — build your formula here.
A12: Policy No | B12: Client | C12: Branch | D12: Inception | E12: Expiry | F12: Days to Expiry at the reporting date | G12: Lifecycle Status (Expired / In Grace / Renewal Due / In Force)
A13: ='1.17 Data'!A6 | B13: ='1.17 Data'!B6 | C13: ='1.17 Data'!C6 | D13: ='1.17 Data'!E6
A14: ='1.17 Data'!A7 | B14: ='1.17 Data'!B7 | C14: ='1.17 Data'!C7 | D14: ='1.17 Data'!E7
A15: ='1.17 Data'!A8 | B15: ='1.17 Data'!B8 | C15: ='1.17 Data'!C8 | D15: ='1.17 Data'!E8
A16: ='1.17 Data'!A9 | B16: ='1.17 Data'!B9 | C16: ='1.17 Data'!C9 | D16: ='1.17 Data'!E9
A17: ='1.17 Data'!A10 | B17: ='1.17 Data'!B10 | C17: ='1.17 Data'!C10 | D17: ='1.17 Data'!E10
A18: ='1.17 Data'!A11 | B18: ='1.17 Data'!B11 | C18: ='1.17 Data'!C11 | D18: ='1.17 Data'!E11
A19: ='1.17 Data'!A12 | B19: ='1.17 Data'!B12 | C19: ='1.17 Data'!C12 | D19: ='1.17 Data'!E12
A20: ='1.17 Data'!A13 | B20: ='1.17 Data'!B13 | C20: ='1.17 Data'!C13 | D20: ='1.17 Data'!E13
A21: ='1.17 Data'!A14 | B21: ='1.17 Data'!B14 | C21: ='1.17 Data'!C14 | D21: ='1.17 Data'!E14
A22: ='1.17 Data'!A15 | B22: ='1.17 Data'!B15 | C22: ='1.17 Data'!C15 | D22: ='1.17 Data'!E15
A23: ='1.17 Data'!A16 | B23: ='1.17 Data'!B16 | C23: ='1.17 Data'!C16 | D23: ='1.17 Data'!E16
A24: ='1.17 Data'!A17 | B24: ='1.17 Data'!B17 | C24: ='1.17 Data'!C17 | D24: ='1.17 Data'!E17
... A34: ='1.17 Data'!A27 | B34: ='1.17 Data'!B27 | C34: ='1.17 Data'!C27 | D34: ='1.17 Data'!E27
A35: TOTAL / RESULT
A37: HOW TO WORK: navy-header columns are linked live from the dataset sheet — click any cell to see the formula. Gold-header columns are blank and shaded yellow — build the required formula there and copy it down every row, then complete the TOTAL / RESULT row at the foot.
A39: FURTHER REQUESTS ON THIS DATASET
A40: # | B40: Request | C40: Requested by | D40: Report / figure required | E40: Your formula or answer
A41: 1 | B41: Renewal Call List by urgency bucket | C41: Team Leader, Renewals Call Centre | D41: A call list bucketed as 0-15 days / 16-30 days / 31-60 days / over 60 days, showing count of policies and total premium at risk in each bucket, and the detail list sorted with the most urgent first.
A42: 2 | B42: Renewal Notice Despatch Deadlines | C42: Manager, Renewals | D42: A despatch schedule: Policy No | Expiry Date | Notice Deadline (15 working days before expiry, excluding public holidays) | Days remaining from the reporting date | Flag 'Despatch now' where the deadline is within seven days.
A43: 3 | B43: Pro-rata Cancellation Refund Schedule | C43: Finance Manager — Premium Accounting | D43: A refund schedule: Policy No | Gross Premium | Expiry | Unexpired Days at the cancellation date | Unexpired proportion | Pro-rata Refund (PKR). Total refund shown at the foot. Amounts #,##0.
A44: 4 | B44: November Renewal Forecast for the Board pack | C44: Chief Financial Officer | D44: A forecast block: renewals falling in November 2024 split by auto-renew flag, with count, premium, weighted premium at the two certainty factors, and a single forecast total for the Board.

Sheet 2.1 Data
A1: Dataset 2.1 — Understanding Array Formulas in Excel 2016
A2: Session 2: Array Formulas, Advanced Logic & Named Ranges | Part A: Array Formulas (Ctrl+Shift+Enter) | Adamjee Assurance Company Limited (Pakistan) — training data, figures in PKR
A4: Table A — Underwriting extract 2024 (no helper columns allowed)
A5: Policy No | B5: Branch | C5: Product | D5: Sum Insured (PKR) | E5: Rate | F5: Claims Paid (PKR) | G5: Policy Status
A6: ADM-FIR-KHI-2024-1001 | B6: Karachi Main | C6: Fire & Property | D6: 4500000 | E6: 0.02133 | F6: 96262 | G6: Active
A7: ADM-TRV-LHR-2024-1002 | B7: Lahore Gulberg | C7: Travel | D7: 12000000 | E7: 0.01675 | F7: 111595 | G7: Active
A8: ADM-MTR-ISB-2024-1003 | B8: Islamabad Blue Area | C8: Motor | D8: 65000000 | E8: 0.02149 | F8: 1436098 | G8: Active
A9: ADM-HLT-FSD-2024-1004 | B9: Faisalabad | C9: Health | D9: 18500000 | E9: 0.01649 | F9: 185930 | G9: Cancelled
A10: ADM-MSC-MUL-2024-1005 | B10: Multan | C10: Miscellaneous | D10: 4500000 | E10: 0.01667 | F10: 44061 | G10: Active
A11: ADM-MAR-PEW-2024-1006 | B11: Peshawar | C11: Marine Cargo | D11: 25000000 | E11: 0.0152 | F11: 91249 | G11: Active
A12: ADM-ENG-QTA-2024-1007 | B12: Quetta | C12: Engineering | D12: 18500000 | E12: 0.01227 | F12: 78775 | G12: Active
A13: ADM-FIR-HYD-2024-1008 | B13: Hyderabad | C13: Fire & Property | D13: 25000000 | E13: 0.0116 | F13: 249183 | G13: Renewed
A14: ADM-TRV-SKT-2024-1009 | B14: Sialkot | C14: Travel | D14: 7500000 | E14: 0.00493 | F14: 48145 | G14: Active
A15: ADM-MTR-RWP-2024-1010 | B15: Rawalpindi | C15: Motor | D15: 65000000 | E15: 0.01169 | F15: 162016 | G15: Cancelled
A16: ADM-HLT-KHI-2024-1011 | B16: Karachi Main | C16: Health | D16: 90000000 | E16: 0.0067 | F16: 595704 | G16: Active
A17: ADM-MSC-LHR-2024-1012 | B17: Lahore Gulberg | C17: Miscellaneous | D17: 40000000 | E17: 0.0128 | F17: 394713 | G17: Active
... A33: ADM-ENG-HYD-2024-1028 | B33: Hyderabad | C33: Engineering | D33: 4500000 | E33: 0.006 | F33: 22858 | G33: Active
A35: Note: This is simulated training data modelled on Adamjee Assurance general insurance operations. It is not actual company data.

Sheet 2.1 Report
A1: ADAMJEE ASSURANCE COMPANY LIMITED
A2: Premium Reconstruction on a locked MIS extract
A3: Prepared for: | B3: Head of Management Reporting
A4: Prepared by:
A5: Reporting date: | B5: As at reporting date shown on the dataset
A7: The MIS extract arrives locked: sum insured and rate on every row, no premium column, and IT will not add one because the sheet is system-generated. The month-end pack needs the premium total in ninety minutes and the current workaround is to copy the file, add a column and hope nobody notices the numbers came from a different file than the one on the server.
A9: Source data: '2.1 Data' (click to open)
A11: DELIVERABLE CHECKLIST
A12: # | B12: Deliverable | C12: Report specification | D12: Requested by | E12: Done?
A13: 1 | B13: Premium Reconstruction on a locked MIS extract | C13: A summary block computed from the locked extract with no helper columns: Total Gross Premium | Largest single-policy premium | Number of policies above PKR 500,000. Each figure in one cell, amounts #,##0. | D13: Head of Management Reporting
A14: 2 | B14: Entry-method defect note for the reporting runbook | C14: A runbook entry, in the yellow box, recording: what the formula returns when entered with Enter, what appears in the formula bar when entered correctly, and what F9 on the multiplication segment reveals. | D14: Head of MIS
A15: 3 | B15: Performance warning for the 200,000-row claims file | C15: A two-line performance note explaining the cost of whole-column array references in a large file and the specific change you would make to the formula before it is used on the claims data. | D15: Head of MIS
A17: BUILD YOUR REPORT / OUTPUT BELOW (pivot, chart, macro output, or model — as required above)
A33: HOW TO WORK: build the requested output in the blank area above (or insert a pivot table / chart / macro-driven control here), tick each deliverable off in the checklist, and record any formula or setting worth remembering in the specification column.

Sheet 2.2 Data
A1: Dataset 2.2 — Single-Cell Array Formulas for Multi-Criteria Calculations
A2: Session 2: Array Formulas, Advanced Logic & Named Ranges | Part A: Array Formulas (Ctrl+Shift+Enter) | Adamjee Assurance Company Limited (Pakistan) — training data, figures in PKR
A4: Table A — Underwriting extract 2024
A5: Policy No | B5: Branch | C5: Region | D5: Product | E5: Channel | F5: Month | G5: Sum Insured (PKR) | H5: Gross Premium (PKR) | I5: Claims Paid (PKR) | J5: Commission % | K5: Policy Status
A6: ADM-FIR-KHI-2024-1001 | B6: Karachi Main | C6: South | D6: Fire & Property | E6: Direct | F6: Jan-2024 | G6: 4500000 | H6: 96000 | I6: 96262 | J6: 0.15 | K6: Active
A7: ADM-TRV-LHR-2024-1002 | B7: Lahore Gulberg | C7: Central | D7: Travel | E7: Agency | F7: Feb-2024 | G7: 12000000 | H7: 201000 | I7: 111595 | J7: 0.175 | K7: Active
A8: ADM-MTR-ISB-2024-1003 | B8: Islamabad Blue Area | C8: North | D8: Motor | E8: Bancassurance | F8: Mar-2024 | G8: 65000000 | H8: 1397000 | I8: 1436098 | J8: 0.125 | K8: Active
A9: ADM-HLT-FSD-2024-1004 | B9: Faisalabad | C9: Central | D9: Health | E9: Corporate | F9: Apr-2024 | G9: 18500000 | H9: 305000 | I9: 185930 | J9: 0.125 | K9: Cancelled
A10: ADM-MSC-MUL-2024-1005 | B10: Multan | C10: Central | D10: Miscellaneous | E10: Direct | F10: May-2024 | G10: 4500000 | H10: 75000 | I10: 44061 | J10: 0.175 | K10: Active
A11: ADM-MAR-PEW-2024-1006 | B11: Peshawar | C11: North | D11: Marine Cargo | E11: Agency | F11: Jun-2024 | G11: 25000000 | H11: 380000 | I11: 91249 | J11: 0.125 | K11: Active
A12: ADM-ENG-QTA-2024-1007 | B12: Quetta | C12: South | D12: Engineering | E12: Bancassurance | F12: Jul-2024 | G12: 18500000 | H12: 227000 | I12: 78775 | J12: 0.125 | K12: Active
A13: ADM-FIR-HYD-2024-1008 | B13: Hyderabad | C13: South | D13: Fire & Property | E13: Corporate | F13: Aug-2024 | G13: 25000000 | H13: 290000 | I13: 249183 | J13: 0.125 | K13: Renewed
A14: ADM-TRV-SKT-2024-1009 | B14: Sialkot | C14: Central | D14: Travel | E14: Direct | F14: Sep-2024 | G14: 7500000 | H14: 37000 | I14: 48145 | J14: 0.125 | K14: Active
A15: ADM-MTR-RWP-2024-1010 | B15: Rawalpindi | C15: North | D15: Motor | E15: Agency | F15: Oct-2024 | G15: 65000000 | H15: 760000 | I15: 162016 | J15: 0.2 | K15: Cancelled
A16: ADM-HLT-KHI-2024-1011 | B16: Karachi Main | C16: South | D16: Health | E16: Bancassurance | F16: Nov-2024 | G16: 90000000 | H16: 603000 | I16: 595704 | J16: 0.2 | K16: Active
A17: ADM-MSC-LHR-2024-1012 | B17: Lahore Gulberg | C17: Central | D17: Miscellaneous | E17: Corporate | F17: Dec-2024 | G17: 40000000 | H17: 512000 | I17: 394713 | J17: 0.125 | K17: Active
... A41: ADM-FIR-PEW-2024-1036 | B41: Peshawar | C41: North | D41: Fire & Property | E41: Corporate | F41: Dec-2024 | G41: 4500000 | H41: 113000 | I41: 125166 | J41: 0.125 | K41: Active
A43: Table B — Criteria block (change these and the answers must update)
A44: Criteria | B44: Value
A45: Branch | B45: Karachi Main
A46: Product | B46: Motor
A47: Channel | B47: Bancassurance
A48: Region | B48: South
A49: Policy Status | B49: Active
A50: Premium threshold (PKR) | B50: 300000
A52: Note: This is simulated training data modelled on Adamjee Assurance general insurance operations. It is not actual company data.

Sheet 2.2 Report
A1: ADAMJEE ASSURANCE COMPANY LIMITED
A2: Regional Head query panel — three-criteria premium
A3: Prepared for: | B3: Regional Head — South
A4: Prepared by:
A5: Reporting date: | B5: As at reporting date shown on the dataset
A7: The Regional Head asks for single figures with several conditions attached, usually during a call: premium for Motor in the South written through Agency, then the same for Bancassurance, then for a different branch. Each request currently means a new filter and a new manual SUM, and two of last month's answers disagreed with the pack.
A9: Source data: '2.2 Data' (click to open)
A11: DELIVERABLE CHECKLIST
A12: # | B12: Deliverable | C12: Report specification | D12: Requested by | E12: Done?
A13: 1 | B13: Regional Head query panel — three-criteria premium | C13: A query panel with criteria cells for Branch, Product, Channel, Region, Status and a premium threshold, feeding: Total Premium | Policy Count | Average Premium. Changing any criteria cell must refresh all three without editing a formula. | D13: Regional Head — South
A14: 2 | B14: Combined Motor and Health exposure figure | C14: A single cell returning combined Motor and Health premium, with the two product names taken from cells so the definition of 'personal lines' can be changed without touching the formula. | D14: Chief Underwriting Officer
A15: 3 | B15: Large-risk register above the underwriting threshold | C15: A register summary: policies above the threshold cell AND with status Active — count, total premium, average premium, and the same three figures for the rest of the book for comparison. | D15: Chief Underwriting Officer
A16: 4 | B16: Panel acceptance test before release to four Regional Heads | C16: Evidence of the acceptance test: change the branch criteria cell, record the before and after figures for all three outputs, and confirm no formula was edited. State how you proved no criterion is hard-coded. | D16: Head of MIS
A18: BUILD YOUR REPORT / OUTPUT BELOW (pivot, chart, macro output, or model — as required above)
A34: HOW TO WORK: build the requested output in the blank area above (or insert a pivot table / chart / macro-driven control here), tick each deliverable off in the checklist, and record any formula or setting worth remembering in the specification column.

Sheet 2.3 Data
A1: Dataset 2.3 — Multi-Cell Array Formulas
A2: Session 2: Array Formulas, Advanced Logic & Named Ranges | Part A: Array Formulas (Ctrl+Shift+Enter) | Adamjee Assurance Company Limited (Pakistan) — training data, figures in PKR
A4: Table A — Gross premium book
A5: Policy No | B5: Branch | C5: Product | D5: Gross Premium (PKR) | E5: Commission % | F5: Claims Paid (PKR)
A6: ADM-FIR-KHI-2024-1001 | B6: Karachi Main | C6: Fire & Property | D6: 96000 | E6: 0.15 | F6: 96262
A7: ADM-TRV-LHR-2024-1002 | B7: Lahore Gulberg | C7: Travel | D7: 201000 | E7: 0.175 | F7: 111595
A8: ADM-MTR-ISB-2024-1003 | B8: Islamabad Blue Area | C8: Motor | D8: 1397000 | E8: 0.125 | F8: 1436098
A9: ADM-HLT-FSD-2024-1004 | B9: Faisalabad | C9: Health | D9: 305000 | E9: 0.125 | F9: 185930
A10: ADM-MSC-MUL-2024-1005 | B10: Multan | C10: Miscellaneous | D10: 75000 | E10: 0.175 | F10: 44061
A11: ADM-MAR-PEW-2024-1006 | B11: Peshawar | C11: Marine Cargo | D11: 380000 | E11: 0.125 | F11: 91249
A12: ADM-ENG-QTA-2024-1007 | B12: Quetta | C12: Engineering | D12: 227000 | E12: 0.125 | F12: 78775
A13: ADM-FIR-HYD-2024-1008 | B13: Hyderabad | C13: Fire & Property | D13: 290000 | E13: 0.125 | F13: 249183
A14: ADM-TRV-SKT-2024-1009 | B14: Sialkot | C14: Travel | D14: 37000 | E14: 0.125 | F14: 48145
A15: ADM-MTR-RWP-2024-1010 | B15: Rawalpindi | C15: Motor | D15: 760000 | E15: 0.2 | F15: 162016
A16: ADM-HLT-KHI-2024-1011 | B16: Karachi Main | C16: Health | D16: 603000 | E16: 0.2 | F16: 595704
A17: ADM-MSC-LHR-2024-1012 | B17: Lahore Gulberg | C17: Miscellaneous | D17: 512000 | E17: 0.125 | F17: 394713
... A33: ADM-ENG-HYD-2024-1028 | B33: Hyderabad | C33: Engineering | D33: 27000 | E33: 0.2 | F33: 22858
A35: Table B — Statutory deductions
A36: Item | B36: Rate
A37: Federal Insurance Fee | B37: 0.01
A38: Stamp Duty | B38: 0.0015
A39: Sindh Sales Tax | B39: 0.13
A41: Note: This is simulated training data modelled on Adamjee Assurance general insurance operations. It is not actual company data.

Sheet 2.3 Report
A1: ADAMJEE ASSURANCE COMPANY LIMITED
A2: Net Premium Book for the technical accounts
A3: Prepared for: | B3: Finance Manager — Technical Accounts
A4: Prepared by:
A5: Reporting date: | B5: As at reporting date shown on the dataset
A7: Net premium is gross less commission less federal insurance fee less stamp duty. The column is currently a normal formula copied down and last quarter a branch user overtyped four rows with values pasted from an email. The technical accounts were out by PKR 1.4 million and the difference took two days to find.
A9: Source data: '2.3 Data' (click to open)
A11: DELIVERABLE CHECKLIST
A12: # | B12: Deliverable | C12: Report specification | D12: Requested by | E12: Done?
A13: 1 | B13: Net Premium Book for the technical accounts | C13: A twenty-eight row Net Premium column entered as a single multi-cell array so no individual row can be overwritten, with the statutory rates taken from the deductions table rather than typed. | D13: Finance Manager — Technical Accounts
A14: 2 | B14: Loss Ratio column with the same protection | C14: A twenty-eight row Loss Ratio column, also entered as a multi-cell array, formatted 0.0%, returning a dash rather than an error where gross premium is zero. | D14: Finance Manager — Technical Accounts
A15: 3 | B15: Integrity evidence for the audit file | C15: Audit evidence in the yellow box: the exact message Excel shows when a single cell is edited, the keystroke that selects the entire array, and the correct procedure for deleting and rebuilding it. | D15: Head of Internal Audit
A16: 4 | B16: Control design note — array versus copied formula | C16: A two-line recommendation stating one advantage and one drawback of multi-cell arrays against a normal copied-down formula, with specific reference to what happens when a new policy row is inserted. | D16: Head of Internal Audit
A18: BUILD YOUR REPORT / OUTPUT BELOW (pivot, chart, macro output, or model — as required above)
A34: HOW TO WORK: build the requested output in the blank area above (or insert a pivot table / chart / macro-driven control here), tick each deliverable off in the checklist, and record any formula or setting worth remembering in the specification column.

Sheet 2.4 Data
A1: Dataset 2.4 — SUM with IF Array for Conditional Totals
A2: Session 2: Array Formulas, Advanced Logic & Named Ranges | Part A: Array Formulas (Ctrl+Shift+Enter) | Adamjee Assurance Company Limited (Pakistan) — training data, figures in PKR
A4: Table A — Underwriting extract 2024
A5: Policy No | B5: Branch | C5: Region | D5: Product | E5: Channel | F5: Month | G5: Sum Insured (PKR) | H5: Gross Premium (PKR) | I5: Claims Paid (PKR) | J5: Commission % | K5: Policy Status
A6: ADM-FIR-KHI-2024-1001 | B6: Karachi Main | C6: South | D6: Fire & Property | E6: Direct | F6: Jan-2024 | G6: 4500000 | H6: 96000 | I6: 96262 | J6: 0.15 | K6: Active
A7: ADM-TRV-LHR-2024-1002 | B7: Lahore Gulberg | C7: Central | D7: Travel | E7: Agency | F7: Feb-2024 | G7: 12000000 | H7: 201000 | I7: 111595 | J7: 0.175 | K7: Active
A8: ADM-MTR-ISB-2024-1003 | B8: Islamabad Blue Area | C8: North | D8: Motor | E8: Bancassurance | F8: Mar-2024 | G8: 65000000 | H8: 1397000 | I8: 1436098 | J8: 0.125 | K8: Active
A9: ADM-HLT-FSD-2024-1004 | B9: Faisalabad | C9: Central | D9: Health | E9: Corporate | F9: Apr-2024 | G9: 18500000 | H9: 305000 | I9: 185930 | J9: 0.125 | K9: Cancelled
A10: ADM-MSC-MUL-2024-1005 | B10: Multan | C10: Central | D10: Miscellaneous | E10: Direct | F10: May-2024 | G10: 4500000 | H10: 75000 | I10: 44061 | J10: 0.175 | K10: Active
A11: ADM-MAR-PEW-2024-1006 | B11: Peshawar | C11: North | D11: Marine Cargo | E11: Agency | F11: Jun-2024 | G11: 25000000 | H11: 380000 | I11: 91249 | J11: 0.125 | K11: Active
A12: ADM-ENG-QTA-2024-1007 | B12: Quetta | C12: South | D12: Engineering | E12: Bancassurance | F12: Jul-2024 | G12: 18500000 | H12: 227000 | I12: 78775 | J12: 0.125 | K12: Active
A13: ADM-FIR-HYD-2024-1008 | B13: Hyderabad | C13: South | D13: Fire & Property | E13: Corporate | F13: Aug-2024 | G13: 25000000 | H13: 290000 | I13: 249183 | J13: 0.125 | K13: Renewed
A14: ADM-TRV-SKT-2024-1009 | B14: Sialkot | C14: Central | D14: Travel | E14: Direct | F14: Sep-2024 | G14: 7500000 | H14: 37000 | I14: 48145 | J14: 0.125 | K14: Active
A15: ADM-MTR-RWP-2024-1010 | B15: Rawalpindi | C15: North | D15: Motor | E15: Agency | F15: Oct-2024 | G15: 65000000 | H15: 760000 | I15: 162016 | J15: 0.2 | K15: Cancelled
A16: ADM-HLT-KHI-2024-1011 | B16: Karachi Main | C16: South | D16: Health | E16: Bancassurance | F16: Nov-2024 | G16: 90000000 | H16: 603000 | I16: 595704 | J16: 0.2 | K16: Active
A17: ADM-MSC-LHR-2024-1012 | B17: Lahore Gulberg | C17: Central | D17: Miscellaneous | E17: Corporate | F17: Dec-2024 | G17: 40000000 | H17: 512000 | I17: 394713 | J17: 0.125 | K17: Active
... A41: ADM-FIR-PEW-2024-1036 | B41: Peshawar | C41: North | D41: Fire & Property | E41: Corporate | F41: Dec-2024 | G41: 4500000 | H41: 113000 | I41: 125166 | J41: 0.125 | K41: Active
A43: Table B — Criteria
A44: Criteria | B44: Value
A45: Branch | B45: Karachi Main
A46: Product | B46: Fire & Property
A47: Region | B47: South
A48: Quarter start month | B48: Jan-2024
A49: Quarter end month | B49: Mar-2024
A51: Note: This is simulated training data modelled on Adamjee Assurance general insurance operations. It is not actual company data.

Sheet 2.4 Report
A1: ADAMJEE ASSURANCE COMPANY LIMITED
A2: Above-average producer analysis
A3: Prepared for: | B3: Head of Agency Distribution
A4: Prepared by:
A5: Reporting date: | B5: As at reporting date shown on the dataset
A7: The commission review asks which policies in each branch are written above that branch's own average premium, because those are the accounts worth defending at renewal. SUMIFS cannot answer it, so the analysis has been done branch by branch with manual filters and has not been refreshed since March.
A9: Source data: '2.4 Data' (click to open)
A11: DELIVERABLE CHECKLIST
A12: # | B12: Deliverable | C12: Report specification | D12: Requested by | E12: Done?
A13: 1 | B13: Above-average producer analysis | C13: An analysis block per branch: Branch | Total Premium | Average Premium | Total Premium of policies above that branch average | Count of those policies | Share of branch premium they represent. | D13: Head of Agency Distribution
A14: 2 | B14: Q1 premium total on an inherited workbook | C14: A reconciliation showing the Q1 total for the selected branch and product computed two ways — with SUM(IF()) and with SUMIFS — and the difference between them, which must be zero. | D14: Head of Management Reporting
A15: 3 | B15: Claims total excluding cancelled policies | C15: A claims figure excluding every policy with status Cancelled, shown alongside the unadjusted total and the difference, so the adjustment is visible to the reviewer. | D15: Finance Manager — Technical Accounts
A16: 4 | B16: Modernisation recommendation | C16: A two-line recommendation naming the one situation in this workbook where SUM(IF()) must be kept, and why SUMIFS cannot replace it there. | D16: Head of MIS
A18: BUILD YOUR REPORT / OUTPUT BELOW (pivot, chart, macro output, or model — as required above)
A34: HOW TO WORK: build the requested output in the blank area above (or insert a pivot table / chart / macro-driven control here), tick each deliverable off in the checklist, and record any formula or setting worth remembering in the specification column.

Sheet 2.5 Data
A1: Dataset 2.5 — COUNT and AVERAGE with Array Conditions
A2: Session 2: Array Formulas, Advanced Logic & Named Ranges | Part A: Array Formulas (Ctrl+Shift+Enter) | Adamjee Assurance Company Limited (Pakistan) — training data, figures in PKR
A4: Table A — Underwriting extract 2024
A5: Policy No | B5: Branch | C5: Region | D5: Product | E5: Channel | F5: Month | G5: Sum Insured (PKR) | H5: Gross Premium (PKR) | I5: Claims Paid (PKR) | J5: Commission % | K5: Policy Status
A6: ADM-FIR-KHI-2024-1001 | B6: Karachi Main | C6: South | D6: Fire & Property | E6: Direct | F6: Jan-2024 | G6: 4500000 | H6: 96000 | I6: 96262 | J6: 0.15 | K6: Active
A7: ADM-TRV-LHR-2024-1002 | B7: Lahore Gulberg | C7: Central | D7: Travel | E7: Agency | F7: Feb-2024 | G7: 12000000 | H7: 201000 | I7: 111595 | J7: 0.175 | K7: Active
A8: ADM-MTR-ISB-2024-1003 | B8: Islamabad Blue Area | C8: North | D8: Motor | E8: Bancassurance | F8: Mar-2024 | G8: 65000000 | H8: 1397000 | I8: 1436098 | J8: 0.125 | K8: Active
A9: ADM-HLT-FSD-2024-1004 | B9: Faisalabad | C9: Central | D9: Health | E9: Corporate | F9: Apr-2024 | G9: 18500000 | H9: 305000 | I9: 185930 | J9: 0.125 | K9: Cancelled
A10: ADM-MSC-MUL-2024-1005 | B10: Multan | C10: Central | D10: Miscellaneous | E10: Direct | F10: May-2024 | G10: 4500000 | H10: 75000 | I10: 44061 | J10: 0.175 | K10: Active
A11: ADM-MAR-PEW-2024-1006 | B11: Peshawar | C11: North | D11: Marine Cargo | E11: Agency | F11: Jun-2024 | G11: 25000000 | H11: 380000 | I11: 91249 | J11: 0.125 | K11: Active
A12: ADM-ENG-QTA-2024-1007 | B12: Quetta | C12: South | D12: Engineering | E12: Bancassurance | F12: Jul-2024 | G12: 18500000 | H12: 227000 | I12: 78775 | J12: 0.125 | K12: Active
A13: ADM-FIR-HYD-2024-1008 | B13: Hyderabad | C13: South | D13: Fire & Property | E13: Corporate | F13: Aug-2024 | G13: 25000000 | H13: 290000 | I13: 249183 | J13: 0.125 | K13: Renewed
A14: ADM-TRV-SKT-2024-1009 | B14: Sialkot | C14: Central | D14: Travel | E14: Direct | F14: Sep-2024 | G14: 7500000 | H14: 37000 | I14: 48145 | J14: 0.125 | K14: Active
A15: ADM-MTR-RWP-2024-1010 | B15: Rawalpindi | C15: North | D15: Motor | E15: Agency | F15: Oct-2024 | G15: 65000000 | H15: 760000 | I15: 162016 | J15: 0.2 | K15: Cancelled
A16: ADM-HLT-KHI-2024-1011 | B16: Karachi Main | C16: South | D16: Health | E16: Bancassurance | F16: Nov-2024 | G16: 90000000 | H16: 603000 | I16: 595704 | J16: 0.2 | K16: Active
A17: ADM-MSC-LHR-2024-1012 | B17: Lahore Gulberg | C17: Central | D17: Miscellaneous | E17: Corporate | F17: Dec-2024 | G17: 40000000 | H17: 512000 | I17: 394713 | J17: 0.125 | K17: Active
... A41: ADM-FIR-PEW-2024-1036 | B41: Peshawar | C41: North | D41: Fire & Property | E41: Corporate | F41: Dec-2024 | G41: 4500000 | H41: 113000 | I41: 125166 | J41: 0.125 | K41: Active
A43: Table B — Criteria
A44: Criteria | B44: Value
A45: Product | B45: Health
A46: Channel | B46: Bancassurance
A47: Loss ratio breach level | B47: 0.8
A48: Region | B48: South
A50: Note: This is simulated training data modelled on Adamjee Assurance general insurance operations. It is not actual company data.

Sheet 2.5 Report
A1: ADAMJEE ASSURANCE COMPANY LIMITED
A2: Bancassurance Channel Review pack
A3: Prepared for: | B3: Head of Bancassurance
A4: Prepared by:
A5: Reporting date: | B5: As at reporting date shown on the dataset
A7: The half-yearly channel review needs counts and averages that the standard conditional functions cannot express. The pack was assembled last time by exporting to a pivot, copying the results and typing them into the slides, and two numbers did not tie back.
A9: Source data: '2.5 Data' (click to open)
A11: DELIVERABLE CHECKLIST
A12: # | B12: Deliverable | C12: Report specification | D12: Requested by | E12: Done?
A13: 1 | B13: Bancassurance Channel Review pack | C13: A review block for the selected product and channel: Policy Count | Average Premium | Distinct branches selling the product | Count of policies breaching the loss ratio level. All four from formulas on the live extract. | D13: Head of Bancassurance
A14: 2 | B14: Top-five accounts and the trimmed average | C14: Three figures side by side: headline average premium | average of the top five policies | average excluding the single largest and single smallest policy. Each clearly labelled. | D14: Chief Underwriting Officer
A15: 3 | B15: Regional outperformer count | C15: A single figure with its supporting detail: count of policies in the selected region above that region's average premium, the region average itself, and the same count expressed as a percentage of regional policies. | D15: Regional Head — South
A17: BUILD YOUR REPORT / OUTPUT BELOW (pivot, chart, macro output, or model — as required above)
A33: HOW TO WORK: build the requested output in the blank area above (or insert a pivot table / chart / macro-driven control here), tick each deliverable off in the checklist, and record any formula or setting worth remembering in the specification column.

Sheet 2.6 Data
A1: Dataset 2.6 — Nested IF (Advanced Multi-Level Logic)
A2: Session 2: Array Formulas, Advanced Logic & Named Ranges | Part B: Advanced Logical and Math Functions | Adamjee Assurance Company Limited (Pakistan) — training data, figures in PKR
A4: Table A — Agent production for the month
A5: Agent Code | B5: Agent Name | C5: Branch | D5: Channel | E5: GWP Generated (PKR) | F5: Claims on Portfolio (PKR) | G5: Policies Sold | H5: Years of Service
A6: AG-KHI-011 | B6: Tariq Jameel | C6: Karachi Main | D6: Agency | E6: 36067428 | F6: 22742422 | G6: 267 | H6: 9
A7: AG-LHR-012 | B7: Nadia Hassan | C7: Lahore Gulberg | D7: Direct | E7: 11808410 | F7: 11990618 | G7: 166 | H7: 6.7
A8: AG-ISB-013 | B8: Salman Shah | C8: Islamabad Blue Area | D8: Corporate | E8: 9727848 | F8: 7017049 | G8: 104 | H8: 9.9
A9: AG-FSD-014 | B9: Komal Bashir | C9: Faisalabad | D9: Bancassurance | E9: 24841593 | F9: 16283806 | G9: 189 | H9: 7.6
A10: AG-MUL-015 | B10: Waqar Younis Khan | C10: Multan | D10: Corporate | E10: 37268616 | F10: 31678323 | G10: 294 | H10: 13.2
A11: AG-PEW-016 | B11: Amna Zubair | C11: Peshawar | D11: Bancassurance | E11: 8145792 | F11: 9848948 | G11: 64 | H11: 3.2
A12: AG-QTA-017 | B12: Rizwan Ali Soomro | C12: Quetta | D12: Bancassurance | E12: 36601299 | F12: 24675724 | G12: 301 | H12: 3.2
A13: AG-HYD-018 | B13: Farhan Dar | C13: Hyderabad | D13: Bancassurance | E13: 5947392 | F13: 2739203 | G13: 128 | H13: 6.3
A14: AG-SKT-019 | B14: Sobia Naz | C14: Sialkot | D14: Direct | E14: 23102794 | F14: 27954225 | G14: 286 | H14: 2.5
A15: AG-RWP-020 | B15: Junaid Akram | C15: Rawalpindi | D15: Bancassurance | E15: 11738760 | F15: 10174344 | G15: 264 | H15: 6.2
A16: AG-KHI-021 | B16: Hamid Raza | C16: Karachi Main | D16: Corporate | E16: 11335950 | F16: 5067218 | G16: 90 | H16: 10.2
A17: AG-LHR-022 | B17: Nimra Saleem | C17: Lahore Gulberg | D17: Agency | E17: 32916646 | F17: 33321403 | G17: 317 | H17: 2.6
A19: Table B — Commission slab scheme (editable)
A20: GWP From (PKR) | B20: GWP To (PKR) | C20: Commission Rate | D20: Slab Name
A21: 0 | B21: 4999999 | C21: 0.075 | D21: Bronze
A22: 5000000 | B22: 9999999 | C22: 0.1 | D22: Silver
A23: 10000000 | B23: 19999999 | C23: 0.13 | D23: Gold
A24: 20000000 | B24: 999999999 | C24: 0.16 | D24: Platinum
A26: Table C — Risk grading rules
A27: Loss Ratio | B27: Grade | C27: Action
A28: Below 40% | B28: A | C28: Full bonus
A29: 40% to below 60% | B29: B | C29: Standard bonus
A30: 60% to below 80% | B30: C | C30: Bonus withheld
A31: 80% and above | B31: D | C31: Portfolio review
A33: Note: This is simulated training data modelled on Adamjee Assurance general insurance operations. It is not actual company data.

Sheet 2.6 Report
A1: ADAMJEE ASSURANCE COMPANY LIMITED
A2: Monthly Agent Commission Statement
A3: Prepared for: | B3: Head of Agency Distribution
A4: Prepared by:
A5: Reporting date: | B5: As at reporting date shown on the dataset
A7: Twelve hundred agents are paid on a four-tier slab scheme. The scheme changes twice a year and the current statement has the rates typed inside the formulas, so the January change took an analyst three days and two agents were paid on the old rate for a further month.
A9: Source data: '2.6 Data' (click to open)
A11: Navy headers below = data linked live from the dataset sheet. Gold headers = blank — build your formula here.
A12: Agent Code | B12: Name | C12: Branch | D12: GWP Generated | E12: Slab Name | F12: Commission Rate | G12: Commission Payable
A13: ='2.6 Data'!A6 | B13: ='2.6 Data'!B6 | C13: ='2.6 Data'!C6 | D13: ='2.6 Data'!E6
A14: ='2.6 Data'!A7 | B14: ='2.6 Data'!B7 | C14: ='2.6 Data'!C7 | D14: ='2.6 Data'!E7
A15: ='2.6 Data'!A8 | B15: ='2.6 Data'!B8 | C15: ='2.6 Data'!C8 | D15: ='2.6 Data'!E8
A16: ='2.6 Data'!A9 | B16: ='2.6 Data'!B9 | C16: ='2.6 Data'!C9 | D16: ='2.6 Data'!E9
A17: ='2.6 Data'!A10 | B17: ='2.6 Data'!B10 | C17: ='2.6 Data'!C10 | D17: ='2.6 Data'!E10
A18: ='2.6 Data'!A11 | B18: ='2.6 Data'!B11 | C18: ='2.6 Data'!C11 | D18: ='2.6 Data'!E11
A19: ='2.6 Data'!A12 | B19: ='2.6 Data'!B12 | C19: ='2.6 Data'!C12 | D19: ='2.6 Data'!E12
A20: ='2.6 Data'!A13 | B20: ='2.6 Data'!B13 | C20: ='2.6 Data'!C13 | D20: ='2.6 Data'!E13
A21: ='2.6 Data'!A14 | B21: ='2.6 Data'!B14 | C21: ='2.6 Data'!C14 | D21: ='2.6 Data'!E14
A22: ='2.6 Data'!A15 | B22: ='2.6 Data'!B15 | C22: ='2.6 Data'!C15 | D22: ='2.6 Data'!E15
A23: ='2.6 Data'!A16 | B23: ='2.6 Data'!B16 | C23: ='2.6 Data'!C16 | D23: ='2.6 Data'!E16
A24: ='2.6 Data'!A17 | B24: ='2.6 Data'!B17 | C24: ='2.6 Data'!C17 | D24: ='2.6 Data'!E17
A25: TOTAL / RESULT
A27: HOW TO WORK: navy-header columns are linked live from the dataset sheet — click any cell to see the formula. Gold-header columns are blank and shaded yellow — build the required formula there and copy it down every row, then complete the TOTAL / RESULT row at the foot.
A29: FURTHER REQUESTS ON THIS DATASET
A30: # | B30: Request | C30: Requested by | D30: Report / figure required | E30: Your formula or answer
A31: 1 | B31: Agent Portfolio Risk Grading | C31: Chief Underwriting Officer | D31: A grading column: Agent | Loss Ratio | Grade A to D per the published rules | Bonus Action. Grades derived by formula from the loss ratio, with the rule boundaries in cells.
A32: 2 | B32: Seniority override for long-service agents | C32: Head of Agency Distribution | D32: The grading column with the seniority override applied, plus a flag column showing which agents the override actually changed and by how many grades.
A33: 3 | B33: Scheme change impact assessment | C33: Chief Financial Officer | D33: An impact summary: total commission payable under the current scheme, under a scheme where every rate rises by one percentage point, and the difference in rupees and per cent. Achieved by changing the scheme table only.
A34: 4 | B34: Method note for the payroll handover | C34: Head of Agency Distribution | D34: A two-line note recommending nested IF or VLOOKUP approximate match for the slab, with your reasoning, and one sentence on what happens if the nested IF tests are written in the wrong order.

Sheet 2.7 Data
A1: Dataset 2.7 — AND, OR Combined with IF
A2: Session 2: Array Formulas, Advanced Logic & Named Ranges | Part B: Advanced Logical and Math Functions | Adamjee Assurance Company Limited (Pakistan) — training data, figures in PKR
A4: Table A — Renewal review file
A5: Policy No | B5: Branch | C5: Product | D5: Sum Insured (PKR) | E5: Gross Premium (PKR) | F5: Claims Count | G5: Claims Paid (PKR) | H5: Years with Adamjee | I5: Premium Outstanding (PKR) | J5: Survey Report on File
A6: ADM-FIR-KHI-2024-1001 | B6: Karachi Main | C6: Fire & Property | D6: 4500000 | E6: 96000 | F6: 0 | G6: 96262 | H6: 9 | I6: 620000 | J6: No
A7: ADM-TRV-LHR-2024-1002 | B7: Lahore Gulberg | C7: Travel | D7: 12000000 | E7: 201000 | F7: 0 | G7: 111595 | H7: 10 | I7: 620000 | J7: Yes
A8: ADM-MTR-ISB-2024-1003 | B8: Islamabad Blue Area | C8: Motor | D8: 65000000 | E8: 1397000 | F8: 5 | G8: 1436098 | H8: 4 | I8: 620000 | J8: No
A9: ADM-HLT-FSD-2024-1004 | B9: Faisalabad | C9: Health | D9: 18500000 | E9: 305000 | F9: 1 | G9: 185930 | H9: 3 | I9: 0 | J9: Yes
A10: ADM-MSC-MUL-2024-1005 | B10: Multan | C10: Miscellaneous | D10: 4500000 | E10: 75000 | F10: 3 | G10: 44061 | H10: 3 | I10: 180000 | J10: Yes
A11: ADM-MAR-PEW-2024-1006 | B11: Peshawar | C11: Marine Cargo | D11: 25000000 | E11: 380000 | F11: 2 | G11: 91249 | H11: 12 | I11: 0 | J11: No
A12: ADM-ENG-QTA-2024-1007 | B12: Quetta | C12: Engineering | D12: 18500000 | E12: 227000 | F12: 5 | G12: 78775 | H12: 6 | I12: 45000 | J12: Yes
A13: ADM-FIR-HYD-2024-1008 | B13: Hyderabad | C13: Fire & Property | D13: 25000000 | E13: 290000 | F13: 3 | G13: 249183 | H13: 4 | I13: 45000 | J13: Yes
A14: ADM-TRV-SKT-2024-1009 | B14: Sialkot | C14: Travel | D14: 7500000 | E14: 37000 | F14: 0 | G14: 48145 | H14: 9 | I14: 620000 | J14: Yes
A15: ADM-MTR-RWP-2024-1010 | B15: Rawalpindi | C15: Motor | D15: 65000000 | E15: 760000 | F15: 0 | G15: 162016 | H15: 7 | I15: 0 | J15: Yes
A16: ADM-HLT-KHI-2024-1011 | B16: Karachi Main | C16: Health | D16: 90000000 | E16: 603000 | F16: 5 | G16: 595704 | H16: 4 | I16: 0 | J16: Yes
A17: ADM-MSC-LHR-2024-1012 | B17: Lahore Gulberg | C17: Miscellaneous | D17: 40000000 | E17: 512000 | F17: 4 | G17: 394713 | H17: 3 | I17: 620000 | J17: Yes
... A31: ADM-MSC-PEW-2024-1026 | B31: Peshawar | C31: Miscellaneous | D31: 7500000 | E31: 193000 | F31: 1 | G31: 17765 | H31: 3 | I31: 45000 | J31: No
A33: Table B — Underwriting rules (editable thresholds)
A34: Rule | B34: Threshold
A35: Max Sum Insured for branch authority (PKR) | B35: 25000000
A36: Max claims count for auto-renewal | B36: 2
A37: Max loss ratio for auto-renewal | B37: 0.6
A38: Min years with Adamjee | B38: 2
A39: Max premium outstanding allowed (PKR) | B39: 0
A41: Note: This is simulated training data modelled on Adamjee Assurance general insurance operations. It is not actual company data.

Sheet 2.7 Report
A1: ADAMJEE ASSURANCE COMPANY LIMITED
A2: Renewal Authority Decision Report
A3: Prepared for: | B3: Chief Underwriting Officer
A4: Prepared by:
A5: Reporting date: | B5: As at reporting date shown on the dataset
A7: Renewal authority is rule-based and written in the underwriting manual, but applied by judgement at the branch. An audit sample found eleven renewals granted outside branch authority, three of which later produced claims above the branch's retention.
A9: Source data: '2.7 Data' (click to open)
A11: Navy headers below = data linked live from the dataset sheet. Gold headers = blank — build your formula here.
A12: Policy No | B12: Branch | C12: Sum Insured | D12: Claims Count | E12: Loss Ratio | F12: Years with Adamjee | G12: Decision (Auto-Renew / Refer / Decline)
A13: ='2.7 Data'!A6 | B13: ='2.7 Data'!B6 | C13: ='2.7 Data'!D6 | D13: ='2.7 Data'!F6 | F13: ='2.7 Data'!H6
A14: ='2.7 Data'!A7 | B14: ='2.7 Data'!B7 | C14: ='2.7 Data'!D7 | D14: ='2.7 Data'!F7 | F14: ='2.7 Data'!H7
A15: ='2.7 Data'!A8 | B15: ='2.7 Data'!B8 | C15: ='2.7 Data'!D8 | D15: ='2.7 Data'!F8 | F15: ='2.7 Data'!H8
A16: ='2.7 Data'!A9 | B16: ='2.7 Data'!B9 | C16: ='2.7 Data'!D9 | D16: ='2.7 Data'!F9 | F16: ='2.7 Data'!H9
A17: ='2.7 Data'!A10 | B17: ='2.7 Data'!B10 | C17: ='2.7 Data'!D10 | D17: ='2.7 Data'!F10 | F17: ='2.7 Data'!H10
A18: ='2.7 Data'!A11 | B18: ='2.7 Data'!B11 | C18: ='2.7 Data'!D11 | D18: ='2.7 Data'!F11 | F18: ='2.7 Data'!H11
A19: ='2.7 Data'!A12 | B19: ='2.7 Data'!B12 | C19: ='2.7 Data'!D12 | D19: ='2.7 Data'!F12 | F19: ='2.7 Data'!H12
A20: ='2.7 Data'!A13 | B20: ='2.7 Data'!B13 | C20: ='2.7 Data'!D13 | D20: ='2.7 Data'!F13 | F20: ='2.7 Data'!H13
A21: ='2.7 Data'!A14 | B21: ='2.7 Data'!B14 | C21: ='2.7 Data'!D14 | D21: ='2.7 Data'!F14 | F21: ='2.7 Data'!H14
A22: ='2.7 Data'!A15 | B22: ='2.7 Data'!B15 | C22: ='2.7 Data'!D15 | D22: ='2.7 Data'!F15 | F22: ='2.7 Data'!H15
A23: ='2.7 Data'!A16 | B23: ='2.7 Data'!B16 | C23: ='2.7 Data'!D16 | D23: ='2.7 Data'!F16 | F23: ='2.7 Data'!H16
A24: ='2.7 Data'!A17 | B24: ='2.7 Data'!B17 | C24: ='2.7 Data'!D17 | D24: ='2.7 Data'!F17 | F24: ='2.7 Data'!H17
... A38: ='2.7 Data'!A31 | B38: ='2.7 Data'!B31 | C38: ='2.7 Data'!D31 | D38: ='2.7 Data'!F31 | F38: ='2.7 Data'!H31
A39: TOTAL / RESULT
A41: HOW TO WORK: navy-header columns are linked live from the dataset sheet — click any cell to see the formula. Gold-header columns are blank and shaded yellow — build the required formula there and copy it down every row, then complete the TOTAL / RESULT row at the foot.
A43: FURTHER REQUESTS ON THIS DATASET
A44: # | B44: Request | C44: Requested by | D44: Report / figure required | E44: Your formula or answer
A45: 1 | B45: Head Office Referral Schedule | C45: Manager, Head Office Underwriting | D45: A referral schedule listing only the referred policies, with a Reason column naming which rule triggered the referral (premium outstanding / no survey report / loss ratio above 100%), and a count by reason.
A46: 2 | B46: Motor South survey rule | C46: Chief Underwriting Officer | D46: The decision report with the new rule applied, plus a comparison column showing which policies changed decision as a result and the premium those policies represent.
A47: 3 | B47: Threshold sensitivity for the Underwriting Committee | C47: Chief Underwriting Officer | D47: A sensitivity summary: policies in each decision category at 60%, at 50%, and the movement between them, produced by changing one cell only.

Sheet 2.8 Data
A1: Dataset 2.8 — CHOOSE Function
A2: Session 2: Array Formulas, Advanced Logic & Named Ranges | Part B: Advanced Logical and Math Functions | Adamjee Assurance Company Limited (Pakistan) — training data, figures in PKR
A4: Table A — Policy transactions
A5: Policy No | B5: Branch | C5: Product | D5: Transaction Date | E5: Month No | F5: Product Group No | G5: Gross Premium (PKR) | H5: Claims Paid (PKR) | I5: Commission (PKR)
A6: ADM-FIR-KHI-2024-1001 | B6: Karachi Main | C6: Fire & Property | D6: 45294 | E6: 1 | F6: 1 | G6: 96000 | H6: 96262 | I6: 14400
A7: ADM-TRV-LHR-2024-1002 | B7: Lahore Gulberg | C7: Travel | D7: 45326 | E7: 2 | F7: 2 | G7: 201000 | H7: 111595 | I7: 35175
A8: ADM-MTR-ISB-2024-1003 | B8: Islamabad Blue Area | C8: Motor | D8: 45356 | E8: 3 | F8: 3 | G8: 1397000 | H8: 1436098 | I8: 174625
A9: ADM-HLT-FSD-2024-1004 | B9: Faisalabad | C9: Health | D9: 45388 | E9: 4 | F9: 4 | G9: 305000 | H9: 185930 | I9: 38125
A10: ADM-MSC-MUL-2024-1005 | B10: Multan | C10: Miscellaneous | D10: 45419 | E10: 5 | F10: 5 | G10: 75000 | H10: 44061 | I10: 13125
A11: ADM-MAR-PEW-2024-1006 | B11: Peshawar | C11: Marine Cargo | D11: 45451 | E11: 6 | F11: 1 | G11: 380000 | H11: 91249 | I11: 47500
A12: ADM-ENG-QTA-2024-1007 | B12: Quetta | C12: Engineering | D12: 45482 | E12: 7 | F12: 2 | G12: 227000 | H12: 78775 | I12: 28375
A13: ADM-FIR-HYD-2024-1008 | B13: Hyderabad | C13: Fire & Property | D13: 45514 | E13: 8 | F13: 3 | G13: 290000 | H13: 249183 | I13: 36250
A14: ADM-TRV-SKT-2024-1009 | B14: Sialkot | C14: Travel | D14: 45546 | E14: 9 | F14: 4 | G14: 37000 | H14: 48145 | I14: 4625
A15: ADM-MTR-RWP-2024-1010 | B15: Rawalpindi | C15: Motor | D15: 45577 | E15: 10 | F15: 5 | G15: 760000 | H15: 162016 | I15: 152000
A16: ADM-HLT-KHI-2024-1011 | B16: Karachi Main | C16: Health | D16: 45609 | E16: 11 | F16: 1 | G16: 603000 | H16: 595704 | I16: 120600
A17: ADM-MSC-LHR-2024-1012 | B17: Lahore Gulberg | C17: Miscellaneous | D17: 45640 | E17: 12 | F17: 2 | G17: 512000 | H17: 394713 | I17: 64000
... A29: ADM-MTR-FSD-2024-1024 | B29: Faisalabad | C29: Motor | D29: 45652 | E29: 12 | F29: 4 | G29: 2304000 | H29: 2938527 | I29: 460800
A31: Table B — Department mapping (by Product Group No)
A32: Group No | B32: Department
A33: 1 | B33: Motor Underwriting
A34: 2 | B34: Property & Engineering
A35: 3 | B35: Marine & Transport
A36: 4 | B36: Health & Life Benefits
A37: 5 | B37: Special Risks
A39: Table C — Report switch
A40: Control | B40: Value
A41: Measure number (1=GWP, 2=Claims, 3=Commission, 4=Loss Ratio) | B41: 2
A42: Financial year starts in month | B42: 7
A44: Note: This is simulated training data modelled on Adamjee Assurance general insurance operations. It is not actual company data.

Sheet 2.8 Report
A1: ADAMJEE ASSURANCE COMPANY LIMITED
A2: Financial Quarter mapping for the July year-end
A3: Prepared for: | B3: Finance Manager — Technical Accounts
A4: Prepared by:
A5: Reporting date: | B5: As at reporting date shown on the dataset
A7: Adamjee reports internally on a July to June financial year while the transaction file carries calendar months. The mapping is done with a lookup table that a colleague maintains and which was last corrected after the December pack went out on calendar quarters.
A9: Source data: '2.8 Data' (click to open)
A11: DELIVERABLE CHECKLIST
A12: # | B12: Deliverable | C12: Report specification | D12: Requested by | E12: Done?
A13: 1 | B13: Financial Quarter mapping for the July year-end | C13: A transaction extract with two extra columns: Calendar Quarter and Financial Quarter (July start). Both produced by formula from the month number, with no lookup table. | D13: Finance Manager — Technical Accounts
A14: 2 | B14: Departmental allocation of premium | C14: An allocation column returning the department name from the product group number without referencing any lookup table, plus a departmental premium summary built on it. | D14: Head of Management Reporting
A15: 3 | B15: One-cell Measure Switch for the CFO summary | C15: A single summary cell driven by the measure number in the control table, returning total GWP, total claims, total commission or the overall loss ratio, correctly formatted for whichever measure is selected. | D15: Chief Financial Officer
A16: 4 | B16: Weekday profile of policy bookings | C16: A weekday profile: Day name | Policies booked | Total premium | Average premium, covering all transactions, with the day name derived by formula from the date. | D16: Head of Operations
A18: BUILD YOUR REPORT / OUTPUT BELOW (pivot, chart, macro output, or model — as required above)
A34: HOW TO WORK: build the requested output in the blank area above (or insert a pivot table / chart / macro-driven control here), tick each deliverable off in the checklist, and record any formula or setting worth remembering in the specification column.

Sheet 2.9 Data
A1: Dataset 2.9 — SUMPRODUCT for Multi-Criteria Summing and Counting
A2: Session 2: Array Formulas, Advanced Logic & Named Ranges | Part B: Advanced Logical and Math Functions | Adamjee Assurance Company Limited (Pakistan) — training data, figures in PKR
A4: Table A — Underwriting extract 2024
A5: Policy No | B5: Branch | C5: Region | D5: Product | E5: Channel | F5: Month | G5: Sum Insured (PKR) | H5: Gross Premium (PKR) | I5: Claims Paid (PKR) | J5: Commission % | K5: Policy Status
A6: ADM-FIR-KHI-2024-1001 | B6: Karachi Main | C6: South | D6: Fire & Property | E6: Direct | F6: Jan-2024 | G6: 4500000 | H6: 96000 | I6: 96262 | J6: 0.15 | K6: Active
A7: ADM-TRV-LHR-2024-1002 | B7: Lahore Gulberg | C7: Central | D7: Travel | E7: Agency | F7: Feb-2024 | G7: 12000000 | H7: 201000 | I7: 111595 | J7: 0.175 | K7: Active
A8: ADM-MTR-ISB-2024-1003 | B8: Islamabad Blue Area | C8: North | D8: Motor | E8: Bancassurance | F8: Mar-2024 | G8: 65000000 | H8: 1397000 | I8: 1436098 | J8: 0.125 | K8: Active
A9: ADM-HLT-FSD-2024-1004 | B9: Faisalabad | C9: Central | D9: Health | E9: Corporate | F9: Apr-2024 | G9: 18500000 | H9: 305000 | I9: 185930 | J9: 0.125 | K9: Cancelled
A10: ADM-MSC-MUL-2024-1005 | B10: Multan | C10: Central | D10: Miscellaneous | E10: Direct | F10: May-2024 | G10: 4500000 | H10: 75000 | I10: 44061 | J10: 0.175 | K10: Active
A11: ADM-MAR-PEW-2024-1006 | B11: Peshawar | C11: North | D11: Marine Cargo | E11: Agency | F11: Jun-2024 | G11: 25000000 | H11: 380000 | I11: 91249 | J11: 0.125 | K11: Active
A12: ADM-ENG-QTA-2024-1007 | B12: Quetta | C12: South | D12: Engineering | E12: Bancassurance | F12: Jul-2024 | G12: 18500000 | H12: 227000 | I12: 78775 | J12: 0.125 | K12: Active
A13: ADM-FIR-HYD-2024-1008 | B13: Hyderabad | C13: South | D13: Fire & Property | E13: Corporate | F13: Aug-2024 | G13: 25000000 | H13: 290000 | I13: 249183 | J13: 0.125 | K13: Renewed
A14: ADM-TRV-SKT-2024-1009 | B14: Sialkot | C14: Central | D14: Travel | E14: Direct | F14: Sep-2024 | G14: 7500000 | H14: 37000 | I14: 48145 | J14: 0.125 | K14: Active
A15: ADM-MTR-RWP-2024-1010 | B15: Rawalpindi | C15: North | D15: Motor | E15: Agency | F15: Oct-2024 | G15: 65000000 | H15: 760000 | I15: 162016 | J15: 0.2 | K15: Cancelled
A16: ADM-HLT-KHI-2024-1011 | B16: Karachi Main | C16: South | D16: Health | E16: Bancassurance | F16: Nov-2024 | G16: 90000000 | H16: 603000 | I16: 595704 | J16: 0.2 | K16: Active
A17: ADM-MSC-LHR-2024-1012 | B17: Lahore Gulberg | C17: Central | D17: Miscellaneous | E17: Corporate | F17: Dec-2024 | G17: 40000000 | H17: 512000 | I17: 394713 | J17: 0.125 | K17: Active
... A41: ADM-FIR-PEW-2024-1036 | B41: Peshawar | C41: North | D41: Fire & Property | E41: Corporate | F41: Dec-2024 | G41: 4500000 | H41: 113000 | I41: 125166 | J41: 0.125 | K41: Active
A43: Table B — Criteria
A44: Criteria | B44: Value
A45: Region | B45: Central
A46: Product | B46: Motor
A47: Channel | B47: Direct
A48: Status | B48: Active
A49: Premium threshold (PKR) | B49: 250000
A51: Note: This is simulated training data modelled on Adamjee Assurance general insurance operations. It is not actual company data.

Sheet 2.9 Report
A1: ADAMJEE ASSURANCE COMPANY LIMITED
A2: Portfolio Weighted Average Rate for the reinsurance submission
A3: Prepared for: | B3: Head of Reinsurance
A4: Prepared by:
A5: Reporting date: | B5: As at reporting date shown on the dataset
A7: The treaty renewal submission must show the portfolio's weighted average rate. Last year a simple average of the individual policy rates was submitted, which overweighted hundreds of small personal policies and understated the rate the reinsurer was actually being asked to accept. The reinsurer's actuary found it.
A9: Source data: '2.9 Data' (click to open)
A11: DELIVERABLE CHECKLIST
A12: # | B12: Deliverable | C12: Report specification | D12: Requested by | E12: Done?
A13: 1 | B13: Portfolio Weighted Average Rate for the reinsurance submission | C13: A rate schedule: Total Sum Insured | Total Gross Premium | Weighted Average Rate | Simple Average Rate | Difference. Rates shown to three decimal places with a one-line note on which is correct for the submission. | D13: Head of Reinsurance
A14: 2 | B14: Regional segment figures without array entry | C14: A segment block for the selected region and product: Total Premium | Policy Count | Average Premium | Overall Loss Ratio. Every figure built without Ctrl+Shift+Enter so it survives being copied anywhere. | D14: Head of MIS
A15: 3 | B15: Personal lines exposure with an OR condition | C15: A personal lines figure combining the selected products, built so that adding a third product means adding one condition rather than rewriting the formula. | D15: Chief Underwriting Officer
A16: 4 | B16: Defect report on the mismatched range | C16: A defect note: reproduce the error by pointing one condition at a range of a different size, record what Excel returns, and state the rule that prevents it recurring. | D16: Head of MIS
A18: BUILD YOUR REPORT / OUTPUT BELOW (pivot, chart, macro output, or model — as required above)
A34: HOW TO WORK: build the requested output in the blank area above (or insert a pivot table / chart / macro-driven control here), tick each deliverable off in the checklist, and record any formula or setting worth remembering in the specification column.

Sheet 2.10 Data
A1: Dataset 2.10 — SUMIFS, COUNTIFS, AVERAGEIFS (Multiple Criteria)
A2: Session 2: Array Formulas, Advanced Logic & Named Ranges | Part B: Advanced Logical and Math Functions | Adamjee Assurance Company Limited (Pakistan) — training data, figures in PKR
A4: Table A — Transaction register 2024
A5: Policy No | B5: Client Name | C5: Branch | D5: Region | E5: Product | F5: Channel | G5: Booking Date | H5: Gross Premium (PKR) | I5: Claims Paid (PKR) | J5: Policy Status
A6: ADM-FIR-KHI-2024-1001 | B6: Gul Ahmed Textile Mills Ltd | C6: Karachi Main | D6: South | E6: Fire & Property | F6: Direct | G6: 45293 | H6: 96000 | I6: 96262 | J6: Active
A7: ADM-TRV-LHR-2024-1002 | B7: Packages Limited | C7: Lahore Gulberg | D7: Central | E7: Travel | F7: Agency | G7: 45325 | H7: 201000 | I7: 111595 | J7: Active
A8: ADM-MTR-ISB-2024-1003 | B8: Lucky Cement Limited | C8: Islamabad Blue Area | D8: North | E8: Motor | F8: Bancassurance | G8: 45355 | H8: 1397000 | I8: 1436098 | J8: Active
A9: ADM-HLT-FSD-2024-1004 | B9: Attock Refinery Limited | C9: Faisalabad | D9: Central | E9: Health | F9: Corporate | G9: 45387 | H9: 305000 | I9: 185930 | J9: Cancelled
A10: ADM-MSC-MUL-2024-1005 | B10: Descon Engineering Ltd | C10: Multan | D10: Central | E10: Miscellaneous | F10: Direct | G10: 45418 | H10: 75000 | I10: 44061 | J10: Active
A11: ADM-MAR-PEW-2024-1006 | B11: Fauji Fertilizer Company | C11: Peshawar | D11: North | E11: Marine Cargo | F11: Agency | G11: 45450 | H11: 380000 | I11: 91249 | J11: Active
A12: ADM-ENG-QTA-2024-1007 | B12: Indus Motor Company Ltd | C12: Quetta | D12: South | E12: Engineering | F12: Bancassurance | G12: 45481 | H12: 227000 | I12: 78775 | J12: Active
A13: ADM-FIR-HYD-2024-1008 | B13: Nishat Mills Limited | C13: Hyderabad | D13: South | E13: Fire & Property | F13: Corporate | G13: 45513 | H13: 290000 | I13: 249183 | J13: Renewed
A14: ADM-TRV-SKT-2024-1009 | B14: Pak Suzuki Motor Co | C14: Sialkot | D14: Central | E14: Travel | F14: Direct | G14: 45545 | H14: 37000 | I14: 48145 | J14: Active
A15: ADM-MTR-RWP-2024-1010 | B15: Engro Polymer & Chemicals | C15: Rawalpindi | D15: North | E15: Motor | F15: Agency | G15: 45576 | H15: 760000 | I15: 162016 | J15: Cancelled
A16: ADM-HLT-KHI-2024-1011 | B16: Interloop Limited | C16: Karachi Main | D16: South | E16: Health | F16: Bancassurance | G16: 45608 | H16: 603000 | I16: 595704 | J16: Active
A17: ADM-MSC-LHR-2024-1012 | B17: Service Industries Ltd | C17: Lahore Gulberg | D17: Central | E17: Miscellaneous | F17: Corporate | G17: 45639 | H17: 512000 | I17: 394713 | J17: Active
... A41: ADM-FIR-PEW-2024-1036 | B41: Sadia Rehman | C41: Peshawar | D41: North | E41: Fire & Property | F41: Corporate | G41: 45637 | H41: 113000 | I41: 125166 | J41: Active
A43: Table B — Report parameters
A44: Parameter | B44: Value
A45: Period start | B45: 45474
A46: Period end | B46: 45565
A47: Branch | B47: Karachi Main
A48: Product | B48: Motor
A49: Minimum premium (PKR) | B49: 200000
A50: Client name pattern | B50: *Limited
A52: Note: This is simulated training data modelled on Adamjee Assurance general insurance operations. It is not actual company data.

Sheet 2.10 Report
A1: ADAMJEE ASSURANCE COMPANY LIMITED
A2: Monthly Branch Performance Pack — the core grid
A3: Prepared for: | B3: Regional Head — Central
A4: Prepared by:
A5: Reporting date: | B5: As at reporting date shown on the dataset
A7: The performance pack is the single most-read report in the company and it is built by filtering the transaction register ten times and pasting the totals. It takes a day and a half and the June pack had two branches transposed.
A9: Source data: '2.10 Data' (click to open)
A11: DELIVERABLE CHECKLIST
A12: # | B12: Deliverable | C12: Report specification | D12: Requested by | E12: Done?
A13: 1 | B13: Monthly Branch Performance Pack — the core grid | C13: The core grid: branches down the side, products across the top, showing Gross Premium. Built with one formula written once and copied across and down the whole grid. Row and column totals included. | D13: Regional Head — Central
A14: 2 | B14: Q3 period-bounded figures | C14: The same grid restricted to the period between the two date parameter cells, plus policy count and average premium grids on the same basis. Changing the two dates must move every grid. | D14: Chief Financial Officer
A15: 3 | B15: Corporate client premium by name pattern | C15: A corporate segment figure: premium and policy count for clients whose name matches the pattern in the parameter cell, with the pattern changeable without editing the formula. | D15: Head of Corporate Business
A16: 4 | B16: Claims excluding cancelled policies, by branch | C16: A branch claims column excluding cancelled policies, alongside the unadjusted figure and the difference, so the adjustment reconciles to the ledger. | D16: Finance Manager — Technical Accounts
A17: 5 | B17: Presentation of empty segments | C17: The average premium grid presented with a dash where no policies exist, and a one-line note stating why AVERAGEIFS behaves this way and what the dash means to the reader. | D17: Head of Management Reporting
A19: BUILD YOUR REPORT / OUTPUT BELOW (pivot, chart, macro output, or model — as required above)
A35: HOW TO WORK: build the requested output in the blank area above (or insert a pivot table / chart / macro-driven control here), tick each deliverable off in the checklist, and record any formula or setting worth remembering in the specification column.

Sheet 2.11 Data
A1: Dataset 2.11 — AGGREGATE Function (Ignoring Errors and Hidden Rows)
A2: Session 2: Array Formulas, Advanced Logic & Named Ranges | Part B: Advanced Logical and Math Functions | Adamjee Assurance Company Limited (Pakistan) — training data, figures in PKR
A4: Table A — Claims register with deliberate data problems
A5: Claim No | B5: Branch | C5: Product | D5: Claimed Amount (PKR) | E5: Paid Amount (PKR) | F5: Recovery (PKR) | G5: Claim Status | H5: Data Note
A6: CLM-KHI-2024-0501 | B6: Karachi Main | C6: Motor | D6: 385000 | E6: 341000 | F6: 22000 | G6: Settled
A7: CLM-LHR-2024-0502 | B7: Lahore Gulberg | C7: Fire & Property | D7: 1240000 | E7: 1015000 | F7: 0 | G7: Settled
A8: CLM-ISB-2024-0503 | B8: Islamabad Blue Area | C8: Health | D8: 92500 | E8: N/A | F8: 0 | G8: Under Survey | H8: Text in number column
A9: CLM-FSD-2024-0504 | B9: Faisalabad | C9: Engineering | D9: 660000 | E9: 512000 | F9: 48000 | G9: Settled
A10: CLM-MUL-2024-0505 | B10: Multan | C10: Marine Cargo | D10: 208000 | E10: 208000 | F10: 0 | G10: Settled
A11: CLM-KHI-2024-0506 | B11: Karachi Main | C11: Motor | D11: 1875000 | E11: Pending | F11: 0 | G11: Outstanding | H11: Text in number column
A12: CLM-PEW-2024-0507 | B12: Peshawar | C12: Miscellaneous | D12: 445000 | E12: 398000 | F12: 15000 | G12: Settled
A13: CLM-HYD-2024-0508 | B13: Hyderabad | C13: Motor | D13: 130000 | E13: 117000 | F13: 0 | G13: Settled
A14: CLM-LHR-2024-0509 | B14: Lahore Gulberg | C14: Health | D14: 76000 | E14: 76000 | F14: 0 | G14: Settled
A15: CLM-KHI-2024-0510 | B15: Karachi Main | C15: Marine Cargo | D15: 2450000 | E15: 1980000 | F15: 310000 | G15: Settled
A16: CLM-SKT-2024-0511 | B16: Sialkot | C16: Fire & Property | D16: 890000 | E16: Repudiated | F16: 0 | G16: Repudiated | H16: Text in number column
A17: CLM-RWP-2024-0512 | B17: Rawalpindi | C17: Motor | D17: 312000 | E17: 289000 | F17: 0 | G17: Settled
A18: CLM-QTA-2024-0513 | B18: Quetta | C18: Engineering | D18: 1120000 | E18: 940000 | F18: 76000 | G18: Settled
A19: CLM-FSD-2024-0514 | B19: Faisalabad | C19: Health | D19: 54000 | E19: 54000 | F19: 0 | G19: Settled
A20: CLM-KHI-2024-0515 | B20: Karachi Main | C20: Travel | D20: 41000 | E20: 41000 | F20: 0 | G20: Settled
A22: Note: This is simulated training data modelled on Adamjee Assurance general insurance operations. It is not actual company data.

Sheet 2.11 Report
A1: ADAMJEE ASSURANCE COMPANY LIMITED
A2: Claims Register totals despite unresolved records
A3: Prepared for: | B3: Head of Claims Operations
A4: Prepared by:
A5: Reporting date: | B5: As at reporting date shown on the dataset
A7: Three claims carry text in the paid amount column — 'N/A', 'Pending' and 'Repudiated' — because Finance uses those markers to identify unresolved records and refuses to replace them with zero. Every SUM on the sheet has failed since the markers were introduced and the register total is currently typed in by hand.
A9: Source data: '2.11 Data' (click to open)
A11: DELIVERABLE CHECKLIST
A12: # | B12: Deliverable | C12: Report specification | D12: Requested by | E12: Done?
A13: 1 | B13: Claims Register totals despite unresolved records | C13: A register summary: Total Claimed | Total Paid | Average Claim | Largest Claim | Smallest Claim, every figure ignoring the text and error values without deleting or altering a single source cell. | D13: Head of Claims Operations
A14: 2 | B14: Filter-responsive branch totals for the review meeting | C14: A totals block that responds to the AutoFilter and still ignores the error values, demonstrated by filtering to Karachi Main and recording the figures before and after. | D14: Head of Claims Operations
A15: 3 | B15: Largest claims schedule for the reinsurance notification | C15: A schedule of the largest three claims by claimed amount, each with claim number, branch, product and amount, produced without sorting or altering the register. | D15: Head of Reinsurance
A16: 4 | B16: Hidden versus filtered rows — control note | C16: A control note recording what AGGREGATE option 5 and option 7 each do after rows are hidden manually rather than filtered, with evidence from the register. | D16: Head of Internal Audit
A17: 5 | B17: Data quality escalation | C17: A two-line escalation: whether you would ship the AGGREGATE solution or insist the source data is fixed, what you would say to Finance about the text markers, and what control you would put in place meanwhile. | D17: Head of Internal Audit
A19: BUILD YOUR REPORT / OUTPUT BELOW (pivot, chart, macro output, or model — as required above)
A35: HOW TO WORK: build the requested output in the blank area above (or insert a pivot table / chart / macro-driven control here), tick each deliverable off in the checklist, and record any formula or setting worth remembering in the specification column.

Sheet 2.12 Data
A1: Dataset 2.12 — Creating and Managing Named Ranges
A2: Session 2: Array Formulas, Advanced Logic & Named Ranges | Part C: Named Ranges and Dynamic Ranges | Adamjee Assurance Company Limited (Pakistan) — training data, figures in PKR
A4: Table A — Underwriting extract 2024
A5: Policy No | B5: Branch | C5: Region | D5: Product | E5: Channel | F5: Month | G5: Sum Insured (PKR) | H5: Gross Premium (PKR) | I5: Claims Paid (PKR) | J5: Commission % | K5: Policy Status
A6: ADM-FIR-KHI-2024-1001 | B6: Karachi Main | C6: South | D6: Fire & Property | E6: Direct | F6: Jan-2024 | G6: 4500000 | H6: 96000 | I6: 96262 | J6: 0.15 | K6: Active
A7: ADM-TRV-LHR-2024-1002 | B7: Lahore Gulberg | C7: Central | D7: Travel | E7: Agency | F7: Feb-2024 | G7: 12000000 | H7: 201000 | I7: 111595 | J7: 0.175 | K7: Active
A8: ADM-MTR-ISB-2024-1003 | B8: Islamabad Blue Area | C8: North | D8: Motor | E8: Bancassurance | F8: Mar-2024 | G8: 65000000 | H8: 1397000 | I8: 1436098 | J8: 0.125 | K8: Active
A9: ADM-HLT-FSD-2024-1004 | B9: Faisalabad | C9: Central | D9: Health | E9: Corporate | F9: Apr-2024 | G9: 18500000 | H9: 305000 | I9: 185930 | J9: 0.125 | K9: Cancelled
A10: ADM-MSC-MUL-2024-1005 | B10: Multan | C10: Central | D10: Miscellaneous | E10: Direct | F10: May-2024 | G10: 4500000 | H10: 75000 | I10: 44061 | J10: 0.175 | K10: Active
A11: ADM-MAR-PEW-2024-1006 | B11: Peshawar | C11: North | D11: Marine Cargo | E11: Agency | F11: Jun-2024 | G11: 25000000 | H11: 380000 | I11: 91249 | J11: 0.125 | K11: Active
A12: ADM-ENG-QTA-2024-1007 | B12: Quetta | C12: South | D12: Engineering | E12: Bancassurance | F12: Jul-2024 | G12: 18500000 | H12: 227000 | I12: 78775 | J12: 0.125 | K12: Active
A13: ADM-FIR-HYD-2024-1008 | B13: Hyderabad | C13: South | D13: Fire & Property | E13: Corporate | F13: Aug-2024 | G13: 25000000 | H13: 290000 | I13: 249183 | J13: 0.125 | K13: Renewed
A14: ADM-TRV-SKT-2024-1009 | B14: Sialkot | C14: Central | D14: Travel | E14: Direct | F14: Sep-2024 | G14: 7500000 | H14: 37000 | I14: 48145 | J14: 0.125 | K14: Active
A15: ADM-MTR-RWP-2024-1010 | B15: Rawalpindi | C15: North | D15: Motor | E15: Agency | F15: Oct-2024 | G15: 65000000 | H15: 760000 | I15: 162016 | J15: 0.2 | K15: Cancelled
A16: ADM-HLT-KHI-2024-1011 | B16: Karachi Main | C16: South | D16: Health | E16: Bancassurance | F16: Nov-2024 | G16: 90000000 | H16: 603000 | I16: 595704 | J16: 0.2 | K16: Active
A17: ADM-MSC-LHR-2024-1012 | B17: Lahore Gulberg | C17: Central | D17: Miscellaneous | E17: Corporate | F17: Dec-2024 | G17: 40000000 | H17: 512000 | I17: 394713 | J17: 0.125 | K17: Active
... A41: ADM-FIR-PEW-2024-1036 | B41: Peshawar | C41: North | D41: Fire & Property | E41: Corporate | F41: Dec-2024 | G41: 4500000 | H41: 113000 | I41: 125166 | J41: 0.125 | K41: Active
A43: Table B — Names to create
A44: Suggested Name | B44: Applies to | C44: Scope
A45: Policy_No | B45: Policy No column | C45: Workbook
A46: Branch_List | B46: Branch column | C46: Workbook
A47: Product_List | B47: Product column | C47: Workbook
A48: Gross_Premium | B48: Gross Premium column | C48: Workbook
A49: Claims_Paid | B49: Claims Paid column | C49: Workbook
A50: FIF_Rate | B50: Single rate cell | C50: Workbook
A51: Report_Branch | B51: Criteria input cell | C51: Worksheet only
A53: Table C — Constants for the model
A54: Item | B54: Value
A55: Federal Insurance Fee rate | B55: 0.01
A56: Target loss ratio | B56: 0.65
A57: Reporting currency | B57: PKR
A59: Note: This is simulated training data modelled on Adamjee Assurance general insurance operations. It is not actual company data.

Sheet 2.12 Report
A1: ADAMJEE ASSURANCE COMPANY LIMITED
A2: Readability rebuild of the MIS reporting model
A3: Prepared for: | B3: Head of Internal Audit
A4: Prepared by:
A5: Reporting date: | B5: As at reporting date shown on the dataset
A7: The monthly MIS workbook is handed to a different analyst each month and audit cannot review it. Formulas read like SUMIFS('Data 2024'!$H$5:$H$2000,'Data 2024'!$B$5:$B$2000,$A12) and the reviewer has to open three sheets to work out what is being summed. Audit has asked for the model to be made readable before the year-end review.
A9: Source data: '2.12 Data' (click to open)
A11: DELIVERABLE CHECKLIST
A12: # | B12: Deliverable | C12: Report specification | D12: Requested by | E12: Done?
A13: 1 | B13: Readability rebuild of the MIS reporting model | C13: The model rebuilt with named ranges: total premium, total claims and a branch premium figure, each written so a reviewer can read the formula and understand it without opening the source sheet. Names as listed in the naming table. | D13: Head of Internal Audit
A14: 2 | B14: Named constants for the statutory rates | C14: The fee rate held as a named constant used by every calculation that needs it, plus a one-line note on where the value lives and how it is changed. | D14: Finance Manager — Technical Accounts
A15: 3 | B15: Name Manager clean-up before handover | C15: A clean-up record: names deleted, names renamed, and confirmation that renaming a name updated every formula using it. Include the scope of each surviving name. | D15: Head of MIS
A16: 4 | B16: Naming standard for the reporting team | C16: A short naming standard for the team: the three rules that make a name invalid, when to use workbook scope against worksheet scope, and a worked example of each from this workbook. | D16: Head of MIS
A18: BUILD YOUR REPORT / OUTPUT BELOW (pivot, chart, macro output, or model — as required above)
A34: HOW TO WORK: build the requested output in the blank area above (or insert a pivot table / chart / macro-driven control here), tick each deliverable off in the checklist, and record any formula or setting worth remembering in the specification column.

Sheet 2.13 Data
A1: Dataset 2.13 — Dynamic Named Ranges Using OFFSET and COUNTA
A2: Session 2: Array Formulas, Advanced Logic & Named Ranges | Part C: Named Ranges and Dynamic Ranges | Adamjee Assurance Company Limited (Pakistan) — training data, figures in PKR
A4: Table A — Daily policy feed (rows are appended each morning)
A5: Policy No | B5: Booking Date | C5: Branch | D5: Product | E5: Gross Premium (PKR) | F5: Sum Insured (PKR)
A6: ADM-FIR-KHI-2024-1001 | B6: 45536 | C6: Karachi Main | D6: Fire & Property | E6: 96000 | F6: 4500000
A7: ADM-TRV-LHR-2024-1002 | B7: 45537 | C7: Lahore Gulberg | D7: Travel | E7: 201000 | F7: 12000000
A8: ADM-MTR-ISB-2024-1003 | B8: 45538 | C8: Islamabad Blue Area | D8: Motor | E8: 1397000 | F8: 65000000
A9: ADM-HLT-FSD-2024-1004 | B9: 45539 | C9: Faisalabad | D9: Health | E9: 305000 | F9: 18500000
A10: ADM-MSC-MUL-2024-1005 | B10: 45540 | C10: Multan | D10: Miscellaneous | E10: 75000 | F10: 4500000
A11: ADM-MAR-PEW-2024-1006 | B11: 45541 | C11: Peshawar | D11: Marine Cargo | E11: 380000 | F11: 25000000
A12: ADM-ENG-QTA-2024-1007 | B12: 45542 | C12: Quetta | D12: Engineering | E12: 227000 | F12: 18500000
A13: ADM-FIR-HYD-2024-1008 | B13: 45543 | C13: Hyderabad | D13: Fire & Property | E13: 290000 | F13: 25000000
A14: ADM-TRV-SKT-2024-1009 | B14: 45544 | C14: Sialkot | D14: Travel | E14: 37000 | F14: 7500000
A15: ADM-MTR-RWP-2024-1010 | B15: 45545 | C15: Rawalpindi | D15: Motor | E15: 760000 | F15: 65000000
A16: ADM-HLT-KHI-2024-1011 | B16: 45546 | C16: Karachi Main | D16: Health | E16: 603000 | F16: 90000000
A17: ADM-MSC-LHR-2024-1012 | B17: 45547 | C17: Lahore Gulberg | D17: Miscellaneous | E17: 512000 | F17: 40000000
... A30: ADM-HLT-MUL-2024-1025 | B30: 45560 | C30: Multan | D30: Health | E30: 19000 | F30: 2800000
A32: Table B — Dynamic range definitions to build
A33: Name | B33: Should cover | C33: Note
A34: Dyn_Premium | B34: Gross Premium column, growing | C34: Single column
A35: Dyn_Branch | B35: Branch column, growing | C35: Single column
A36: Dyn_Data | B36: The whole table, growing | C36: Multi column
A37: Dyn_Dates | B37: Booking Date column, growing | C37: Feeds the dashboard timeline
A39: Note: This is simulated training data modelled on Adamjee Assurance general insurance operations. It is not actual company data.

Sheet 2.13 Report
A1: ADAMJEE ASSURANCE COMPANY LIMITED
A2: Self-extending dashboard ranges
A3: Prepared for: | B3: Head of MIS
A4: Prepared by:
A5: Reporting date: | B5: As at reporting date shown on the dataset
A7: New policies are appended to the data sheet every morning. Every named range and pivot source stops at yesterday's last row, so the dashboard has been quietly under-reporting since the range was last extended in August. Nobody noticed until the branch challenged its own figure.
A9: Source data: '2.13 Data' (click to open)
A11: DELIVERABLE CHECKLIST
A12: # | B12: Deliverable | C12: Report specification | D12: Requested by | E12: Done?
A13: 1 | B13: Self-extending dashboard ranges | C13: Dynamic named ranges for the premium column, the branch column, the date column and the whole table, each growing automatically as rows are appended. Plus a total premium cell built on the dynamic range. | D13: Head of MIS
A14: 2 | B14: Acceptance test — three new policies | C14: Test evidence: the total premium before, three new policy rows added, the total after, and confirmation that no formula, name or range was edited between the two readings. | D14: Head of Internal Audit
A15: 3 | B15: Pivot source that never needs changing | C15: A pivot table sourced from the dynamic name rather than a fixed range, with evidence that refreshing after new rows are added brings the new data in. | D15: Head of Management Reporting
A16: 4 | B16: Blank-cell risk assessment | C16: A risk note: what happens to the dynamic range when blanks appear in the counted column, the effect on the reported total, and the alternative Excel 2016 feature that avoids the problem entirely. | D16: Head of MIS
A18: BUILD YOUR REPORT / OUTPUT BELOW (pivot, chart, macro output, or model — as required above)
A34: HOW TO WORK: build the requested output in the blank area above (or insert a pivot table / chart / macro-driven control here), tick each deliverable off in the checklist, and record any formula or setting worth remembering in the specification column.

Sheet 2.14 Data
A1: Dataset 2.14 — Using Named Ranges in Formulas and Data Validation
A2: Session 2: Array Formulas, Advanced Logic & Named Ranges | Part C: Named Ranges and Dynamic Ranges | Adamjee Assurance Company Limited (Pakistan) — training data, figures in PKR
A4: Table A — Reference lists for validation
A5: Branches | B5: Products | C5: Channels | D5: Policy Status
A6: Karachi Main | B6: Motor | C6: Direct | D6: Active
A7: Lahore Gulberg | B7: Fire & Property | C7: Agency | D7: Renewed
A8: Islamabad Blue Area | B8: Marine Cargo | C8: Bancassurance | D8: Lapsed
A9: Faisalabad | B9: Health | C9: Corporate | D9: Cancelled
A10: Multan | B10: Travel
A11: Peshawar | B11: Engineering
A12: Quetta | B12: Miscellaneous
A13: Hyderabad
A14: Sialkot
A15: Rawalpindi
A17: Table B — Products each branch is licensed to sell (dependent lists)
A18: Karachi_Main | B18: Lahore_Gulberg | C18: Islamabad_Blue_Area | D18: Faisalabad
A19: Motor | B19: Motor | C19: Motor | D19: Motor
A20: Fire & Property | B20: Fire & Property | C20: Health | D20: Fire & Property
A21: Marine Cargo | B21: Health | C21: Travel | D21: Engineering
A22: Health | B22: Engineering
A23: Travel | B23: Travel
A24: Engineering
A25: Miscellaneous
A27: Table C — Branch underwriting authority
A28: Branch | B28: Max Sum Insured (PKR)
A29: Karachi Main | B29: 100000000
A30: Lahore Gulberg | B30: 60000000
A31: Islamabad Blue Area | B31: 40000000
A32: Faisalabad | B32: 25000000
A34: Table D — Data entry area (the template users will fill)
A35: Entry No | B35: Branch | C35: Product | D35: Channel | E35: Sum Insured (PKR) | F35: Gross Premium (PKR)
A36: 1
A37: 2
A38: 3
A39: 4
A40: 5
A41: 6
A42: 7
A43: 8
A45: Note: This is simulated training data modelled on Adamjee Assurance general insurance operations. It is not actual company data.

Sheet 2.14 Report
A1: ADAMJEE ASSURANCE COMPANY LIMITED
A2: Branch Data Entry Template — controlled at source
A3: Prepared for: | B3: Head of Operations
A4: Prepared by:
A5: Reporting date: | B5: As at reporting date shown on the dataset
A7: The branch entry template goes to ten locations tomorrow. The last version allowed free typing and came back with branch names spelt four different ways, products that the branch is not licensed to sell, and one sum insured of PKR 900 million entered by a user who held the zero key down.
A9: Source data: '2.14 Data' (click to open)
A11: DELIVERABLE CHECKLIST
A12: # | B12: Deliverable | C12: Report specification | D12: Requested by | E12: Done?
A13: 1 | B13: Branch Data Entry Template — controlled at source | C13: The entry template with: drop-down lists on Branch, Product, Channel and Status sourced from named ranges, so no branch name can be mistyped. Ten rows ready for entry. | D13: Head of Operations
A14: 2 | B14: Licensed-product control per branch | C14: A dependent Product drop-down that offers only the products the selected branch is licensed to sell, tested by selecting each of the four branches in turn. | D14: Chief Underwriting Officer
A15: 3 | B15: Underwriting authority limit at the point of entry | C15: A validation rule on Sum Insured limiting entry to the selected branch's authority, with a custom input message and a Stop error alert written in language a branch clerk will understand. | D15: Chief Underwriting Officer
A16: 4 | B16: Duplicate policy number control | C16: A validation rule that refuses a duplicate policy number within the entry range, plus evidence of Circle Invalid Data being used to expose entries made before the controls existed. | D16: Head of Internal Audit
A17: 5 | B17: Maintenance note — adding an eleventh branch | C17: A maintenance note stating what happens to the drop-downs when a branch is added to the reference list, and the change you would make now so the addition needs no rework. | D17: Head of Operations
A19: BUILD YOUR REPORT / OUTPUT BELOW (pivot, chart, macro output, or model — as required above)
A35: HOW TO WORK: build the requested output in the blank area above (or insert a pivot table / chart / macro-driven control here), tick each deliverable off in the checklist, and record any formula or setting worth remembering in the specification column.

Sheet 2.15 Data
A1: Dataset 2.15 — INDIRECT Function for Dynamic References
A2: Session 2: Array Formulas, Advanced Logic & Named Ranges | Part C: Named Ranges and Dynamic Ranges | Adamjee Assurance Company Limited (Pakistan) — training data, figures in PKR
A4: Table A — Karachi_Main (imagine this is its own sheet, same layout for every branch)
A5: Line Item | B5: Q1 (PKR) | C5: Q2 (PKR) | D5: Q3 (PKR) | E5: Q4 (PKR)
A6: Gross Written Premium | B6: 48500000 | C6: 52300000 | D6: 55900000 | E6: 61200000
A7: Claims Paid | B7: 21300000 | C7: 24800000 | D7: 26100000 | E7: 29400000
A8: Commission | B8: 6800000 | C8: 7300000 | D8: 7900000 | E8: 8500000
A9: Management Expenses | B9: 5200000 | C9: 5400000 | D9: 5600000 | E9: 5900000
A11: Table B — Lahore_Gulberg
A12: Line Item | B12: Q1 (PKR) | C12: Q2 (PKR) | D12: Q3 (PKR) | E12: Q4 (PKR)
A13: Gross Written Premium | B13: 33200000 | C13: 35600000 | D13: 34100000 | E13: 38900000
A14: Claims Paid | B14: 19900000 | C14: 18400000 | D14: 21700000 | E14: 22300000
A15: Commission | B15: 4600000 | C15: 4900000 | D15: 4700000 | E15: 5300000
A16: Management Expenses | B16: 3800000 | C16: 3900000 | D16: 4000000 | E16: 4200000
A18: Table C — Islamabad_Blue_Area
A19: Line Item | B19: Q1 (PKR) | C19: Q2 (PKR) | D19: Q3 (PKR) | E19: Q4 (PKR)
A20: Gross Written Premium | B20: 18700000 | C20: 19900000 | D20: 21400000 | E20: 23100000
A21: Claims Paid | B21: 8100000 | C21: 9600000 | D21: 10200000 | E21: 11800000
A22: Commission | B22: 2500000 | C22: 2700000 | D22: 2900000 | E22: 3100000
A23: Management Expenses | B23: 2100000 | C23: 2150000 | D23: 2200000 | E23: 2300000
A25: Table D — Summary controls
A26: Control | B26: Value
A27: Branch selected | B27: Lahore_Gulberg
A28: Quarter selected | B28: Q3
A29: Line item | B29: Claims Paid
A31: Note: This is simulated training data modelled on Adamjee Assurance general insurance operations. It is not actual company data.

Sheet 2.15 Report
A1: ADAMJEE ASSURANCE COMPANY LIMITED
A2: Regional Summary Page across branch sheets
A3: Prepared for: | B3: Regional Head — South
A4: Prepared by:
A5: Reporting date: | B5: As at reporting date shown on the dataset
A7: Each branch keeps its own identically structured sheet in the regional workbook. The summary page is built by writing a separate formula for every branch, so adding the new branch last quarter meant editing forty-eight formulas and two were missed.
A9: Source data: '2.15 Data' (click to open)
A11: DELIVERABLE CHECKLIST
A12: # | B12: Deliverable | C12: Report specification | D12: Requested by | E12: Done?
A13: 1 | B13: Regional Summary Page across branch sheets | C13: A summary page with one branch selector cell returning that branch's figures for the selected quarter and line item — Gross Written Premium, Claims Paid, Commission and Management Expenses — with no formula edited when the selection changes. | D13: Regional Head — South
A14: 2 | B14: Branch Loss Ratio comparison | C14: A comparison block showing all three branches side by side for the selected quarter: GWP, Claims, Loss Ratio and Combined Ratio, driven by the same INDIRECT pattern copied across. | D14: Regional Head — South
A15: 3 | B15: Robustness note before the workbook is shared | C15: A robustness note recording two limitations of INDIRECT that matter in production, and your recommendation on whether this summary page should be shared as it is. | D15: Head of MIS
A17: BUILD YOUR REPORT / OUTPUT BELOW (pivot, chart, macro output, or model — as required above)
A33: HOW TO WORK: build the requested output in the blank area above (or insert a pivot table / chart / macro-driven control here), tick each deliverable off in the checklist, and record any formula or setting worth remembering in the specification column.

Sheet 3.1 Data
A1: Dataset 3.1 — Calculated Fields and Calculated Items
A2: Session 3: Advanced Pivot Tables, Power Query & What-If Analysis | Part A: Advanced Pivot Tables | Adamjee Assurance Company Limited (Pakistan) — training data, figures in PKR
A4: Table A — Policy transaction register 2024 (120 rows — the pivot source)
A5: Policy No | B5: Booking Date | C5: Branch | D5: Region | E5: Product | F5: Channel | G5: Agent Name | H5: Client Type | I5: Sum Insured (PKR) | J5: Gross Premium (PKR) | K5: Claims Paid (PKR) | L5: Policy Count | M5: Policy Status
A6: ADM-MTR-KHI-2024-2001 | B6: 45292 | C6: Karachi Main | D6: South | E6: Motor | F6: Direct | G6: Tariq Jameel | H6: Individual | I6: 3400000 | J6: 33200 | K6: 52907 | L6: 1 | M6: Active
A7: ADM-HLT-LHR-2024-2002 | B7: 45330 | C7: Lahore Gulberg | D7: Central | E7: Health | F7: Agency | G7: Nadia Hassan | H7: Corporate | I7: 1200000 | J7: 15300 | K7: 3207 | L7: 1 | M7: Active
A8: ADM-MSC-ISB-2024-2003 | B8: 45366 | C8: Islamabad Blue Area | D8: North | E8: Miscellaneous | F8: Bancassurance | G8: Salman Shah | H8: Corporate | I8: 11500000 | J8: 206100 | K8: 260673 | L8: 1 | M8: Renewed
A9: ADM-MAR-FSD-2024-2004 | B9: 45404 | C9: Faisalabad | D9: Central | E9: Marine Cargo | F9: Corporate | G9: Komal Bashir | H9: Individual | I9: 47000000 | J9: 1335500 | K9: 125902 | L9: 1 | M9: Lapsed
A10: ADM-ENG-MUL-2024-2005 | B10: 45413 | C10: Multan | D10: Central | E10: Engineering | F10: Direct | G10: Waqar Younis Khan | H10: Corporate | I10: 1200000 | J10: 14500 | K10: 20595 | L10: 1 | M10: Cancelled
A11: ADM-FIR-PEW-2024-2006 | B11: 45451 | C11: Peshawar | D11: North | E11: Fire & Property | F11: Agency | G11: Amna Zubair | H11: Corporate | I11: 72000000 | J11: 1519000 | K11: 2506397 | L11: 1 | M11: Active
A12: ADM-TRV-QTA-2024-2007 | B12: 45488 | C12: Quetta | D12: South | E12: Travel | F12: Bancassurance | G12: Rizwan Ali Soomro | H12: Individual | I12: 1200000 | J12: 23900 | K12: 3819 | L12: 1 | M12: Active
A13: ADM-MTR-HYD-2024-2008 | B13: 45526 | C13: Hyderabad | D13: South | E13: Motor | F13: Corporate | G13: Farhan Dar | H13: Corporate | I13: 11500000 | J13: 204900 | K13: 293808 | L13: 1 | M13: Renewed
A14: ADM-HLT-SKT-2024-2009 | B14: 45536 | C14: Sialkot | D14: Central | E14: Health | F14: Direct | G14: Sobia Naz | H14: Corporate | I14: 6800000 | J14: 145900 | K14: 101845 | L14: 1 | M14: Lapsed
A15: ADM-MSC-RWP-2024-2010 | B15: 45573 | C15: Rawalpindi | D15: North | E15: Miscellaneous | F15: Agency | G15: Junaid Akram | H15: Individual | I15: 1200000 | J15: 20000 | K15: 15603 | L15: 1 | M15: Cancelled
A16: ADM-MAR-KHI-2024-2011 | B16: 45611 | C16: Karachi Main | D16: South | E16: Marine Cargo | F16: Bancassurance | G16: Hamid Raza | H16: Corporate | I16: 47000000 | J16: 716000 | K16: 109689 | L16: 1 | M16: Active
A17: ADM-ENG-LHR-2024-2012 | B17: 45648 | C17: Lahore Gulberg | D17: Central | E17: Engineering | F17: Corporate | G17: Nimra Saleem | H17: Corporate | I17: 28000000 | J17: 722600 | K17: 919063 | L17: 1 | M17: Active
... A125: ADM-MTR-RWP-2024-2120 | B125: 45648 | C125: Rawalpindi | D125: North | E125: Motor | F125: Corporate | G125: Nimra Saleem | H125: Corporate | I125: 6800000 | J125: 111000 | K125: 91930 | L125: 1 | M125: Cancelled
A127: Table B — Rates for the calculated fields
A128: Item | B128: Rate
A129: Standard commission | B129: 0.145
A130: Federal insurance fee | B130: 0.01
A131: Target loss ratio | B131: 0.65
A133: Note: This is simulated training data modelled on Adamjee Assurance general insurance operations. It is not actual company data.

Sheet 3.1 Report
A1: ADAMJEE ASSURANCE COMPANY LIMITED
A2: Branch Scorecard with ratios inside the pivot
A3: Prepared for: | B3: Regional Head — Central
A4: Prepared by:
A5: Reporting date: | B5: As at reporting date shown on the dataset
A7: The scorecard is a pivot with the loss ratio calculated in cells beside it. Every time a Regional Head re-arranges the pivot or applies a filter, the ratio column stops lining up with the rows and the meeting is told a branch has a 340% loss ratio. It has happened in three of the last five monthly calls.
A9: Source data: '3.1 Data' (click to open)
A11: DELIVERABLE CHECKLIST
A12: # | B12: Deliverable | C12: Report specification | D12: Requested by | E12: Done?
A13: 1 | B13: Branch Scorecard with ratios inside the pivot | C13: A pivot scorecard with Branch on rows and Gross Premium, Claims Paid, Policy Count as values, plus Loss Ratio calculated INSIDE the pivot so it survives filtering and re-arrangement. Loss ratio formatted 0.0%. | D13: Regional Head — Central
A14: 2 | B14: Commission and Net Premium lines for the technical pack | C14: The scorecard extended with Commission Cost (gross premium at the standard rate) and Net Premium as calculated fields, and an Average Premium per Policy field. Rates taken from the rates table. | D14: Finance Manager — Technical Accounts
A15: 3 | B15: Transport Risks grouping for the underwriting review | C15: A product pivot with a calculated item combining Motor and Marine Cargo into a single 'Transport Risks' line, shown alongside the individual lines. | D15: Chief Underwriting Officer
A16: 4 | B16: Methodology note on the loss ratio definition | C16: A methodology note explaining why a calculated field gives a different answer from averaging the row-level loss ratios, with both figures for one branch shown as evidence, and a statement of which Adamjee should use. | D16: Head of Internal Audit
A17: 5 | B17: Calculation documentation for the workbook handover | C17: The List Formulas output documenting every calculated field and item in the workbook, plus a one-line note on one thing a calculated field cannot do. | D17: Head of MIS
A19: BUILD YOUR REPORT / OUTPUT BELOW (pivot, chart, macro output, or model — as required above)
A35: HOW TO WORK: build the requested output in the blank area above (or insert a pivot table / chart / macro-driven control here), tick each deliverable off in the checklist, and record any formula or setting worth remembering in the specification column.

Sheet 3.2 Data
A1: Dataset 3.2 — Grouping Data (Dates by Month/Quarter/Year, Numbers, Text)
A2: Session 3: Advanced Pivot Tables, Power Query & What-If Analysis | Part A: Advanced Pivot Tables | Adamjee Assurance Company Limited (Pakistan) — training data, figures in PKR
A4: Table A — Policy transaction register 2024 (120 rows — the pivot source)
A5: Policy No | B5: Booking Date | C5: Branch | D5: Region | E5: Product | F5: Channel | G5: Agent Name | H5: Client Type | I5: Sum Insured (PKR) | J5: Gross Premium (PKR) | K5: Claims Paid (PKR) | L5: Policy Count | M5: Policy Status
A6: ADM-MTR-KHI-2024-2001 | B6: 45292 | C6: Karachi Main | D6: South | E6: Motor | F6: Direct | G6: Tariq Jameel | H6: Individual | I6: 3400000 | J6: 33200 | K6: 52907 | L6: 1 | M6: Active
A7: ADM-HLT-LHR-2024-2002 | B7: 45330 | C7: Lahore Gulberg | D7: Central | E7: Health | F7: Agency | G7: Nadia Hassan | H7: Corporate | I7: 1200000 | J7: 15300 | K7: 3207 | L7: 1 | M7: Active
A8: ADM-MSC-ISB-2024-2003 | B8: 45366 | C8: Islamabad Blue Area | D8: North | E8: Miscellaneous | F8: Bancassurance | G8: Salman Shah | H8: Corporate | I8: 11500000 | J8: 206100 | K8: 260673 | L8: 1 | M8: Renewed
A9: ADM-MAR-FSD-2024-2004 | B9: 45404 | C9: Faisalabad | D9: Central | E9: Marine Cargo | F9: Corporate | G9: Komal Bashir | H9: Individual | I9: 47000000 | J9: 1335500 | K9: 125902 | L9: 1 | M9: Lapsed
A10: ADM-ENG-MUL-2024-2005 | B10: 45413 | C10: Multan | D10: Central | E10: Engineering | F10: Direct | G10: Waqar Younis Khan | H10: Corporate | I10: 1200000 | J10: 14500 | K10: 20595 | L10: 1 | M10: Cancelled
A11: ADM-FIR-PEW-2024-2006 | B11: 45451 | C11: Peshawar | D11: North | E11: Fire & Property | F11: Agency | G11: Amna Zubair | H11: Corporate | I11: 72000000 | J11: 1519000 | K11: 2506397 | L11: 1 | M11: Active
A12: ADM-TRV-QTA-2024-2007 | B12: 45488 | C12: Quetta | D12: South | E12: Travel | F12: Bancassurance | G12: Rizwan Ali Soomro | H12: Individual | I12: 1200000 | J12: 23900 | K12: 3819 | L12: 1 | M12: Active
A13: ADM-MTR-HYD-2024-2008 | B13: 45526 | C13: Hyderabad | D13: South | E13: Motor | F13: Corporate | G13: Farhan Dar | H13: Corporate | I13: 11500000 | J13: 204900 | K13: 293808 | L13: 1 | M13: Renewed
A14: ADM-HLT-SKT-2024-2009 | B14: 45536 | C14: Sialkot | D14: Central | E14: Health | F14: Direct | G14: Sobia Naz | H14: Corporate | I14: 6800000 | J14: 145900 | K14: 101845 | L14: 1 | M14: Lapsed
A15: ADM-MSC-RWP-2024-2010 | B15: 45573 | C15: Rawalpindi | D15: North | E15: Miscellaneous | F15: Agency | G15: Junaid Akram | H15: Individual | I15: 1200000 | J15: 20000 | K15: 15603 | L15: 1 | M15: Cancelled
A16: ADM-MAR-KHI-2024-2011 | B16: 45611 | C16: Karachi Main | D16: South | E16: Marine Cargo | F16: Bancassurance | G16: Hamid Raza | H16: Corporate | I16: 47000000 | J16: 716000 | K16: 109689 | L16: 1 | M16: Active
A17: ADM-ENG-LHR-2024-2012 | B17: 45648 | C17: Lahore Gulberg | D17: Central | E17: Engineering | F17: Corporate | G17: Nimra Saleem | H17: Corporate | I17: 28000000 | J17: 722600 | K17: 919063 | L17: 1 | M17: Active
... A125: ADM-MTR-RWP-2024-2120 | B125: 45648 | C125: Rawalpindi | D125: North | E125: Motor | F125: Corporate | G125: Nimra Saleem | H125: Corporate | I125: 6800000 | J125: 111000 | K125: 91930 | L125: 1 | M125: Cancelled
A127: Note: This is simulated training data modelled on Adamjee Assurance general insurance operations. It is not actual company data.

Sheet 3.2 Report
A1: ADAMJEE ASSURANCE COMPANY LIMITED
A2: Quarterly Premium Report from 120 daily transactions
A3: Prepared for: | B3: Chief Financial Officer
A4: Prepared by:
A5: Reporting date: | B5: As at reporting date shown on the dataset
A7: The transaction register holds a separate date for every policy. The quarterly report is currently produced by adding a helper column of quarter labels, which a different analyst rebuilds each quarter and which was wrong for two weeks in July.
A9: Source data: '3.2 Data' (click to open)
A11: DELIVERABLE CHECKLIST
A12: # | B12: Deliverable | C12: Report specification | D12: Requested by | E12: Done?
A13: 1 | B13: Quarterly Premium Report from 120 daily transactions | C13: A quarterly report: Year and Quarter on rows, Gross Premium and Policy Count as values, produced by grouping inside the pivot with no helper column. Months shown when a quarter is expanded. | D13: Chief Financial Officer
A14: 2 | B14: Sum Insured Band Distribution for the reinsurance submission | C14: A band distribution: sum insured grouped in bands of PKR 10 million, showing policy count, total sum insured and total premium per band, with the band structure changeable in seconds. | D14: Head of Reinsurance
A15: 3 | B15: Regional grouping without a region column | C15: A pivot with those three branches manually grouped into a renamed 'South Region' line, alongside the remaining branches, with premium and claims. | D15: Regional Head — South
A16: 4 | B16: Weekly bucketing for the claims surge review | C16: A seven-day bucketed report starting 1 January 2024 showing claims count and value per bucket, with the three heaviest buckets identified. | D16: Head of Claims Operations
A17: 5 | B17: Defect note — why grouping failed on the branch file | C17: A defect note stating the one condition that makes date grouping fail, how to identify the offending rows in the source, and the correct fix. Also state how to report on a July-start financial year, which grouping cannot do. | D17: Head of MIS
A19: BUILD YOUR REPORT / OUTPUT BELOW (pivot, chart, macro output, or model — as required above)
A35: HOW TO WORK: build the requested output in the blank area above (or insert a pivot table / chart / macro-driven control here), tick each deliverable off in the checklist, and record any formula or setting worth remembering in the specification column.

Sheet 3.3 Data
A1: Dataset 3.3 — Show Values As (% of Grand Total, % of Parent, Running Total, Difference From)
A2: Session 3: Advanced Pivot Tables, Power Query & What-If Analysis | Part A: Advanced Pivot Tables | Adamjee Assurance Company Limited (Pakistan) — training data, figures in PKR
A4: Table A — Policy transaction register 2024 (120 rows — the pivot source)
A5: Policy No | B5: Booking Date | C5: Branch | D5: Region | E5: Product | F5: Channel | G5: Agent Name | H5: Client Type | I5: Sum Insured (PKR) | J5: Gross Premium (PKR) | K5: Claims Paid (PKR) | L5: Policy Count | M5: Policy Status
A6: ADM-MTR-KHI-2024-2001 | B6: 45292 | C6: Karachi Main | D6: South | E6: Motor | F6: Direct | G6: Tariq Jameel | H6: Individual | I6: 3400000 | J6: 33200 | K6: 52907 | L6: 1 | M6: Active
A7: ADM-HLT-LHR-2024-2002 | B7: 45330 | C7: Lahore Gulberg | D7: Central | E7: Health | F7: Agency | G7: Nadia Hassan | H7: Corporate | I7: 1200000 | J7: 15300 | K7: 3207 | L7: 1 | M7: Active
A8: ADM-MSC-ISB-2024-2003 | B8: 45366 | C8: Islamabad Blue Area | D8: North | E8: Miscellaneous | F8: Bancassurance | G8: Salman Shah | H8: Corporate | I8: 11500000 | J8: 206100 | K8: 260673 | L8: 1 | M8: Renewed
A9: ADM-MAR-FSD-2024-2004 | B9: 45404 | C9: Faisalabad | D9: Central | E9: Marine Cargo | F9: Corporate | G9: Komal Bashir | H9: Individual | I9: 47000000 | J9: 1335500 | K9: 125902 | L9: 1 | M9: Lapsed
A10: ADM-ENG-MUL-2024-2005 | B10: 45413 | C10: Multan | D10: Central | E10: Engineering | F10: Direct | G10: Waqar Younis Khan | H10: Corporate | I10: 1200000 | J10: 14500 | K10: 20595 | L10: 1 | M10: Cancelled
A11: ADM-FIR-PEW-2024-2006 | B11: 45451 | C11: Peshawar | D11: North | E11: Fire & Property | F11: Agency | G11: Amna Zubair | H11: Corporate | I11: 72000000 | J11: 1519000 | K11: 2506397 | L11: 1 | M11: Active
A12: ADM-TRV-QTA-2024-2007 | B12: 45488 | C12: Quetta | D12: South | E12: Travel | F12: Bancassurance | G12: Rizwan Ali Soomro | H12: Individual | I12: 1200000 | J12: 23900 | K12: 3819 | L12: 1 | M12: Active
A13: ADM-MTR-HYD-2024-2008 | B13: 45526 | C13: Hyderabad | D13: South | E13: Motor | F13: Corporate | G13: Farhan Dar | H13: Corporate | I13: 11500000 | J13: 204900 | K13: 293808 | L13: 1 | M13: Renewed
A14: ADM-HLT-SKT-2024-2009 | B14: 45536 | C14: Sialkot | D14: Central | E14: Health | F14: Direct | G14: Sobia Naz | H14: Corporate | I14: 6800000 | J14: 145900 | K14: 101845 | L14: 1 | M14: Lapsed
A15: ADM-MSC-RWP-2024-2010 | B15: 45573 | C15: Rawalpindi | D15: North | E15: Miscellaneous | F15: Agency | G15: Junaid Akram | H15: Individual | I15: 1200000 | J15: 20000 | K15: 15603 | L15: 1 | M15: Cancelled
A16: ADM-MAR-KHI-2024-2011 | B16: 45611 | C16: Karachi Main | D16: South | E16: Marine Cargo | F16: Bancassurance | G16: Hamid Raza | H16: Corporate | I16: 47000000 | J16: 716000 | K16: 109689 | L16: 1 | M16: Active
A17: ADM-ENG-LHR-2024-2012 | B17: 45648 | C17: Lahore Gulberg | D17: Central | E17: Engineering | F17: Corporate | G17: Nimra Saleem | H17: Corporate | I17: 28000000 | J17: 722600 | K17: 919063 | L17: 1 | M17: Active
... A125: ADM-MTR-RWP-2024-2120 | B125: 45648 | C125: Rawalpindi | D125: North | E125: Motor | F125: Corporate | G125: Nimra Saleem | H125: Corporate | I125: 6800000 | J125: 111000 | K125: 91930 | L125: 1 | M125: Cancelled
A127: Note: This is simulated training data modelled on Adamjee Assurance general insurance operations. It is not actual company data.

Sheet 3.3 Report
A1: ADAMJEE ASSURANCE COMPANY LIMITED
A2: Share-of-Book report for the Regional Heads
A3: Prepared for: | B3: Regional Head — North
A4: Prepared by:
A5: Reporting date: | B5: As at reporting date shown on the dataset
A7: The pack is entirely in rupees and the Regional Head's standing complaint is that he cannot tell who is growing and who is merely large. Percentages are currently added in cells beside the pivot and break whenever the pivot is filtered.
A9: Source data: '3.3 Data' (click to open)
A11: DELIVERABLE CHECKLIST
A12: # | B12: Deliverable | C12: Report specification | D12: Requested by | E12: Done?
A13: 1 | B13: Share-of-Book report for the Regional Heads | C13: A pivot with Region and Branch nested on rows showing: Gross Premium in rupees, as a per cent of the grand total, and as a per cent of the parent region. All three from the same pivot, with the value headings renamed into business language. | D13: Regional Head — North
A14: 2 | B14: Cumulative Premium Position for the seasonality discussion | C14: A monthly pivot showing premium, running total across the year, and running total as a per cent of the annual book, so the half-way month is immediately visible. | D14: Chief Financial Officer
A15: 3 | B15: Month-on-Month Movement pack | C15: A pivot showing premium by month with Difference From previous month in rupees and as a percentage, for the whole company and expandable to branch level. | D15: Head of Management Reporting
A16: 4 | B16: Branch ranking and product benchmarking | C16: Two views: branches ranked largest to smallest by premium inside the pivot, and each product's premium expressed as a difference from the Motor line. | D16: Chief Underwriting Officer
A18: BUILD YOUR REPORT / OUTPUT BELOW (pivot, chart, macro output, or model — as required above)
A34: HOW TO WORK: build the requested output in the blank area above (or insert a pivot table / chart / macro-driven control here), tick each deliverable off in the checklist, and record any formula or setting worth remembering in the specification column.

Sheet 3.4 Data
A1: Dataset 3.4 — Slicers and Timelines Connected to Multiple Pivot Tables
A2: Session 3: Advanced Pivot Tables, Power Query & What-If Analysis | Part A: Advanced Pivot Tables | Adamjee Assurance Company Limited (Pakistan) — training data, figures in PKR
A4: Table A — Policy transaction register 2024 (120 rows — the pivot source)
A5: Policy No | B5: Booking Date | C5: Branch | D5: Region | E5: Product | F5: Channel | G5: Agent Name | H5: Client Type | I5: Sum Insured (PKR) | J5: Gross Premium (PKR) | K5: Claims Paid (PKR) | L5: Policy Count | M5: Policy Status
A6: ADM-MTR-KHI-2024-2001 | B6: 45292 | C6: Karachi Main | D6: South | E6: Motor | F6: Direct | G6: Tariq Jameel | H6: Individual | I6: 3400000 | J6: 33200 | K6: 52907 | L6: 1 | M6: Active
A7: ADM-HLT-LHR-2024-2002 | B7: 45330 | C7: Lahore Gulberg | D7: Central | E7: Health | F7: Agency | G7: Nadia Hassan | H7: Corporate | I7: 1200000 | J7: 15300 | K7: 3207 | L7: 1 | M7: Active
A8: ADM-MSC-ISB-2024-2003 | B8: 45366 | C8: Islamabad Blue Area | D8: North | E8: Miscellaneous | F8: Bancassurance | G8: Salman Shah | H8: Corporate | I8: 11500000 | J8: 206100 | K8: 260673 | L8: 1 | M8: Renewed
A9: ADM-MAR-FSD-2024-2004 | B9: 45404 | C9: Faisalabad | D9: Central | E9: Marine Cargo | F9: Corporate | G9: Komal Bashir | H9: Individual | I9: 47000000 | J9: 1335500 | K9: 125902 | L9: 1 | M9: Lapsed
A10: ADM-ENG-MUL-2024-2005 | B10: 45413 | C10: Multan | D10: Central | E10: Engineering | F10: Direct | G10: Waqar Younis Khan | H10: Corporate | I10: 1200000 | J10: 14500 | K10: 20595 | L10: 1 | M10: Cancelled
A11: ADM-FIR-PEW-2024-2006 | B11: 45451 | C11: Peshawar | D11: North | E11: Fire & Property | F11: Agency | G11: Amna Zubair | H11: Corporate | I11: 72000000 | J11: 1519000 | K11: 2506397 | L11: 1 | M11: Active
A12: ADM-TRV-QTA-2024-2007 | B12: 45488 | C12: Quetta | D12: South | E12: Travel | F12: Bancassurance | G12: Rizwan Ali Soomro | H12: Individual | I12: 1200000 | J12: 23900 | K12: 3819 | L12: 1 | M12: Active
A13: ADM-MTR-HYD-2024-2008 | B13: 45526 | C13: Hyderabad | D13: South | E13: Motor | F13: Corporate | G13: Farhan Dar | H13: Corporate | I13: 11500000 | J13: 204900 | K13: 293808 | L13: 1 | M13: Renewed
A14: ADM-HLT-SKT-2024-2009 | B14: 45536 | C14: Sialkot | D14: Central | E14: Health | F14: Direct | G14: Sobia Naz | H14: Corporate | I14: 6800000 | J14: 145900 | K14: 101845 | L14: 1 | M14: Lapsed
A15: ADM-MSC-RWP-2024-2010 | B15: 45573 | C15: Rawalpindi | D15: North | E15: Miscellaneous | F15: Agency | G15: Junaid Akram | H15: Individual | I15: 1200000 | J15: 20000 | K15: 15603 | L15: 1 | M15: Cancelled
A16: ADM-MAR-KHI-2024-2011 | B16: 45611 | C16: Karachi Main | D16: South | E16: Marine Cargo | F16: Bancassurance | G16: Hamid Raza | H16: Corporate | I16: 47000000 | J16: 716000 | K16: 109689 | L16: 1 | M16: Active
A17: ADM-ENG-LHR-2024-2012 | B17: 45648 | C17: Lahore Gulberg | D17: Central | E17: Engineering | F17: Corporate | G17: Nimra Saleem | H17: Corporate | I17: 28000000 | J17: 722600 | K17: 919063 | L17: 1 | M17: Active
... A125: ADM-MTR-RWP-2024-2120 | B125: 45648 | C125: Rawalpindi | D125: North | E125: Motor | F125: Corporate | G125: Nimra Saleem | H125: Corporate | I125: 6800000 | J125: 111000 | K125: 91930 | L125: 1 | M125: Cancelled
A127: Note: This is simulated training data modelled on Adamjee Assurance general insurance operations. It is not actual company data.

Sheet 3.4 Report
A1: ADAMJEE ASSURANCE COMPANY LIMITED
A2: Executive Committee Dashboard — one page, three pivots
A3: Prepared for: | B3: Chief Executive's office
A4: Prepared by:
A5: Reporting date: | B5: As at reporting date shown on the dataset
A7: The Committee pack has three pivots on one page, each with its own report filter. In the last meeting the premium pivot was filtered to Q3 and the claims pivot to the full year, and the Committee spent twenty minutes discussing a loss ratio that did not exist.
A9: Source data: '3.4 Data' (click to open)
A11: DELIVERABLE CHECKLIST
A12: # | B12: Deliverable | C12: Report specification | D12: Requested by | E12: Done?
A13: 1 | B13: Executive Committee Dashboard — one page, three pivots | C13: A single dashboard page with three pivots — premium by branch, claims by product, policy count by channel — all driven by one shared set of controls so they can never show different periods. | D13: Chief Executive's office
A14: 2 | B14: Period control on the dashboard | C14: A Timeline on the booking date connected to all three pivots, set to quarters, with evidence that selecting Q3 2024 moves every pivot on the page together. | D14: Chief Executive's office
A15: 3 | B15: Dashboard layout and finishing | C15: The finished dashboard header: slicers arranged in two columns, a consistent style applied, and items with no data hidden. Screenshot or description of the layout in the yellow box. | D15: Head of Management Reporting
A16: 4 | B16: Protecting the dashboard from its users | C16: The dashboard protected so users can operate the slicers and timeline but cannot move, resize or delete them, with the protection settings recorded. | D16: Head of MIS
A18: BUILD YOUR REPORT / OUTPUT BELOW (pivot, chart, macro output, or model — as required above)
A34: HOW TO WORK: build the requested output in the blank area above (or insert a pivot table / chart / macro-driven control here), tick each deliverable off in the checklist, and record any formula or setting worth remembering in the specification column.

Sheet 3.5 Data
A1: Dataset 3.5 — Pivot Table from Multiple Sheets Using Consolidation
A2: Session 3: Advanced Pivot Tables, Power Query & What-If Analysis | Part A: Advanced Pivot Tables | Adamjee Assurance Company Limited (Pakistan) — training data, figures in PKR
A4: Block 1 — KARACHI MAIN (treat this as its own sheet)
A5: Month | B5: Motor | C5: Fire & Property | D5: Marine Cargo | E5: Health | F5: Engineering
A6: Jan-2024 | B6: 4200000 | C6: 3100000 | D6: 2650000 | E6: 1450000 | F6: 980000
A7: Feb-2024 | B7: 4380000 | C7: 3195000 | D7: 2710000 | E7: 1492000 | F7: 1011000
A8: Mar-2024 | B8: 4560000 | C8: 3290000 | D8: 2770000 | E8: 1534000 | F8: 1042000
A9: Apr-2024 | B9: 4740000 | C9: 3385000 | D9: 2830000 | E9: 1576000 | F9: 1073000
A10: May-2024 | B10: 4920000 | C10: 3480000 | D10: 2890000 | E10: 1618000 | F10: 1104000
A11: Jun-2024 | B11: 5100000 | C11: 3575000 | D11: 2950000 | E11: 1660000 | F11: 1135000
A12: Jul-2024 | B12: 5280000 | C12: 3670000 | D12: 3010000 | E12: 1702000 | F12: 1166000
A13: Aug-2024 | B13: 5460000 | C13: 3765000 | D13: 3070000 | E13: 1744000 | F13: 1197000
A14: Sep-2024 | B14: 5640000 | C14: 3860000 | D14: 3130000 | E14: 1786000 | F14: 1228000
A15: Oct-2024 | B15: 5820000 | C15: 3955000 | D15: 3190000 | E15: 1828000 | F15: 1259000
A16: Nov-2024 | B16: 6000000 | C16: 4050000 | D16: 3250000 | E16: 1870000 | F16: 1290000
A17: Dec-2024 | B17: 6180000 | C17: 4145000 | D17: 3310000 | E17: 1912000 | F17: 1321000
A19: Block 2 — LAHORE GULBERG
A20: Month | B20: Motor | C20: Fire & Property | D20: Marine Cargo | E20: Health | F20: Engineering
A21: Jan-2024 | B21: 2900000 | C21: 2450000 | D21: 1150000 | E21: 1980000 | F21: 1320000
A22: Feb-2024 | B22: 3020000 | C22: 2538000 | D22: 1176000 | E22: 2035000 | F22: 1364000
A23: Mar-2024 | B23: 3140000 | C23: 2626000 | D23: 1202000 | E23: 2090000 | F23: 1408000
A24: Apr-2024 | B24: 3260000 | C24: 2714000 | D24: 1228000 | E24: 2145000 | F24: 1452000
A25: May-2024 | B25: 3380000 | C25: 2802000 | D25: 1254000 | E25: 2200000 | F25: 1496000
A26: Jun-2024 | B26: 3500000 | C26: 2890000 | D26: 1280000 | E26: 2255000 | F26: 1540000
A27: Jul-2024 | B27: 3620000 | C27: 2978000 | D27: 1306000 | E27: 2310000 | F27: 1584000
A28: Aug-2024 | B28: 3740000 | C28: 3066000 | D28: 1332000 | E28: 2365000 | F28: 1628000
A29: Sep-2024 | B29: 3860000 | C29: 3154000 | D29: 1358000 | E29: 2420000 | F29: 1672000
A30: Oct-2024 | B30: 3980000 | C30: 3242000 | D30: 1384000 | E30: 2475000 | F30: 1716000
A31: Nov-2024 | B31: 4100000 | C31: 3330000 | D31: 1410000 | E31: 2530000 | F31: 1760000
A32: Dec-2024 | B32: 4220000 | C32: 3418000 | D32: 1436000 | E32: 2585000 | F32: 1804000
A34: Block 3 — ISLAMABAD BLUE AREA
A35: Month | B35: Motor | C35: Fire & Property | D35: Marine Cargo | E35: Health | F35: Engineering
A36: Jan-2024 | B36: 1650000 | C36: 1320000 | D36: 420000 | E36: 2240000 | F36: 760000
A37: Feb-2024 | B37: 1724000 | C37: 1371000 | D37: 431000 | E37: 2308000 | F37: 782000
A38: Mar-2024 | B38: 1798000 | C38: 1422000 | D38: 442000 | E38: 2376000 | F38: 804000
A39: Apr-2024 | B39: 1872000 | C39: 1473000 | D39: 453000 | E39: 2444000 | F39: 826000
A40: May-2024 | B40: 1946000 | C40: 1524000 | D40: 464000 | E40: 2512000 | F40: 848000
A41: Jun-2024 | B41: 2020000 | C41: 1575000 | D41: 475000 | E41: 2580000 | F41: 870000
A42: Jul-2024 | B42: 2094000 | C42: 1626000 | D42: 486000 | E42: 2648000 | F42: 892000
A43: Aug-2024 | B43: 2168000 | C43: 1677000 | D43: 497000 | E43: 2716000 | F43: 914000
A44: Sep-2024 | B44: 2242000 | C44: 1728000 | D44: 508000 | E44: 2784000 | F44: 936000
A45: Oct-2024 | B45: 2316000 | C45: 1779000 | D45: 519000 | E45: 2852000 | F45: 958000
A46: Nov-2024 | B46: 2390000 | C46: 1830000 | D46: 530000 | E46: 2920000 | F46: 980000
A47: Dec-2024 | B47: 2464000 | C47: 1881000 | D47: 541000 | E47: 2988000 | F47: 1002000
A49: Note: This is simulated training data modelled on Adamjee Assurance general insurance operations. It is not actual company data.

Sheet 3.5 Report
A1: ADAMJEE ASSURANCE COMPANY LIMITED
A2: Consolidated Regional Report from three branch files
A3: Prepared for: | B3: Regional Head — Central
A4: Prepared by:
A5: Reporting date: | B5: As at reporting date shown on the dataset
A7: Three branches still send separate monthly files with identical layouts. The consolidation is done by copying each into a master and adding the blocks, which takes a morning and produced a double-counted Karachi block in April.
A9: Source data: '3.5 Data' (click to open)
A11: DELIVERABLE CHECKLIST
A12: # | B12: Deliverable | C12: Report specification | D12: Requested by | E12: Done?
A13: 1 | B13: Consolidated Regional Report from three branch files | C13: A consolidated pivot built from the three blocks using the Multiple Consolidation Ranges wizard, with a page field naming each branch so the consolidation can be filtered back to any single branch. | D13: Regional Head — Central
A14: 2 | B14: Reconciliation before the pack is issued | C14: A reconciliation block: total per the consolidated pivot | sum of the three branch blocks | difference, which must be zero, with the branch-by-branch figures shown. | D14: Head of Internal Audit
A15: 3 | B15: Readable field names for the Regional Head | C15: The consolidated pivot with fields renamed to Month, Product and Branch, and the value field renamed to Premium. | D15: Regional Head — Central
A16: 4 | B16: Method recommendation for next month | C16: A two-line recommendation comparing the consolidation wizard against a Power Query Append for this job, naming two limitations of the wizard and stating which you would ship for next month end. | D16: Head of MIS
A18: BUILD YOUR REPORT / OUTPUT BELOW (pivot, chart, macro output, or model — as required above)
A34: HOW TO WORK: build the requested output in the blank area above (or insert a pivot table / chart / macro-driven control here), tick each deliverable off in the checklist, and record any formula or setting worth remembering in the specification column.

Sheet 3.6 Data
A1: Dataset 3.6 — Conditional Formatting Applied to Pivot Tables
A2: Session 3: Advanced Pivot Tables, Power Query & What-If Analysis | Part A: Advanced Pivot Tables | Adamjee Assurance Company Limited (Pakistan) — training data, figures in PKR
A4: Table A — Policy transaction register 2024 (120 rows — the pivot source)
A5: Policy No | B5: Booking Date | C5: Branch | D5: Region | E5: Product | F5: Channel | G5: Agent Name | H5: Client Type | I5: Sum Insured (PKR) | J5: Gross Premium (PKR) | K5: Claims Paid (PKR) | L5: Policy Count | M5: Policy Status
A6: ADM-MTR-KHI-2024-2001 | B6: 45292 | C6: Karachi Main | D6: South | E6: Motor | F6: Direct | G6: Tariq Jameel | H6: Individual | I6: 3400000 | J6: 33200 | K6: 52907 | L6: 1 | M6: Active
A7: ADM-HLT-LHR-2024-2002 | B7: 45330 | C7: Lahore Gulberg | D7: Central | E7: Health | F7: Agency | G7: Nadia Hassan | H7: Corporate | I7: 1200000 | J7: 15300 | K7: 3207 | L7: 1 | M7: Active
A8: ADM-MSC-ISB-2024-2003 | B8: 45366 | C8: Islamabad Blue Area | D8: North | E8: Miscellaneous | F8: Bancassurance | G8: Salman Shah | H8: Corporate | I8: 11500000 | J8: 206100 | K8: 260673 | L8: 1 | M8: Renewed
A9: ADM-MAR-FSD-2024-2004 | B9: 45404 | C9: Faisalabad | D9: Central | E9: Marine Cargo | F9: Corporate | G9: Komal Bashir | H9: Individual | I9: 47000000 | J9: 1335500 | K9: 125902 | L9: 1 | M9: Lapsed
A10: ADM-ENG-MUL-2024-2005 | B10: 45413 | C10: Multan | D10: Central | E10: Engineering | F10: Direct | G10: Waqar Younis Khan | H10: Corporate | I10: 1200000 | J10: 14500 | K10: 20595 | L10: 1 | M10: Cancelled
A11: ADM-FIR-PEW-2024-2006 | B11: 45451 | C11: Peshawar | D11: North | E11: Fire & Property | F11: Agency | G11: Amna Zubair | H11: Corporate | I11: 72000000 | J11: 1519000 | K11: 2506397 | L11: 1 | M11: Active
A12: ADM-TRV-QTA-2024-2007 | B12: 45488 | C12: Quetta | D12: South | E12: Travel | F12: Bancassurance | G12: Rizwan Ali Soomro | H12: Individual | I12: 1200000 | J12: 23900 | K12: 3819 | L12: 1 | M12: Active
A13: ADM-MTR-HYD-2024-2008 | B13: 45526 | C13: Hyderabad | D13: South | E13: Motor | F13: Corporate | G13: Farhan Dar | H13: Corporate | I13: 11500000 | J13: 204900 | K13: 293808 | L13: 1 | M13: Renewed
A14: ADM-HLT-SKT-2024-2009 | B14: 45536 | C14: Sialkot | D14: Central | E14: Health | F14: Direct | G14: Sobia Naz | H14: Corporate | I14: 6800000 | J14: 145900 | K14: 101845 | L14: 1 | M14: Lapsed
A15: ADM-MSC-RWP-2024-2010 | B15: 45573 | C15: Rawalpindi | D15: North | E15: Miscellaneous | F15: Agency | G15: Junaid Akram | H15: Individual | I15: 1200000 | J15: 20000 | K15: 15603 | L15: 1 | M15: Cancelled
A16: ADM-MAR-KHI-2024-2011 | B16: 45611 | C16: Karachi Main | D16: South | E16: Marine Cargo | F16: Bancassurance | G16: Hamid Raza | H16: Corporate | I16: 47000000 | J16: 716000 | K16: 109689 | L16: 1 | M16: Active
A17: ADM-ENG-LHR-2024-2012 | B17: 45648 | C17: Lahore Gulberg | D17: Central | E17: Engineering | F17: Corporate | G17: Nimra Saleem | H17: Corporate | I17: 28000000 | J17: 722600 | K17: 919063 | L17: 1 | M17: Active
... A125: ADM-MTR-RWP-2024-2120 | B125: 45648 | C125: Rawalpindi | D125: North | E125: Motor | F125: Corporate | G125: Nimra Saleem | H125: Corporate | I125: 6800000 | J125: 111000 | K125: 91930 | L125: 1 | M125: Cancelled
A127: Table B — Scorecard thresholds
A128: Measure | B128: Green | C128: Amber | D128: Red
A129: Loss Ratio | B129: below 50% | C129: 50% to 65% | D129: above 65%
A130: Premium growth | B130: above 10% | C130: 0% to 10% | D130: negative
A131: Policy count | B131: above 40 | C131: 20 to 40 | D131: below 20
A133: Note: This is simulated training data modelled on Adamjee Assurance general insurance operations. It is not actual company data.

Sheet 3.6 Report
A1: ADAMJEE ASSURANCE COMPANY LIMITED
A2: Branch Scorecard readable in five seconds
A3: Prepared for: | B3: Regional Head — South
A4: Prepared by:
A5: Reporting date: | B5: As at reporting date shown on the dataset
A7: The scorecard is read on a phone before the Monday call. In its current form it is a block of numbers and the Regional Head has said he stops reading after the third row.
A9: Source data: '3.6 Data' (click to open)
A11: DELIVERABLE CHECKLIST
A12: # | B12: Deliverable | C12: Report specification | D12: Requested by | E12: Done?
A13: 1 | B13: Branch Scorecard readable in five seconds | C13: A scorecard pivot with Branch on rows showing premium, claims, policy count and loss ratio, formatted so that breached loss ratios, top premium branches and relative policy volumes are visible without reading a single number. | D13: Regional Head — South
A14: 2 | B14: Threshold-based traffic lights, not percentiles | C14: The loss ratio column with an icon set driven by the published numeric thresholds rather than percentiles, and the thresholds documented beside the scorecard. | D14: Chief Underwriting Officer
A15: 3 | B15: Whole-row highlighting for breached branches | C15: A formula-based rule shading the entire row where the loss ratio exceeds 65%, plus a Top 10 Items rule highlighting the three largest branches by premium. | D15: Regional Head — South
A16: 4 | B16: Refresh survival test | C16: Evidence that the formatting survives: record the scope option chosen for each rule, refresh the pivot after changing the source, and confirm every rule still applies. | D16: Head of MIS
